Workbook
Name BANCO: Tabla10[BANCO]
Name BANCO: Tabla10[BANCO]
Name Concepto: 'MGZ121'!$J$2:$J$110
Name EMPRESA: INDICE!#REF!
Name ESTADO: METODO[ESTADO]
Name ESTADO: METODO[ESTADO]
Name Familia: INDICE!$H$1:$H$8
Name Gasto: INDICE!$G$2:$G$4
Name Ingreso: INDICE!$F$2:$F$10
Name Inicial: INDICE!$R$2
Name TIPO: INDICE!$C$2:$C$4

Sheet ENE25
B1: ENERO
B2: CONCEPTOS | C2: MGZ121 | D2: MGZ BBVA | E2: MGZ DOLARES | F2: MGZ BAJIO | G2: VICTOR BANAMEX | H2: VICTOR BANORTE | I2: RODRIGO | J2: MOY | K2: NORMA RUTH | L2: VALERIA | M2: MANUEL BANAMEX | N2: ROBERTO | O2: JUAN | P2: NORMA SANCHEZ | Q2: JOSE CARLOS | R2: LUIS ENRIQUE | S2: CESARIA | T2: ALAN | U2: ELVIA | V2: CAJA | W2: CAJA TIGRES | X2: RESERVA | Y2: TOTALES | Z2: ACUMULADO
B3: ENTRADAS
B4: INGRESOS
A5: 11.1 | B5: VENTA PIÑAS | C5: =IFERROR(SUMIFS('MGZ121'!$M$2:'MGZ121'!$M$175,'MGZ121'!$H$2:$H$175,"ENTRADA",'MGZ121'!$J$2:$J$175,$B5),0) -> 6887540 | D5: =IFERROR(SUMIFS('MGZ BBVA'!$M$2:$M$88,'MGZ BBVA'!$H$2:$H$88,"ENTRADA",'MGZ BBVA'!$J$2:$J$88,$B5),0) -> 2018660 | E5: =IFERROR(SUMIFS('MGZ DOLARES'!$M$2:$M$2,'MGZ DOLARES'!$F$2:$F$2,"ENTRADA",'MGZ DOLARES'!$J$2:$J$2,$B5),0) -> 0 | F5: =IFERROR(SUMIFS('MGZ BAJIO'!$M$2:$M$4,'MGZ BAJIO'!$H$2:$H$4,"ENTRADA",'MGZ BAJIO'!$J$2:$J$4,$B5),0) -> 0 | G5: =IFERROR(SUMIFS('VICTOR BANAMEX'!$M$2:$M$65,'VICTOR BANAMEX'!$H$2:$H$65,"ENTRADA",'VICTOR BANAMEX'!$J$2:$J$65,$B5),0) -> 0 | H5: =IFERROR(SUMIFS('VICTOR BANORTE'!$M$2:$M$9,'VICTOR BANORTE'!$H$2:$H$9,"ENTRADA",'VICTOR BANORTE'!$J$2:$J$9,$B5),0) -> 0 | I5: =IFERROR(SUMIFS(RODRIGO!$M$2:$M$2,RODRIGO!$H$2:$H$2,"ENTRADA",RODRIGO!$J$2:$J$2,$B5),0) -> 0 | J5: =IFERROR(SUMIFS(MOY!$M$2:$M$12,MOY!$H$2:$H$12,"ENTRADA",MOY!$J$2:$J$12,$B5),0) -> 0 | K5: =IFERROR(SUMIFS('NORMA RUTH'!$M$2:$M$12,'NORMA RUTH'!$H$2:$H$12,"ENTRADA",'NORMA RUTH'!$J$2:$J$12,$B5),0) -> 70000 | L5: =IFERROR(SUMIFS(VALERIA!$M$2:$M$10,VALERIA!$H$2:$H$10,"ENTRADA",VALERIA!$J$2:$J$10,$B5),0) -> 0 | M5: =IFERROR(SUMIFS('MANUEL BANAMEX'!$M$2:$M$25,'MANUEL BANAMEX'!$H$2:$H$25,"ENTRADA",'MANUEL BANAMEX'!$J$2:$J$25,$B5),0) -> 0 | N5: =IFERROR(SUMIFS(ROBERTO!$M$2:$M$2,ROBERTO!$H$2:$H$2,"ENTRADA",ROBERTO!$J$2:$J$2,$B5),0) -> 0 | O5: =IFERROR(SUMIFS(JUAN!$M$2:$M$11,JUAN!$H$2:$H$11,"ENTRADA",JUAN!$J$2:$J$11,$B5),0) -> 0 | P5: =IFERROR(SUMIFS('NORMA SANCHEZ'!$M$2:$M$14,'NORMA SANCHEZ'!$H$2:$H$14,"ENTRADA",'NORMA SANCHEZ'!$J$2:$J$14,$B5),0) -> 0 | Q5: =IFERROR(SUMIFS('JOSE CARLOS'!$M$2:$M$16,'JOSE CARLOS'!$H$2:$H$16,"ENTRADA",'JOSE CARLOS'!$J$2:$J$16,$B5),0) -> 0 | R5: =IFERROR(SUMIFS('LUIS ENRIQUE '!$M$2:$M$21,'LUIS ENRIQUE '!$H$2:$H$21,"ENTRADA",'LUIS ENRIQUE '!$J$2:$J$21,$B5),0) -> 0 | S5: =IFERROR(SUMIFS(CESARIA!$M$2:$M$15,CESARIA!$H$2:$H$15,"ENTRADA",CESARIA!$J$2:$J$15,$B5),0) -> 0 | T5: =IFERROR(SUMIFS(ALAN!$M$2:$M$14,ALAN!$H$2:$H$14,"ENTRADA",ALAN!$J$2:$J$14,$B5),0) -> 0 | U5: =IFERROR(SUMIFS(ELVIA!$M$2:$M$6,ELVIA!$H$2:$H$6,"ENTRADA",ELVIA!$J$2:$J$6,$B5),0) -> 0 | V5: =IFERROR(SUMIFS(CAJA!$M$2:$M$586,CAJA!$H$2:$H$586,"ENTRADA",CAJA!$J$2:$J$586,$B5),0) -> 1050602 | W5: =IFERROR(SUMIFS('CAJA TIGRES'!$M$2:$M$139,'CAJA TIGRES'!$H$2:$H$139,"ENTRADA",'CAJA TIGRES'!$J$2:$J$139,$B5),0) -> 0 | X5: =IFERROR(SUMIFS(RESERVA!$M$2:$M$2,RESERVA!$H$2:$H$2,"ENTRADA",RESERVA!$J$2:$J$2,$B5),0) -> 0 | Y5: =SUM(C5:X5) -> 10026802 | Z5: =Y5 -> 10026802
A6: 11.2 | B6: VENTA GANADO | C6: =IFERROR(SUMIFS('MGZ121'!$M$2:'MGZ121'!$M$175,'MGZ121'!$H$2:$H$175,"ENTRADA",'MGZ121'!$J$2:$J$175,$B6),0) -> 0 | D6: =IFERROR(SUMIFS('MGZ BBVA'!$M$2:$M$88,'MGZ BBVA'!$H$2:$H$88,"ENTRADA",'MGZ BBVA'!$J$2:$J$88,$B6),0) -> 0 | E6: =IFERROR(SUMIFS('MGZ DOLARES'!$M$2:$M$2,'MGZ DOLARES'!$F$2:$F$2,"ENTRADA",'MGZ DOLARES'!$J$2:$J$2,$B6),0) -> 0 | F6: =IFERROR(SUMIFS('MGZ BAJIO'!$M$2:$M$4,'MGZ BAJIO'!$H$2:$H$4,"ENTRADA",'MGZ BAJIO'!$J$2:$J$4,$B6),0) -> 0 | G6: =IFERROR(SUMIFS('VICTOR BANAMEX'!$M$2:$M$65,'VICTOR BANAMEX'!$H$2:$H$65,"ENTRADA",'VICTOR BANAMEX'!$J$2:$J$65,$B6),0) -> 0 | H6: =IFERROR(SUMIFS('VICTOR BANORTE'!$M$2:$M$9,'VICTOR BANORTE'!$H$2:$H$9,"ENTRADA",'VICTOR BANORTE'!$J$2:$J$9,$B6),0) -> 0 | I6: =IFERROR(SUMIFS(RODRIGO!$M$2:$M$2,RODRIGO!$H$2:$H$2,"ENTRADA",RODRIGO!$J$2:$J$2,$B6),0) -> 0 | J6: =IFERROR(SUMIFS(MOY!$M$2:$M$12,MOY!$H$2:$H$12,"ENTRADA",MOY!$J$2:$J$12,$B6),0) -> 0 | K6: =IFERROR(SUMIFS('NORMA RUTH'!$M$2:$M$12,'NORMA RUTH'!$H$2:$H$12,"ENTRADA",'NORMA RUTH'!$J$2:$J$12,$B6),0) -> 0 | L6: =IFERROR(SUMIFS(VALERIA!$M$2:$M$10,VALERIA!$H$2:$H$10,"ENTRADA",VALERIA!$J$2:$J$10,$B6),0) -> 0 | M6: =IFERROR(SUMIFS('MANUEL BANAMEX'!$M$2:$M$25,'MANUEL BANAMEX'!$H$2:$H$25,"ENTRADA",'MANUEL BANAMEX'!$J$2:$J$25,$B6),0) -> 0 | N6: =IFERROR(SUMIFS(ROBERTO!$M$2:$M$2,ROBERTO!$H$2:$H$2,"ENTRADA",ROBERTO!$J$2:$J$2,$B6),0) -> 0 | O6: =IFERROR(SUMIFS(JUAN!$M$2:$M$11,JUAN!$H$2:$H$11,"ENTRADA",JUAN!$J$2:$J$11,$B6),0) -> 0 | P6: =IFERROR(SUMIFS('NORMA SANCHEZ'!$M$2:$M$14,'NORMA SANCHEZ'!$H$2:$H$14,"ENTRADA",'NORMA SANCHEZ'!$J$2:$J$14,$B6),0) -> 0 | Q6: =IFERROR(SUMIFS('JOSE CARLOS'!$M$2:$M$16,'JOSE CARLOS'!$H$2:$H$16,"ENTRADA",'JOSE CARLOS'!$J$2:$J$16,$B6),0) -> 0 | R6: =IFERROR(SUMIFS('LUIS ENRIQUE '!$M$2:$M$21,'LUIS ENRIQUE '!$H$2:$H$21,"ENTRADA",'LUIS ENRIQUE '!$J$2:$J$21,$B6),0) -> 0 | S6: =IFERROR(SUMIFS(CESARIA!$M$2:$M$15,CESARIA!$H$2:$H$15,"ENTRADA",CESARIA!$J$2:$J$15,$B6),0) -> 0 | T6: =IFERROR(SUMIFS(ALAN!$M$2:$M$14,ALAN!$H$2:$H$14,"ENTRADA",ALAN!$J$2:$J$14,$B6),0) -> 0 | U6: =IFERROR(SUMIFS(ELVIA!$M$2:$M$6,ELVIA!$H$2:$H$6,"ENTRADA",ELVIA!$J$2:$J$6,$B6),0) -> 0 | V6: =IFERROR(SUMIFS(CAJA!$M$2:$M$586,CAJA!$H$2:$H$586,"ENTRADA",CAJA!$J$2:$J$586,$B6),0) -> 185975 | W6: =IFERROR(SUMIFS('CAJA TIGRES'!$M$2:$M$139,'CAJA TIGRES'!$H$2:$H$139,"ENTRADA",'CAJA TIGRES'!$J$2:$J$139,$B6),0) -> 0 | X6: =IFERROR(SUMIFS(RESERVA!$M$2:$M$2,RESERVA!$H$2:$H$2,"ENTRADA",RESERVA!$J$2:$J$2,$B6),0) -> 0 | Y6: =SUM(C6:X6) -> 185975 | Z6: =Y6 -> 185975
A7: 11.3 | B7: OTROS INGRESOS | C7: =IFERROR(SUMIFS('MGZ121'!$M$2:'MGZ121'!$M$175,'MGZ121'!$H$2:$H$175,"ENTRADA",'MGZ121'!$J$2:$J$175,$B7),0) -> 0 | D7: =IFERROR(SUMIFS('MGZ BBVA'!$M$2:$M$88,'MGZ BBVA'!$H$2:$H$88,"ENTRADA",'MGZ BBVA'!$J$2:$J$88,$B7),0) -> 0 | E7: =IFERROR(SUMIFS('MGZ DOLARES'!$M$2:$M$2,'MGZ DOLARES'!$F$2:$F$2,"ENTRADA",'MGZ DOLARES'!$J$2:$J$2,$B7),0) -> 0 | F7: =IFERROR(SUMIFS('MGZ BAJIO'!$M$2:$M$4,'MGZ BAJIO'!$H$2:$H$4,"ENTRADA",'MGZ BAJIO'!$J$2:$J$4,$B7),0) -> 0 | G7: =IFERROR(SUMIFS('VICTOR BANAMEX'!$M$2:$M$65,'VICTOR BANAMEX'!$H$2:$H$65,"ENTRADA",'VICTOR BANAMEX'!$J$2:$J$65,$B7),0) -> 0 | H7: =IFERROR(SUMIFS('VICTOR BANORTE'!$M$2:$M$9,'VICTOR BANORTE'!$H$2:$H$9,"ENTRADA",'VICTOR BANORTE'!$J$2:$J$9,$B7),0) -> 0 | I7: =IFERROR(SUMIFS(RODRIGO!$M$2:$M$2,RODRIGO!$H$2:$H$2,"ENTRADA",RODRIGO!$J$2:$J$2,$B7),0) -> 0 | J7: =IFERROR(SUMIFS(MOY!$M$2:$M$12,MOY!$H$2:$H$12,"ENTRADA",MOY!$J$2:$J$12,$B7),0) -> 0 | K7: =IFERROR(SUMIFS('NORMA RUTH'!$M$2:$M$12,'NORMA RUTH'!$H$2:$H$12,"ENTRADA",'NORMA RUTH'!$J$2:$J$12,$B7),0) -> 0 | L7: =IFERROR(SUMIFS(VALERIA!$M$2:$M$10,VALERIA!$H$2:$H$10,"ENTRADA",VALERIA!$J$2:$J$10,$B7),0) -> 0 | M7: =IFERROR(SUMIFS('MANUEL BANAMEX'!$M$2:$M$25,'MANUEL BANAMEX'!$H$2:$H$25,"ENTRADA",'MANUEL BANAMEX'!$J$2:$J$25,$B7),0) -> 0 | N7: =IFERROR(SUMIFS(ROBERTO!$M$2:$M$2,ROBERTO!$H$2:$H$2,"ENTRADA",ROBERTO!$J$2:$J$2,$B7),0) -> 0 | O7: =IFERROR(SUMIFS(JUAN!$M$2:$M$11,JUAN!$H$2:$H$11,"ENTRADA",JUAN!$J$2:$J$11,$B7),0) -> 0 | P7: =IFERROR(SUMIFS('NORMA SANCHEZ'!$M$2:$M$14,'NORMA SANCHEZ'!$H$2:$H$14,"ENTRADA",'NORMA SANCHEZ'!$J$2:$J$14,$B7),0) -> 0 | Q7: =IFERROR(SUMIFS('JOSE CARLOS'!$M$2:$M$16,'JOSE CARLOS'!$H$2:$H$16,"ENTRADA",'JOSE CARLOS'!$J$2:$J$16,$B7),0) -> 0 | R7: =IFERROR(SUMIFS('LUIS ENRIQUE '!$M$2:$M$21,'LUIS ENRIQUE '!$H$2:$H$21,"ENTRADA",'LUIS ENRIQUE '!$J$2:$J$21,$B7),0) -> 0 | S7: =IFERROR(SUMIFS(CESARIA!$M$2:$M$15,CESARIA!$H$2:$H$15,"ENTRADA",CESARIA!$J$2:$J$15,$B7),0) -> 0 | T7: =IFERROR(SUMIFS(ALAN!$M$2:$M$14,ALAN!$H$2:$H$14,"ENTRADA",ALAN!$J$2:$J$14,$B7),0) -> 0 | U7: =IFERROR(SUMIFS(ELVIA!$M$2:$M$6,ELVIA!$H$2:$H$6,"ENTRADA",ELVIA!$J$2:$J$6,$B7),0) -> 0 | V7: =IFERROR(SUMIFS(CAJA!$M$2:$M$586,CAJA!$H$2:$H$586,"ENTRADA",CAJA!$J$2:$J$586,$B7),0) -> 0 | W7: =IFERROR(SUMIFS('CAJA TIGRES'!$M$2:$M$139,'CAJA TIGRES'!$H$2:$H$139,"ENTRADA",'CAJA TIGRES'!$J$2:$J$139,$B7),0) -> 0 | X7: =IFERROR(SUMIFS(RESERVA!$M$2:$M$2,RESERVA!$H$2:$H$2,"ENTRADA",RESERVA!$J$2:$J$2,$B7),0) -> 0 | Y7: =SUM(C7:X7) -> 0 | Z7: =Y7 -> 0
A8: 11.4 | B8: CABALLOS | C8: =IFERROR(SUMIFS('MGZ121'!$M$2:'MGZ121'!$M$175,'MGZ121'!$H$2:$H$175,"ENTRADA",'MGZ121'!$J$2:$J$175,$B8),0) -> 0 | D8: =IFERROR(SUMIFS('MGZ BBVA'!$M$2:$M$88,'MGZ BBVA'!$H$2:$H$88,"ENTRADA",'MGZ BBVA'!$J$2:$J$88,$B8),0) -> 0 | E8: =IFERROR(SUMIFS('MGZ DOLARES'!$M$2:$M$2,'MGZ DOLARES'!$F$2:$F$2,"ENTRADA",'MGZ DOLARES'!$J$2:$J$2,$B8),0) -> 0 | F8: =IFERROR(SUMIFS('MGZ BAJIO'!$M$2:$M$4,'MGZ BAJIO'!$H$2:$H$4,"ENTRADA",'MGZ BAJIO'!$J$2:$J$4,$B8),0) -> 0 | G8: =IFERROR(SUMIFS('VICTOR BANAMEX'!$M$2:$M$65,'VICTOR BANAMEX'!$H$2:$H$65,"ENTRADA",'VICTOR BANAMEX'!$J$2:$J$65,$B8),0) -> 0 | H8: =IFERROR(SUMIFS('VICTOR BANORTE'!$M$2:$M$9,'VICTOR BANORTE'!$H$2:$H$9,"ENTRADA",'VICTOR BANORTE'!$J$2:$J$9,$B8),0) -> 0 | I8: =IFERROR(SUMIFS(RODRIGO!$M$2:$M$2,RODRIGO!$H$2:$H$2,"ENTRADA",RODRIGO!$J$2:$J$2,$B8),0) -> 0 | J8: =IFERROR(SUMIFS(MOY!$M$2:$M$12,MOY!$H$2:$H$12,"ENTRADA",MOY!$J$2:$J$12,$B8),0) -> 0 | K8: =IFERROR(SUMIFS('NORMA RUTH'!$M$2:$M$12,'NORMA RUTH'!$H$2:$H$12,"ENTRADA",'NORMA RUTH'!$J$2:$J$12,$B8),0) -> 0 | L8: =IFERROR(SUMIFS(VALERIA!$M$2:$M$10,VALERIA!$H$2:$H$10,"ENTRADA",VALERIA!$J$2:$J$10,$B8),0) -> 0 | M8: =IFERROR(SUMIFS('MANUEL BANAMEX'!$M$2:$M$25,'MANUEL BANAMEX'!$H$2:$H$25,"ENTRADA",'MANUEL BANAMEX'!$J$2:$J$25,$B8),0) -> 0 | N8: =IFERROR(SUMIFS(ROBERTO!$M$2:$M$2,ROBERTO!$H$2:$H$2,"ENTRADA",ROBERTO!$J$2:$J$2,$B8),0) -> 0 | O8: =IFERROR(SUMIFS(JUAN!$M$2:$M$11,JUAN!$H$2:$H$11,"ENTRADA",JUAN!$J$2:$J$11,$B8),0) -> 0 | P8: =IFERROR(SUMIFS('NORMA SANCHEZ'!$M$2:$M$14,'NORMA SANCHEZ'!$H$2:$H$14,"ENTRADA",'NORMA SANCHEZ'!$J$2:$J$14,$B8),0) -> 0 | Q8: =IFERROR(SUMIFS('JOSE CARLOS'!$M$2:$M$16,'JOSE CARLOS'!$H$2:$H$16,"ENTRADA",'JOSE CARLOS'!$J$2:$J$16,$B8),0) -> 0 | R8: =IFERROR(SUMIFS('LUIS ENRIQUE '!$M$2:$M$21,'LUIS ENRIQUE '!$H$2:$H$21,"ENTRADA",'LUIS ENRIQUE '!$J$2:$J$21,$B8),0) -> 0 | S8: =IFERROR(SUMIFS(CESARIA!$M$2:$M$15,CESARIA!$H$2:$H$15,"ENTRADA",CESARIA!$J$2:$J$15,$B8),0) -> 0 | T8: =IFERROR(SUMIFS(ALAN!$M$2:$M$14,ALAN!$H$2:$H$14,"ENTRADA",ALAN!$J$2:$J$14,$B8),0) -> 0 | U8: =IFERROR(SUMIFS(ELVIA!$M$2:$M$6,ELVIA!$H$2:$H$6,"ENTRADA",ELVIA!$J$2:$J$6,$B8),0) -> 0 | V8: =IFERROR(SUMIFS(CAJA!$M$2:$M$586,CAJA!$H$2:$H$586,"ENTRADA",CAJA!$J$2:$J$586,$B8),0) -> 0 | W8: =IFERROR(SUMIFS('CAJA TIGRES'!$M$2:$M$139,'CAJA TIGRES'!$H$2:$H$139,"ENTRADA",'CAJA TIGRES'!$J$2:$J$139,$B8),0) -> 0 | X8: =IFERROR(SUMIFS(RESERVA!$M$2:$M$2,RESERVA!$H$2:$H$2,"ENTRADA",RESERVA!$J$2:$J$2,$B8),0) -> 0 | Y8: =SUM(C8:X8) -> 0 | Z8: =Y8 -> 0
A9: 11.5 | B9: PRODUCTOS FINANCIEROS | C9: =IFERROR(SUMIFS('MGZ121'!$M$2:'MGZ121'!$M$175,'MGZ121'!$H$2:$H$175,"ENTRADA",'MGZ121'!$J$2:$J$175,$B9),0) -> 0.02 | D9: =IFERROR(SUMIFS('MGZ BBVA'!$M$2:$M$88,'MGZ BBVA'!$H$2:$H$88,"ENTRADA",'MGZ BBVA'!$J$2:$J$88,$B9),0) -> 0.97 | E9: =IFERROR(SUMIFS('MGZ DOLARES'!$M$2:$M$2,'MGZ DOLARES'!$F$2:$F$2,"ENTRADA",'MGZ DOLARES'!$J$2:$J$2,$B9),0) -> 0 | F9: =IFERROR(SUMIFS('MGZ BAJIO'!$M$2:$M$4,'MGZ BAJIO'!$H$2:$H$4,"ENTRADA",'MGZ BAJIO'!$J$2:$J$4,$B9),0) -> 0 | G9: =IFERROR(SUMIFS('VICTOR BANAMEX'!$M$2:$M$65,'VICTOR BANAMEX'!$H$2:$H$65,"ENTRADA",'VICTOR BANAMEX'!$J$2:$J$65,$B9),0) -> 0 | H9: =IFERROR(SUMIFS('VICTOR BANORTE'!$M$2:$M$9,'VICTOR BANORTE'!$H$2:$H$9,"ENTRADA",'VICTOR BANORTE'!$J$2:$J$9,$B9),0) -> 0 | I9: =IFERROR(SUMIFS(RODRIGO!$M$2:$M$2,RODRIGO!$H$2:$H$2,"ENTRADA",RODRIGO!$J$2:$J$2,$B9),0) -> 0 | J9: =IFERROR(SUMIFS(MOY!$M$2:$M$12,MOY!$H$2:$H$12,"ENTRADA",MOY!$J$2:$J$12,$B9),0) -> 0 | K9: =IFERROR(SUMIFS('NORMA RUTH'!$M$2:$M$12,'NORMA RUTH'!$H$2:$H$12,"ENTRADA",'NORMA RUTH'!$J$2:$J$12,$B9),0) -> 0 | L9: =IFERROR(SUMIFS(VALERIA!$M$2:$M$10,VALERIA!$H$2:$H$10,"ENTRADA",VALERIA!$J$2:$J$10,$B9),0) -> 0 | M9: =IFERROR(SUMIFS('MANUEL BANAMEX'!$M$2:$M$25,'MANUEL BANAMEX'!$H$2:$H$25,"ENTRADA",'MANUEL BANAMEX'!$J$2:$J$25,$B9),0) -> 0 | N9: =IFERROR(SUMIFS(ROBERTO!$M$2:$M$2,ROBERTO!$H$2:$H$2,"ENTRADA",ROBERTO!$J$2:$J$2,$B9),0) -> 0 | O9: =IFERROR(SUMIFS(JUAN!$M$2:$M$11,JUAN!$H$2:$H$11,"ENTRADA",JUAN!$J$2:$J$11,$B9),0) -> 0 | P9: =IFERROR(SUMIFS('NORMA SANCHEZ'!$M$2:$M$14,'NORMA SANCHEZ'!$H$2:$H$14,"ENTRADA",'NORMA SANCHEZ'!$J$2:$J$14,$B9),0) -> 0 | Q9: =IFERROR(SUMIFS('JOSE CARLOS'!$M$2:$M$16,'JOSE CARLOS'!$H$2:$H$16,"ENTRADA",'JOSE CARLOS'!$J$2:$J$16,$B9),0) -> 0 | R9: =IFERROR(SUMIFS('LUIS ENRIQUE '!$M$2:$M$21,'LUIS ENRIQUE '!$H$2:$H$21,"ENTRADA",'LUIS ENRIQUE '!$J$2:$J$21,$B9),0) -> 0 | S9: =IFERROR(SUMIFS(CESARIA!$M$2:$M$15,CESARIA!$H$2:$H$15,"ENTRADA",CESARIA!$J$2:$J$15,$B9),0) -> 0 | T9: =IFERROR(SUMIFS(ALAN!$M$2:$M$14,ALAN!$H$2:$H$14,"ENTRADA",ALAN!$J$2:$J$14,$B9),0) -> 0 | U9: =IFERROR(SUMIFS(ELVIA!$M$2:$M$6,ELVIA!$H$2:$H$6,"ENTRADA",ELVIA!$J$2:$J$6,$B9),0) -> 0 | V9: =IFERROR(SUMIFS(CAJA!$M$2:$M$586,CAJA!$H$2:$H$586,"ENTRADA",CAJA!$J$2:$J$586,$B9),0) -> 0 | W9: =IFERROR(SUMIFS('CAJA TIGRES'!$M$2:$M$139,'CAJA TIGRES'!$H$2:$H$139,"ENTRADA",'CAJA TIGRES'!$J$2:$J$139,$B9),0) -> 0 | X9: =IFERROR(SUMIFS(RESERVA!$M$2:$M$2,RESERVA!$H$2:$H$2,"ENTRADA",RESERVA!$J$2:$J$2,$B9),0) -> 0 | Y9: =SUM(C9:X9) -> 0.99 | Z9: =Y9 -> 0.99
A10: 11.6 | B10: REMESAS | C10: =IFERROR(SUMIFS('MGZ121'!$M$2:'MGZ121'!$M$175,'MGZ121'!$H$2:$H$175,"ENTRADA",'MGZ121'!$J$2:$J$175,$B10),0) -> 0 | D10: =IFERROR(SUMIFS('MGZ BBVA'!$M$2:$M$88,'MGZ BBVA'!$H$2:$H$88,"ENTRADA",'MGZ BBVA'!$J$2:$J$88,$B10),0) -> 0 | E10: =IFERROR(SUMIFS('MGZ DOLARES'!$M$2:$M$2,'MGZ DOLARES'!$F$2:$F$2,"ENTRADA",'MGZ DOLARES'!$J$2:$J$2,$B10),0) -> 0 | F10: =IFERROR(SUMIFS('MGZ BAJIO'!$M$2:$M$4,'MGZ BAJIO'!$H$2:$H$4,"ENTRADA",'MGZ BAJIO'!$J$2:$J$4,$B10),0) -> 0 | G10: =IFERROR(SUMIFS('VICTOR BANAMEX'!$M$2:$M$65,'VICTOR BANAMEX'!$H$2:$H$65,"ENTRADA",'VICTOR BANAMEX'!$J$2:$J$65,$B10),0) -> 0 | H10: =IFERROR(SUMIFS('VICTOR BANORTE'!$M$2:$M$9,'VICTOR BANORTE'!$H$2:$H$9,"ENTRADA",'VICTOR BANORTE'!$J$2:$J$9,$B10),0) -> 0 | I10: =IFERROR(SUMIFS(RODRIGO!$M$2:$M$2,RODRIGO!$H$2:$H$2,"ENTRADA",RODRIGO!$J$2:$J$2,$B10),0) -> 0 | J10: =IFERROR(SUMIFS(MOY!$M$2:$M$12,MOY!$H$2:$H$12,"ENTRADA",MOY!$J$2:$J$12,$B10),0) -> 0 | K10: =IFERROR(SUMIFS('NORMA RUTH'!$M$2:$M$12,'NORMA RUTH'!$H$2:$H$12,"ENTRADA",'NORMA RUTH'!$J$2:$J$12,$B10),0) -> 0 | L10: =IFERROR(SUMIFS(VALERIA!$M$2:$M$10,VALERIA!$H$2:$H$10,"ENTRADA",VALERIA!$J$2:$J$10,$B10),0) -> 0 | M10: =IFERROR(SUMIFS('MANUEL BANAMEX'!$M$2:$M$25,'MANUEL BANAMEX'!$H$2:$H$25,"ENTRADA",'MANUEL BANAMEX'!$J$2:$J$25,$B10),0) -> 0 | N10: =IFERROR(SUMIFS(ROBERTO!$M$2:$M$2,ROBERTO!$H$2:$H$2,"ENTRADA",ROBERTO!$J$2:$J$2,$B10),0) -> 0 | O10: =IFERROR(SUMIFS(JUAN!$M$2:$M$11,JUAN!$H$2:$H$11,"ENTRADA",JUAN!$J$2:$J$11,$B10),0) -> 0 | P10: =IFERROR(SUMIFS('NORMA SANCHEZ'!$M$2:$M$14,'NORMA SANCHEZ'!$H$2:$H$14,"ENTRADA",'NORMA SANCHEZ'!$J$2:$J$14,$B10),0) -> 0 | Q10: =IFERROR(SUMIFS('JOSE CARLOS'!$M$2:$M$16,'JOSE CARLOS'!$H$2:$H$16,"ENTRADA",'JOSE CARLOS'!$J$2:$J$16,$B10),0) -> 0 | R10: =IFERROR(SUMIFS('LUIS ENRIQUE '!$M$2:$M$21,'LUIS ENRIQUE '!$H$2:$H$21,"ENTRADA",'LUIS ENRIQUE '!$J$2:$J$21,$B10),0) -> 0 | S10: =IFERROR(SUMIFS(CESARIA!$M$2:$M$15,CESARIA!$H$2:$H$15,"ENTRADA",CESARIA!$J$2:$J$15,$B10),0) -> 0 | T10: =IFERROR(SUMIFS(ALAN!$M$2:$M$14,ALAN!$H$2:$H$14,"ENTRADA",ALAN!$J$2:$J$14,$B10),0) -> 0 | U10: =IFERROR(SUMIFS(ELVIA!$M$2:$M$6,ELVIA!$H$2:$H$6,"ENTRADA",ELVIA!$J$2:$J$6,$B10),0) -> 0 | V10: =IFERROR(SUMIFS(CAJA!$M$2:$M$586,CAJA!$H$2:$H$586,"ENTRADA",CAJA!$J$2:$J$586,$B10),0) -> 0 | W10: =IFERROR(SUMIFS('CAJA TIGRES'!$M$2:$M$139,'CAJA TIGRES'!$H$2:$H$139,"ENTRADA",'CAJA TIGRES'!$J$2:$J$139,$B10),0) -> 0 | X10: =IFERROR(SUMIFS(RESERVA!$M$2:$M$2,RESERVA!$H$2:$H$2,"ENTRADA",RESERVA!$J$2:$J$2,$B10),0) -> 0 | Y10: =SUM(C10:X10) -> 0 | Z10: =Y10 -> 0
A11: 11.7 | B11: REEMBOLSO | C11: =IFERROR(SUMIFS('MGZ121'!$M$2:'MGZ121'!$M$175,'MGZ121'!$H$2:$H$175,"ENTRADA",'MGZ121'!$J$2:$J$175,$B11),0) -> 0 | D11: =IFERROR(SUMIFS('MGZ BBVA'!$M$2:$M$88,'MGZ BBVA'!$H$2:$H$88,"ENTRADA",'MGZ BBVA'!$J$2:$J$88,$B11),0) -> 0 | E11: =IFERROR(SUMIFS('MGZ DOLARES'!$M$2:$M$2,'MGZ DOLARES'!$F$2:$F$2,"ENTRADA",'MGZ DOLARES'!$J$2:$J$2,$B11),0) -> 0 | F11: =IFERROR(SUMIFS('MGZ BAJIO'!$M$2:$M$4,'MGZ BAJIO'!$H$2:$H$4,"ENTRADA",'MGZ BAJIO'!$J$2:$J$4,$B11),0) -> 0 | G11: =IFERROR(SUMIFS('VICTOR BANAMEX'!$M$2:$M$65,'VICTOR BANAMEX'!$H$2:$H$65,"ENTRADA",'VICTOR BANAMEX'!$J$2:$J$65,$B11),0) -> 0 | H11: =IFERROR(SUMIFS('VICTOR BANORTE'!$M$2:$M$9,'VICTOR BANORTE'!$H$2:$H$9,"ENTRADA",'VICTOR BANORTE'!$J$2:$J$9,$B11),0) -> 0 | I11: =IFERROR(SUMIFS(RODRIGO!$M$2:$M$2,RODRIGO!$H$2:$H$2,"ENTRADA",RODRIGO!$J$2:$J$2,$B11),0) -> 0 | J11: =IFERROR(SUMIFS(MOY!$M$2:$M$12,MOY!$H$2:$H$12,"ENTRADA",MOY!$J$2:$J$12,$B11),0) -> 0 | K11: =IFERROR(SUMIFS('NORMA RUTH'!$M$2:$M$12,'NORMA RUTH'!$H$2:$H$12,"ENTRADA",'NORMA RUTH'!$J$2:$J$12,$B11),0) -> 0 | L11: =IFERROR(SUMIFS(VALERIA!$M$2:$M$10,VALERIA!$H$2:$H$10,"ENTRADA",VALERIA!$J$2:$J$10,$B11),0) -> 0 | M11: =IFERROR(SUMIFS('MANUEL BANAMEX'!$M$2:$M$25,'MANUEL BANAMEX'!$H$2:$H$25,"ENTRADA",'MANUEL BANAMEX'!$J$2:$J$25,$B11),0) -> 0 | N11: =IFERROR(SUMIFS(ROBERTO!$M$2:$M$2,ROBERTO!$H$2:$H$2,"ENTRADA",ROBERTO!$J$2:$J$2,$B11),0) -> 0 | O11: =IFERROR(SUMIFS(JUAN!$M$2:$M$11,JUAN!$H$2:$H$11,"ENTRADA",JUAN!$J$2:$J$11,$B11),0) -> 0 | P11: =IFERROR(SUMIFS('NORMA SANCHEZ'!$M$2:$M$14,'NORMA SANCHEZ'!$H$2:$H$14,"ENTRADA",'NORMA SANCHEZ'!$J$2:$J$14,$B11),0) -> 0 | Q11: =IFERROR(SUMIFS('JOSE CARLOS'!$M$2:$M$16,'JOSE CARLOS'!$H$2:$H$16,"ENTRADA",'JOSE CARLOS'!$J$2:$J$16,$B11),0) -> 0 | R11: =IFERROR(SUMIFS('LUIS ENRIQUE '!$M$2:$M$21,'LUIS ENRIQUE '!$H$2:$H$21,"ENTRADA",'LUIS ENRIQUE '!$J$2:$J$21,$B11),0) -> 0 | S11: =IFERROR(SUMIFS(CESARIA!$M$2:$M$15,CESARIA!$H$2:$H$15,"ENTRADA",CESARIA!$J$2:$J$15,$B11),0) -> 0 | T11: =IFERROR(SUMIFS(ALAN!$M$2:$M$14,ALAN!$H$2:$H$14,"ENTRADA",ALAN!$J$2:$J$14,$B11),0) -> 0 | U11: =IFERROR(SUMIFS(ELVIA!$M$2:$M$6,ELVIA!$H$2:$H$6,"ENTRADA",ELVIA!$J$2:$J$6,$B11),0) -> 0 | V11: =IFERROR(SUMIFS(CAJA!$M$2:$M$586,CAJA!$H$2:$H$586,"ENTRADA",CAJA!$J$2:$J$586,$B11),0) -> 0 | W11: =IFERROR(SUMIFS('CAJA TIGRES'!$M$2:$M$139,'CAJA TIGRES'!$H$2:$H$139,"ENTRADA",'CAJA TIGRES'!$J$2:$J$139,$B11),0) -> 0 | X11: =IFERROR(SUMIFS(RESERVA!$M$2:$M$2,RESERVA!$H$2:$H$2,"ENTRADA",RESERVA!$J$2:$J$2,$B11),0) -> 0 | Y11: =SUM(C11:X11) -> 0 | Z11: =Y11 -> 0
A12: 11.8 | B12: VENTA EXTERNA | C12: =IFERROR(SUMIFS('MGZ121'!$M$2:'MGZ121'!$M$175,'MGZ121'!$H$2:$H$175,"ENTRADA",'MGZ121'!$J$2:$J$175,$B12),0) -> 0 | D12: =IFERROR(SUMIFS('MGZ BBVA'!$M$2:$M$88,'MGZ BBVA'!$H$2:$H$88,"ENTRADA",'MGZ BBVA'!$J$2:$J$88,$B12),0) -> 0 | E12: =IFERROR(SUMIFS('MGZ DOLARES'!$M$2:$M$2,'MGZ DOLARES'!$F$2:$F$2,"ENTRADA",'MGZ DOLARES'!$J$2:$J$2,$B12),0) -> 0 | F12: =IFERROR(SUMIFS('MGZ BAJIO'!$M$2:$M$4,'MGZ BAJIO'!$H$2:$H$4,"ENTRADA",'MGZ BAJIO'!$J$2:$J$4,$B12),0) -> 0 | G12: =IFERROR(SUMIFS('VICTOR BANAMEX'!$M$2:$M$65,'VICTOR BANAMEX'!$H$2:$H$65,"ENTRADA",'VICTOR BANAMEX'!$J$2:$J$65,$B12),0) -> 0 | H12: =IFERROR(SUMIFS('VICTOR BANORTE'!$M$2:$M$9,'VICTOR BANORTE'!$H$2:$H$9,"ENTRADA",'VICTOR BANORTE'!$J$2:$J$9,$B12),0) -> 0 | I12: =IFERROR(SUMIFS(RODRIGO!$M$2:$M$2,RODRIGO!$H$2:$H$2,"ENTRADA",RODRIGO!$J$2:$J$2,$B12),0) -> 0 | J12: =IFERROR(SUMIFS(MOY!$M$2:$M$12,MOY!$H$2:$H$12,"ENTRADA",MOY!$J$2:$J$12,$B12),0) -> 0 | K12: =IFERROR(SUMIFS('NORMA RUTH'!$M$2:$M$12,'NORMA RUTH'!$H$2:$H$12,"ENTRADA",'NORMA RUTH'!$J$2:$J$12,$B12),0) -> 0 | L12: =IFERROR(SUMIFS(VALERIA!$M$2:$M$10,VALERIA!$H$2:$H$10,"ENTRADA",VALERIA!$J$2:$J$10,$B12),0) -> 0 | M12: =IFERROR(SUMIFS('MANUEL BANAMEX'!$M$2:$M$25,'MANUEL BANAMEX'!$H$2:$H$25,"ENTRADA",'MANUEL BANAMEX'!$J$2:$J$25,$B12),0) -> 8000 | N12: =IFERROR(SUMIFS(ROBERTO!$M$2:$M$2,ROBERTO!$H$2:$H$2,"ENTRADA",ROBERTO!$J$2:$J$2,$B12),0) -> 0 | O12: =IFERROR(SUMIFS(JUAN!$M$2:$M$11,JUAN!$H$2:$H$11,"ENTRADA",JUAN!$J$2:$J$11,$B12),0) -> 0 | P12: =IFERROR(SUMIFS('NORMA SANCHEZ'!$M$2:$M$14,'NORMA SANCHEZ'!$H$2:$H$14,"ENTRADA",'NORMA SANCHEZ'!$J$2:$J$14,$B12),0) -> 8000 | Q12: =IFERROR(SUMIFS('JOSE CARLOS'!$M$2:$M$16,'JOSE CARLOS'!$H$2:$H$16,"ENTRADA",'JOSE CARLOS'!$J$2:$J$16,$B12),0) -> 0 | R12: =IFERROR(SUMIFS('LUIS ENRIQUE '!$M$2:$M$21,'LUIS ENRIQUE '!$H$2:$H$21,"ENTRADA",'LUIS ENRIQUE '!$J$2:$J$21,$B12),0) -> 0 | S12: =IFERROR(SUMIFS(CESARIA!$M$2:$M$15,CESARIA!$H$2:$H$15,"ENTRADA",CESARIA!$J$2:$J$15,$B12),0) -> 0 | T12: =IFERROR(SUMIFS(ALAN!$M$2:$M$14,ALAN!$H$2:$H$14,"ENTRADA",ALAN!$J$2:$J$14,$B12),0) -> 0 | U12: =IFERROR(SUMIFS(ELVIA!$M$2:$M$6,ELVIA!$H$2:$H$6,"ENTRADA",ELVIA!$J$2:$J$6,$B12),0) -> 0 | V12: =IFERROR(SUMIFS(CAJA!$M$2:$M$586,CAJA!$H$2:$H$586,"ENTRADA",CAJA!$J$2:$J$586,$B12),0) -> 0 | W12: =IFERROR(SUMIFS('CAJA TIGRES'!$M$2:$M$139,'CAJA TIGRES'!$H$2:$H$139,"ENTRADA",'CAJA TIGRES'!$J$2:$J$139,$B12),0) -> 0 | X12: =IFERROR(SUMIFS(RESERVA!$M$2:$M$2,RESERVA!$H$2:$H$2,"ENTRADA",RESERVA!$J$2:$J$2,$B12),0) -> 0 | Y12: =SUM(C12:X12) -> 16000 | Z12: =Y12 -> 16000
B13: VENTA POMELERO | C13: =IFERROR(SUMIFS('MGZ121'!$M$2:'MGZ121'!$M$175,'MGZ121'!$H$2:$H$175,"ENTRADA",'MGZ121'!$J$2:$J$175,$B13),0) -> 0 | D13: =IFERROR(SUMIFS('MGZ BBVA'!$M$2:$M$88,'MGZ BBVA'!$H$2:$H$88,"ENTRADA",'MGZ BBVA'!$J$2:$J$88,$B13),0) -> 0 | E13: =IFERROR(SUMIFS('MGZ DOLARES'!$M$2:$M$2,'MGZ DOLARES'!$F$2:$F$2,"ENTRADA",'MGZ DOLARES'!$J$2:$J$2,$B13),0) -> 0 | F13: =IFERROR(SUMIFS('MGZ BAJIO'!$M$2:$M$4,'MGZ BAJIO'!$H$2:$H$4,"ENTRADA",'MGZ BAJIO'!$J$2:$J$4,$B13),0) -> 0 | G13: =IFERROR(SUMIFS('VICTOR BANAMEX'!$M$2:$M$65,'VICTOR BANAMEX'!$H$2:$H$65,"ENTRADA",'VICTOR BANAMEX'!$J$2:$J$65,$B13),0) -> 0 | H13: =IFERROR(SUMIFS('VICTOR BANORTE'!$M$2:$M$9,'VICTOR BANORTE'!$H$2:$H$9,"ENTRADA",'VICTOR BANORTE'!$J$2:$J$9,$B13),0) -> 0 | I13: =IFERROR(SUMIFS(RODRIGO!$M$2:$M$2,RODRIGO!$H$2:$H$2,"ENTRADA",RODRIGO!$J$2:$J$2,$B13),0) -> 0 | J13: =IFERROR(SUMIFS(MOY!$M$2:$M$12,MOY!$H$2:$H$12,"ENTRADA",MOY!$J$2:$J$12,$B13),0) -> 0 | K13: =IFERROR(SUMIFS('NORMA RUTH'!$M$2:$M$12,'NORMA RUTH'!$H$2:$H$12,"ENTRADA",'NORMA RUTH'!$J$2:$J$12,$B13),0) -> 0 | L13: =IFERROR(SUMIFS(VALERIA!$M$2:$M$10,VALERIA!$H$2:$H$10,"ENTRADA",VALERIA!$J$2:$J$10,$B13),0) -> 0 | M13: =IFERROR(SUMIFS('MANUEL BANAMEX'!$M$2:$M$25,'MANUEL BANAMEX'!$H$2:$H$25,"ENTRADA",'MANUEL BANAMEX'!$J$2:$J$25,$B13),0) -> 0 | N13: =IFERROR(SUMIFS(ROBERTO!$M$2:$M$2,ROBERTO!$H$2:$H$2,"ENTRADA",ROBERTO!$J$2:$J$2,$B13),0) -> 0 | O13: =IFERROR(SUMIFS(JUAN!$M$2:$M$11,JUAN!$H$2:$H$11,"ENTRADA",JUAN!$J$2:$J$11,$B13),0) -> 0 | P13: =IFERROR(SUMIFS('NORMA SANCHEZ'!$M$2:$M$14,'NORMA SANCHEZ'!$H$2:$H$14,"ENTRADA",'NORMA SANCHEZ'!$J$2:$J$14,$B13),0) -> 0 | Q13: =IFERROR(SUMIFS('JOSE CARLOS'!$M$2:$M$16,'JOSE CARLOS'!$H$2:$H$16,"ENTRADA",'JOSE CARLOS'!$J$2:$J$16,$B13),0) -> 0 | R13: =IFERROR(SUMIFS('LUIS ENRIQUE '!$M$2:$M$21,'LUIS ENRIQUE '!$H$2:$H$21,"ENTRADA",'LUIS ENRIQUE '!$J$2:$J$21,$B13),0) -> 0 | S13: =IFERROR(SUMIFS(CESARIA!$M$2:$M$15,CESARIA!$H$2:$H$15,"ENTRADA",CESARIA!$J$2:$J$15,$B13),0) -> 0 | T13: =IFERROR(SUMIFS(ALAN!$M$2:$M$14,ALAN!$H$2:$H$14,"ENTRADA",ALAN!$J$2:$J$14,$B13),0) -> 0 | U13: =IFERROR(SUMIFS(ELVIA!$M$2:$M$6,ELVIA!$H$2:$H$6,"ENTRADA",ELVIA!$J$2:$J$6,$B13),0) -> 0 | V13: =IFERROR(SUMIFS(CAJA!$M$2:$M$586,CAJA!$H$2:$H$586,"ENTRADA",CAJA!$J$2:$J$586,$B13),0) -> 139080 | W13: =IFERROR(SUMIFS('CAJA TIGRES'!$M$2:$M$139,'CAJA TIGRES'!$H$2:$H$139,"ENTRADA",'CAJA TIGRES'!$J$2:$J$139,$B13),0) -> 0 | X13: =IFERROR(SUMIFS(RESERVA!$M$2:$M$2,RESERVA!$H$2:$H$2,"ENTRADA",RESERVA!$J$2:$J$2,$B13),0) -> 0 | Y13: =SUM(C13:X13) -> 139080 | Z13: =Y13 -> 139080
B14: TOTAL INGRESOS | C14: =SUM(C5:C13) -> 6887540 | D14: =SUM(D5:D13) -> 2018661 | E14: =SUM(E5:E13) -> 0 | F14: =SUM(F5:F13) -> 0 | G14: =SUM(G5:G13) -> 0 | H14: =SUM(H5:H13) -> 0 | I14: =SUM(I5:I13) -> 0 | J14: =SUM(J5:J13) -> 0 | ... Z14: =SUM(Z5:Z13) -> 10367858
B16: SALIDAS
A17: 1 | B17: RAYA | C17: =SUM(C18:C20) -> 0 | D17: =SUM(D18:D20) -> 0 | E17: =SUM(E18:E20) -> 0 | F17: =SUM(F18:F20) -> 0 | G17: =SUM(G18:G20) -> 0 | H17: =SUM(H18:H20) -> 0 | I17: =SUM(I18:I20) -> 0 | J17: =SUM(J18:J20) -> 0 | ... Z17: =SUM(Z18:Z20) -> 2979212.7
A18: 1.1 | B18: RAYA MGZ | C18: =IFERROR(SUMIFS('MGZ121'!$N$2:$N$175,'MGZ121'!H$2:H$175,"SALIDA",'MGZ121'!$J$2:$J$175,$B18),0) -> 0 | D18: =IFERROR(SUMIFS('MGZ BBVA'!$N$2:$N$88,'MGZ BBVA'!$H$2:$H$88,"SALIDA",'MGZ BBVA'!$J$2:$J$88,$B18),0) -> 0 | E18: =IFERROR(SUMIFS('MGZ DOLARES'!$N$2:$N$2,'MGZ DOLARES'!$F$2:$F$2,"SALIDA",'MGZ DOLARES'!$J$2:$J$2,$B18),0) -> 0 | F18: =IFERROR(SUMIFS('MGZ BAJIO'!$N$2:$N$4,'MGZ BAJIO'!$H$2:$H$4,"SALIDA",'MGZ BAJIO'!$J$2:$J$4,$B18),0) -> 0 | G18: =IFERROR(SUMIFS('VICTOR BANAMEX'!$N$2:$N$65,'VICTOR BANAMEX'!$H$2:$H$65,"SALIDA",'VICTOR BANAMEX'!$J$2:$J$65,$B18),0) -> 0 | H18: =IFERROR(SUMIFS('VICTOR BANORTE'!$N$2:$N$9,'VICTOR BANORTE'!$H$2:$H$9,"SALIDA",'VICTOR BANORTE'!$J$2:$J$9,$B18),0) -> 0 | I18: =IFERROR(SUMIFS(RODRIGO!$N$2:$N$2,RODRIGO!$H$2:$H$2,"SALIDA",RODRIGO!$J$2:$J$2,$B18),0) -> 0 | J18: =IFERROR(SUMIFS(MOY!$N$2:$N$12,MOY!$H$2:$H$12,"SALIDA",MOY!$J$2:$J$12,$B18),0) -> 0 | K18: =IFERROR(SUMIFS('NORMA RUTH'!$N$2:$N$12,'NORMA RUTH'!$H$2:$H$12,"SALIDA",'NORMA RUTH'!$J$2:$J$12,$B18),0) -> 0 | L18: =IFERROR(SUMIFS(VALERIA!$N$2:$N$10,VALERIA!$H$2:$H$10,"SALIDA",VALERIA!$J$2:$J$10,$B18),0) -> 0 | M18: =IFERROR(SUMIFS('MANUEL BANAMEX'!$N$2:$N$25,'MANUEL BANAMEX'!$H$2:$H$25,"SALIDA",'MANUEL BANAMEX'!$J$2:$J$25,$B18),0) -> 0 | N18: =IFERROR(SUMIFS(ROBERTO!$N$2:$N$2,ROBERTO!$H$2:$H$2,"SALIDA",ROBERTO!$J$2:$J$2,$B18),0) -> 0 | O18: =IFERROR(SUMIFS(JUAN!$N$2:$N$11,JUAN!$H$2:$H$11,"SALIDA",JUAN!$J$2:$J$11,$B18),0) -> 0 | P18: =IFERROR(SUMIFS('NORMA SANCHEZ'!$N$2:$N$14,'NORMA SANCHEZ'!$H$2:$H$14,"SALIDA",'NORMA SANCHEZ'!$J$2:$J$14,$B18),0) -> 0 | Q18: =IFERROR(SUMIFS('JOSE CARLOS'!$N$2:$N$16,'JOSE CARLOS'!$H$2:$H$16,"SALIDA",'JOSE CARLOS'!$J$2:$J$16,$B18),0) -> 0 | R18: =IFERROR(SUMIFS('LUIS ENRIQUE '!$N$2:$N$21,'LUIS ENRIQUE '!$H$2:$H$21,"SALIDA",'LUIS ENRIQUE '!$J$2:$J$21,$B18),0) -> 0 | S18: =IFERROR(SUMIFS(CESARIA!$N$2:$N$15,CESARIA!$H$2:$H$15,"SALIDA",CESARIA!$J$2:$J$15,$B18),0) -> 0 | T18: =IFERROR(SUMIFS(ALAN!$N$2:$N$14,ALAN!$H$2:$H$14,"SALIDA",ALAN!$J$2:$J$14,$B18),0) -> 0 | U18: =IFERROR(SUMIFS(ELVIA!$N$2:$N$6,ELVIA!$H$2:$H$6,"SALIDA",ELVIA!$J$2:$J$6,$B18),0) -> 0 | V18: =IFERROR(SUMIFS(CAJA!$N$2:$N$586,CAJA!$H$2:$H$586,"SALIDA",CAJA!$J$2:$J$586,$B18),0) -> 1814168.7 | W18: =IFERROR(SUMIFS('CAJA TIGRES'!$N$2:$N$139,'CAJA TIGRES'!$H$2:$H$139,"SALIDA",'CAJA TIGRES'!$J$2:$J$139,$B18),0) -> 747964 | X18: =IFERROR(SUMIFS(RESERVA!$N$2:$N$2,RESERVA!$H$2:$H$2,"SALIDA",RESERVA!$J$2:$J$2,$B18),0) -> 0 | Y18: =SUM(C18:X18) -> 2562132.7 | Z18: =Y18 -> 2562132.7
A19: 1.2 | B19: ANTICIPOS RAYA MGZ | C19: =IFERROR(SUMIFS('MGZ121'!$N$2:$N$175,'MGZ121'!H$2:H$175,"SALIDA",'MGZ121'!$J$2:$J$175,$B19),0) -> 0 | D19: =IFERROR(SUMIFS('MGZ BBVA'!$N$2:$N$88,'MGZ BBVA'!$H$2:$H$88,"SALIDA",'MGZ BBVA'!$J$2:$J$88,$B19),0) -> 0 | E19: =IFERROR(SUMIFS('MGZ DOLARES'!$N$2:$N$2,'MGZ DOLARES'!$F$2:$F$2,"SALIDA",'MGZ DOLARES'!$J$2:$J$2,$B19),0) -> 0 | F19: =IFERROR(SUMIFS('MGZ BAJIO'!$N$2:$N$4,'MGZ BAJIO'!$H$2:$H$4,"SALIDA",'MGZ BAJIO'!$J$2:$J$4,$B19),0) -> 0 | G19: =IFERROR(SUMIFS('VICTOR BANAMEX'!$N$2:$N$65,'VICTOR BANAMEX'!$H$2:$H$65,"SALIDA",'VICTOR BANAMEX'!$J$2:$J$65,$B19),0) -> 0 | H19: =IFERROR(SUMIFS('VICTOR BANORTE'!$N$2:$N$9,'VICTOR BANORTE'!$H$2:$H$9,"SALIDA",'VICTOR BANORTE'!$J$2:$J$9,$B19),0) -> 0 | I19: =IFERROR(SUMIFS(RODRIGO!$N$2:$N$2,RODRIGO!$H$2:$H$2,"SALIDA",RODRIGO!$J$2:$J$2,$B19),0) -> 0 | J19: =IFERROR(SUMIFS(MOY!$N$2:$N$12,MOY!$H$2:$H$12,"SALIDA",MOY!$J$2:$J$12,$B19),0) -> 0 | K19: =IFERROR(SUMIFS('NORMA RUTH'!$N$2:$N$12,'NORMA RUTH'!$H$2:$H$12,"SALIDA",'NORMA RUTH'!$J$2:$J$12,$B19),0) -> 0 | L19: =IFERROR(SUMIFS(VALERIA!$N$2:$N$10,VALERIA!$H$2:$H$10,"SALIDA",VALERIA!$J$2:$J$10,$B19),0) -> 0 | M19: =IFERROR(SUMIFS('MANUEL BANAMEX'!$N$2:$N$25,'MANUEL BANAMEX'!$H$2:$H$25,"SALIDA",'MANUEL BANAMEX'!$J$2:$J$25,$B19),0) -> 0 | N19: =IFERROR(SUMIFS(ROBERTO!$N$2:$N$2,ROBERTO!$H$2:$H$2,"SALIDA",ROBERTO!$J$2:$J$2,$B19),0) -> 0 | O19: =IFERROR(SUMIFS(JUAN!$N$2:$N$11,JUAN!$H$2:$H$11,"SALIDA",JUAN!$J$2:$J$11,$B19),0) -> 0 | P19: =IFERROR(SUMIFS('NORMA SANCHEZ'!$N$2:$N$14,'NORMA SANCHEZ'!$H$2:$H$14,"SALIDA",'NORMA SANCHEZ'!$J$2:$J$14,$B19),0) -> 0 | Q19: =IFERROR(SUMIFS('JOSE CARLOS'!$N$2:$N$16,'JOSE CARLOS'!$H$2:$H$16,"SALIDA",'JOSE CARLOS'!$J$2:$J$16,$B19),0) -> 0 | R19: =IFERROR(SUMIFS('LUIS ENRIQUE '!$N$2:$N$21,'LUIS ENRIQUE '!$H$2:$H$21,"SALIDA",'LUIS ENRIQUE '!$J$2:$J$21,$B19),0) -> 0 | S19: =IFERROR(SUMIFS(CESARIA!$N$2:$N$15,CESARIA!$H$2:$H$15,"SALIDA",CESARIA!$J$2:$J$15,$B19),0) -> 0 | T19: =IFERROR(SUMIFS(ALAN!$N$2:$N$14,ALAN!$H$2:$H$14,"SALIDA",ALAN!$J$2:$J$14,$B19),0) -> 0 | U19: =IFERROR(SUMIFS(ELVIA!$N$2:$N$6,ELVIA!$H$2:$H$6,"SALIDA",ELVIA!$J$2:$J$6,$B19),0) -> 0 | V19: =IFERROR(SUMIFS(CAJA!$N$2:$N$586,CAJA!$H$2:$H$586,"SALIDA",CAJA!$J$2:$J$586,$B19),0) -> 256663 | W19: =IFERROR(SUMIFS('CAJA TIGRES'!$N$2:$N$139,'CAJA TIGRES'!$H$2:$H$139,"SALIDA",'CAJA TIGRES'!$J$2:$J$139,$B19),0) -> 24900 | X19: =IFERROR(SUMIFS(RESERVA!$N$2:$N$2,RESERVA!$H$2:$H$2,"SALIDA",RESERVA!$J$2:$J$2,$B19),0) -> 0 | Y19: =SUM(C19:X19) -> 281563 | Z19: =Y19 -> 281563
A20: 1.3 | B20: RAYA GANADERIA | C20: =IFERROR(SUMIFS('MGZ121'!$N$2:$N$175,'MGZ121'!H$2:H$175,"SALIDA",'MGZ121'!$J$2:$J$175,$B20),0) -> 0 | D20: =IFERROR(SUMIFS('MGZ BBVA'!$N$2:$N$88,'MGZ BBVA'!$H$2:$H$88,"SALIDA",'MGZ BBVA'!$J$2:$J$88,$B20),0) -> 0 | E20: =IFERROR(SUMIFS('MGZ DOLARES'!$N$2:$N$2,'MGZ DOLARES'!$F$2:$F$2,"SALIDA",'MGZ DOLARES'!$J$2:$J$2,$B20),0) -> 0 | F20: =IFERROR(SUMIFS('MGZ BAJIO'!$N$2:$N$4,'MGZ BAJIO'!$H$2:$H$4,"SALIDA",'MGZ BAJIO'!$J$2:$J$4,$B20),0) -> 0 | G20: =IFERROR(SUMIFS('VICTOR BANAMEX'!$N$2:$N$65,'VICTOR BANAMEX'!$H$2:$H$65,"SALIDA",'VICTOR BANAMEX'!$J$2:$J$65,$B20),0) -> 0 | H20: =IFERROR(SUMIFS('VICTOR BANORTE'!$N$2:$N$9,'VICTOR BANORTE'!$H$2:$H$9,"SALIDA",'VICTOR BANORTE'!$J$2:$J$9,$B20),0) -> 0 | I20: =IFERROR(SUMIFS(RODRIGO!$N$2:$N$2,RODRIGO!$H$2:$H$2,"SALIDA",RODRIGO!$J$2:$J$2,$B20),0) -> 0 | J20: =IFERROR(SUMIFS(MOY!$N$2:$N$12,MOY!$H$2:$H$12,"SALIDA",MOY!$J$2:$J$12,$B20),0) -> 0 | K20: =IFERROR(SUMIFS('NORMA RUTH'!$N$2:$N$12,'NORMA RUTH'!$H$2:$H$12,"SALIDA",'NORMA RUTH'!$J$2:$J$12,$B20),0) -> 0 | L20: =IFERROR(SUMIFS(VALERIA!$N$2:$N$10,VALERIA!$H$2:$H$10,"SALIDA",VALERIA!$J$2:$J$10,$B20),0) -> 0 | M20: =IFERROR(SUMIFS('MANUEL BANAMEX'!$N$2:$N$25,'MANUEL BANAMEX'!$H$2:$H$25,"SALIDA",'MANUEL BANAMEX'!$J$2:$J$25,$B20),0) -> 0 | N20: =IFERROR(SUMIFS(ROBERTO!$N$2:$N$2,ROBERTO!$H$2:$H$2,"SALIDA",ROBERTO!$J$2:$J$2,$B20),0) -> 0 | O20: =IFERROR(SUMIFS(JUAN!$N$2:$N$11,JUAN!$H$2:$H$11,"SALIDA",JUAN!$J$2:$J$11,$B20),0) -> 0 | P20: =IFERROR(SUMIFS('NORMA SANCHEZ'!$N$2:$N$14,'NORMA SANCHEZ'!$H$2:$H$14,"SALIDA",'NORMA SANCHEZ'!$J$2:$J$14,$B20),0) -> 0 | Q20: =IFERROR(SUMIFS('JOSE CARLOS'!$N$2:$N$16,'JOSE CARLOS'!$H$2:$H$16,"SALIDA",'JOSE CARLOS'!$J$2:$J$16,$B20),0) -> 0 | R20: =IFERROR(SUMIFS('LUIS ENRIQUE '!$N$2:$N$21,'LUIS ENRIQUE '!$H$2:$H$21,"SALIDA",'LUIS ENRIQUE '!$J$2:$J$21,$B20),0) -> 0 | S20: =IFERROR(SUMIFS(CESARIA!$N$2:$N$15,CESARIA!$H$2:$H$15,"SALIDA",CESARIA!$J$2:$J$15,$B20),0) -> 0 | T20: =IFERROR(SUMIFS(ALAN!$N$2:$N$14,ALAN!$H$2:$H$14,"SALIDA",ALAN!$J$2:$J$14,$B20),0) -> 0 | U20: =IFERROR(SUMIFS(ELVIA!$N$2:$N$6,ELVIA!$H$2:$H$6,"SALIDA",ELVIA!$J$2:$J$6,$B20),0) -> 0 | V20: =IFERROR(SUMIFS(CAJA!$N$2:$N$586,CAJA!$H$2:$H$586,"SALIDA",CAJA!$J$2:$J$586,$B20),0) -> 114767 | W20: =IFERROR(SUMIFS('CAJA TIGRES'!$N$2:$N$139,'CAJA TIGRES'!$H$2:$H$139,"SALIDA",'CAJA TIGRES'!$J$2:$J$139,$B20),0) -> 20750 | X20: =IFERROR(SUMIFS(RESERVA!$N$2:$N$2,RESERVA!$H$2:$H$2,"SALIDA",RESERVA!$J$2:$J$2,$B20),0) -> 0 | Y20: =SUM(C20:X20) -> 135517 | Z20: =Y20 -> 135517
A21: 4 | B21: PRODUCCION | C21: =SUM(C22:C28) -> 1589681.3 | D21: =SUM(D22:D28) -> 130150 | E21: =SUM(E22:E28) -> 0 | F21: =SUM(F22:F28) -> 0 | G21: =SUM(G22:G28) -> 0 | H21: =SUM(H22:H28) -> 0 | I21: =SUM(I22:I28) -> 0 | J21: =SUM(J22:J28) -> 0 | ... Z21: =SUM(Z22:Z28) -> 1942361.3
A22: 4.1 | B22: FERTILIZANTES Y AGROQUIMICOS | C22: =IFERROR(SUMIFS('MGZ121'!$N$2:$N$175,'MGZ121'!H$2:H$175,"SALIDA",'MGZ121'!$J$2:$J$175,$B22),0) -> 1589681.3 | D22: =IFERROR(SUMIFS('MGZ BBVA'!$N$2:$N$88,'MGZ BBVA'!$H$2:$H$88,"SALIDA",'MGZ BBVA'!$J$2:$J$88,$B22),0) -> 130150 | E22: =IFERROR(SUMIFS('MGZ DOLARES'!$N$2:$N$2,'MGZ DOLARES'!$F$2:$F$2,"SALIDA",'MGZ DOLARES'!$J$2:$J$2,$B22),0) -> 0 | F22: =IFERROR(SUMIFS('MGZ BAJIO'!$N$2:$N$4,'MGZ BAJIO'!$H$2:$H$4,"SALIDA",'MGZ BAJIO'!$J$2:$J$4,$B22),0) -> 0 | G22: =IFERROR(SUMIFS('VICTOR BANAMEX'!$N$2:$N$65,'VICTOR BANAMEX'!$H$2:$H$65,"SALIDA",'VICTOR BANAMEX'!$J$2:$J$65,$B22),0) -> 0 | H22: =IFERROR(SUMIFS('VICTOR BANORTE'!$N$2:$N$9,'VICTOR BANORTE'!$H$2:$H$9,"SALIDA",'VICTOR BANORTE'!$J$2:$J$9,$B22),0) -> 0 | I22: =IFERROR(SUMIFS(RODRIGO!$N$2:$N$2,RODRIGO!$H$2:$H$2,"SALIDA",RODRIGO!$J$2:$J$2,$B22),0) -> 0 | J22: =IFERROR(SUMIFS(MOY!$N$2:$N$12,MOY!$H$2:$H$12,"SALIDA",MOY!$J$2:$J$12,$B22),0) -> 0 | K22: =IFERROR(SUMIFS('NORMA RUTH'!$N$2:$N$12,'NORMA RUTH'!$H$2:$H$12,"SALIDA",'NORMA RUTH'!$J$2:$J$12,$B22),0) -> 0 | L22: =IFERROR(SUMIFS(VALERIA!$N$2:$N$10,VALERIA!$H$2:$H$10,"SALIDA",VALERIA!$J$2:$J$10,$B22),0) -> 0 | M22: =IFERROR(SUMIFS('MANUEL BANAMEX'!$N$2:$N$25,'MANUEL BANAMEX'!$H$2:$H$25,"SALIDA",'MANUEL BANAMEX'!$J$2:$J$25,$B22),0) -> 25000 | N22: =IFERROR(SUMIFS(ROBERTO!$N$2:$N$2,ROBERTO!$H$2:$H$2,"SALIDA",ROBERTO!$J$2:$J$2,$B22),0) -> 0 | O22: =IFERROR(SUMIFS(JUAN!$N$2:$N$11,JUAN!$H$2:$H$11,"SALIDA",JUAN!$J$2:$J$11,$B22),0) -> 0 | P22: =IFERROR(SUMIFS('NORMA SANCHEZ'!$N$2:$N$14,'NORMA SANCHEZ'!$H$2:$H$14,"SALIDA",'NORMA SANCHEZ'!$J$2:$J$14,$B22),0) -> 0 | Q22: =IFERROR(SUMIFS('JOSE CARLOS'!$N$2:$N$16,'JOSE CARLOS'!$H$2:$H$16,"SALIDA",'JOSE CARLOS'!$J$2:$J$16,$B22),0) -> 0 | R22: =IFERROR(SUMIFS('LUIS ENRIQUE '!$N$2:$N$21,'LUIS ENRIQUE '!$H$2:$H$21,"SALIDA",'LUIS ENRIQUE '!$J$2:$J$21,$B22),0) -> 0 | S22: =IFERROR(SUMIFS(CESARIA!$N$2:$N$15,CESARIA!$H$2:$H$15,"SALIDA",CESARIA!$J$2:$J$15,$B22),0) -> 0 | T22: =IFERROR(SUMIFS(ALAN!$N$2:$N$14,ALAN!$H$2:$H$14,"SALIDA",ALAN!$J$2:$J$14,$B22),0) -> 0 | U22: =IFERROR(SUMIFS(ELVIA!$N$2:$N$6,ELVIA!$H$2:$H$6,"SALIDA",ELVIA!$J$2:$J$6,$B22),0) -> 0 | V22: =IFERROR(SUMIFS(CAJA!$N$2:$N$586,CAJA!$H$2:$H$586,"SALIDA",CAJA!$J$2:$J$586,$B22),0) -> 0 | W22: =IFERROR(SUMIFS('CAJA TIGRES'!$N$2:$N$139,'CAJA TIGRES'!$H$2:$H$139,"SALIDA",'CAJA TIGRES'!$J$2:$J$139,$B22),0) -> 0 | X22: =IFERROR(SUMIFS(RESERVA!$N$2:$N$2,RESERVA!$H$2:$H$2,"SALIDA",RESERVA!$J$2:$J$2,$B22),0) -> 0 | Y22: =SUM(C22:X22) -> 1744831.3 | Z22: =Y22 -> 1744831.3
A23: 4.2 | B23: ACOLCHADO PLASTICO | C23: =IFERROR(SUMIFS('MGZ121'!$N$2:$N$175,'MGZ121'!H$2:H$175,"SALIDA",'MGZ121'!$J$2:$J$175,$B23),0) -> 0 | D23: =IFERROR(SUMIFS('MGZ BBVA'!$N$2:$N$88,'MGZ BBVA'!$H$2:$H$88,"SALIDA",'MGZ BBVA'!$J$2:$J$88,$B23),0) -> 0 | E23: =IFERROR(SUMIFS('MGZ DOLARES'!$N$2:$N$2,'MGZ DOLARES'!$F$2:$F$2,"SALIDA",'MGZ DOLARES'!$J$2:$J$2,$B23),0) -> 0 | F23: =IFERROR(SUMIFS('MGZ BAJIO'!$N$2:$N$4,'MGZ BAJIO'!$H$2:$H$4,"SALIDA",'MGZ BAJIO'!$J$2:$J$4,$B23),0) -> 0 | G23: =IFERROR(SUMIFS('VICTOR BANAMEX'!$N$2:$N$65,'VICTOR BANAMEX'!$H$2:$H$65,"SALIDA",'VICTOR BANAMEX'!$J$2:$J$65,$B23),0) -> 0 | H23: =IFERROR(SUMIFS('VICTOR BANORTE'!$N$2:$N$9,'VICTOR BANORTE'!$H$2:$H$9,"SALIDA",'VICTOR BANORTE'!$J$2:$J$9,$B23),0) -> 0 | I23: =IFERROR(SUMIFS(RODRIGO!$N$2:$N$2,RODRIGO!$H$2:$H$2,"SALIDA",RODRIGO!$J$2:$J$2,$B23),0) -> 0 | J23: =IFERROR(SUMIFS(MOY!$N$2:$N$12,MOY!$H$2:$H$12,"SALIDA",MOY!$J$2:$J$12,$B23),0) -> 0 | K23: =IFERROR(SUMIFS('NORMA RUTH'!$N$2:$N$12,'NORMA RUTH'!$H$2:$H$12,"SALIDA",'NORMA RUTH'!$J$2:$J$12,$B23),0) -> 0 | L23: =IFERROR(SUMIFS(VALERIA!$N$2:$N$10,VALERIA!$H$2:$H$10,"SALIDA",VALERIA!$J$2:$J$10,$B23),0) -> 0 | M23: =IFERROR(SUMIFS('MANUEL BANAMEX'!$N$2:$N$25,'MANUEL BANAMEX'!$H$2:$H$25,"SALIDA",'MANUEL BANAMEX'!$J$2:$J$25,$B23),0) -> 0 | N23: =IFERROR(SUMIFS(ROBERTO!$N$2:$N$2,ROBERTO!$H$2:$H$2,"SALIDA",ROBERTO!$J$2:$J$2,$B23),0) -> 0 | O23: =IFERROR(SUMIFS(JUAN!$N$2:$N$11,JUAN!$H$2:$H$11,"SALIDA",JUAN!$J$2:$J$11,$B23),0) -> 0 | P23: =IFERROR(SUMIFS('NORMA SANCHEZ'!$N$2:$N$14,'NORMA SANCHEZ'!$H$2:$H$14,"SALIDA",'NORMA SANCHEZ'!$J$2:$J$14,$B23),0) -> 0 | Q23: =IFERROR(SUMIFS('JOSE CARLOS'!$N$2:$N$16,'JOSE CARLOS'!$H$2:$H$16,"SALIDA",'JOSE CARLOS'!$J$2:$J$16,$B23),0) -> 0 | R23: =IFERROR(SUMIFS('LUIS ENRIQUE '!$N$2:$N$21,'LUIS ENRIQUE '!$H$2:$H$21,"SALIDA",'LUIS ENRIQUE '!$J$2:$J$21,$B23),0) -> 0 | S23: =IFERROR(SUMIFS(CESARIA!$N$2:$N$15,CESARIA!$H$2:$H$15,"SALIDA",CESARIA!$J$2:$J$15,$B23),0) -> 0 | T23: =IFERROR(SUMIFS(ALAN!$N$2:$N$14,ALAN!$H$2:$H$14,"SALIDA",ALAN!$J$2:$J$14,$B23),0) -> 0 | U23: =IFERROR(SUMIFS(ELVIA!$N$2:$N$6,ELVIA!$H$2:$H$6,"SALIDA",ELVIA!$J$2:$J$6,$B23),0) -> 0 | V23: =IFERROR(SUMIFS(CAJA!$N$2:$N$586,CAJA!$H$2:$H$586,"SALIDA",CAJA!$J$2:$J$586,$B23),0) -> 0 | W23: =IFERROR(SUMIFS('CAJA TIGRES'!$N$2:$N$139,'CAJA TIGRES'!$H$2:$H$139,"SALIDA",'CAJA TIGRES'!$J$2:$J$139,$B23),0) -> 0 | X23: =IFERROR(SUMIFS(RESERVA!$N$2:$N$2,RESERVA!$H$2:$H$2,"SALIDA",RESERVA!$J$2:$J$2,$B23),0) -> 0 | Y23: =SUM(C23:X23) -> 0 | Z23: =Y23 -> 0
A24: 4.3 | B24: MALLA SOMBRA | C24: =IFERROR(SUMIFS('MGZ121'!$N$2:$N$175,'MGZ121'!H$2:H$175,"SALIDA",'MGZ121'!$J$2:$J$175,$B24),0) -> 0 | D24: =IFERROR(SUMIFS('MGZ BBVA'!$N$2:$N$88,'MGZ BBVA'!$H$2:$H$88,"SALIDA",'MGZ BBVA'!$J$2:$J$88,$B24),0) -> 0 | E24: =IFERROR(SUMIFS('MGZ DOLARES'!$N$2:$N$2,'MGZ DOLARES'!$F$2:$F$2,"SALIDA",'MGZ DOLARES'!$J$2:$J$2,$B24),0) -> 0 | F24: =IFERROR(SUMIFS('MGZ BAJIO'!$N$2:$N$4,'MGZ BAJIO'!$H$2:$H$4,"SALIDA",'MGZ BAJIO'!$J$2:$J$4,$B24),0) -> 0 | G24: =IFERROR(SUMIFS('VICTOR BANAMEX'!$N$2:$N$65,'VICTOR BANAMEX'!$H$2:$H$65,"SALIDA",'VICTOR BANAMEX'!$J$2:$J$65,$B24),0) -> 0 | H24: =IFERROR(SUMIFS('VICTOR BANORTE'!$N$2:$N$9,'VICTOR BANORTE'!$H$2:$H$9,"SALIDA",'VICTOR BANORTE'!$J$2:$J$9,$B24),0) -> 0 | I24: =IFERROR(SUMIFS(RODRIGO!$N$2:$N$2,RODRIGO!$H$2:$H$2,"SALIDA",RODRIGO!$J$2:$J$2,$B24),0) -> 0 | J24: =IFERROR(SUMIFS(MOY!$N$2:$N$12,MOY!$H$2:$H$12,"SALIDA",MOY!$J$2:$J$12,$B24),0) -> 0 | K24: =IFERROR(SUMIFS('NORMA RUTH'!$N$2:$N$12,'NORMA RUTH'!$H$2:$H$12,"SALIDA",'NORMA RUTH'!$J$2:$J$12,$B24),0) -> 0 | L24: =IFERROR(SUMIFS(VALERIA!$N$2:$N$10,VALERIA!$H$2:$H$10,"SALIDA",VALERIA!$J$2:$J$10,$B24),0) -> 0 | M24: =IFERROR(SUMIFS('MANUEL BANAMEX'!$N$2:$N$25,'MANUEL BANAMEX'!$H$2:$H$25,"SALIDA",'MANUEL BANAMEX'!$J$2:$J$25,$B24),0) -> 0 | N24: =IFERROR(SUMIFS(ROBERTO!$N$2:$N$2,ROBERTO!$H$2:$H$2,"SALIDA",ROBERTO!$J$2:$J$2,$B24),0) -> 0 | O24: =IFERROR(SUMIFS(JUAN!$N$2:$N$11,JUAN!$H$2:$H$11,"SALIDA",JUAN!$J$2:$J$11,$B24),0) -> 0 | P24: =IFERROR(SUMIFS('NORMA SANCHEZ'!$N$2:$N$14,'NORMA SANCHEZ'!$H$2:$H$14,"SALIDA",'NORMA SANCHEZ'!$J$2:$J$14,$B24),0) -> 0 | Q24: =IFERROR(SUMIFS('JOSE CARLOS'!$N$2:$N$16,'JOSE CARLOS'!$H$2:$H$16,"SALIDA",'JOSE CARLOS'!$J$2:$J$16,$B24),0) -> 0 | R24: =IFERROR(SUMIFS('LUIS ENRIQUE '!$N$2:$N$21,'LUIS ENRIQUE '!$H$2:$H$21,"SALIDA",'LUIS ENRIQUE '!$J$2:$J$21,$B24),0) -> 0 | S24: =IFERROR(SUMIFS(CESARIA!$N$2:$N$15,CESARIA!$H$2:$H$15,"SALIDA",CESARIA!$J$2:$J$15,$B24),0) -> 0 | T24: =IFERROR(SUMIFS(ALAN!$N$2:$N$14,ALAN!$H$2:$H$14,"SALIDA",ALAN!$J$2:$J$14,$B24),0) -> 0 | U24: =IFERROR(SUMIFS(ELVIA!$N$2:$N$6,ELVIA!$H$2:$H$6,"SALIDA",ELVIA!$J$2:$J$6,$B24),0) -> 0 | V24: =IFERROR(SUMIFS(CAJA!$N$2:$N$586,CAJA!$H$2:$H$586,"SALIDA",CAJA!$J$2:$J$586,$B24),0) -> 0 | W24: =IFERROR(SUMIFS('CAJA TIGRES'!$N$2:$N$139,'CAJA TIGRES'!$H$2:$H$139,"SALIDA",'CAJA TIGRES'!$J$2:$J$139,$B24),0) -> 0 | X24: =IFERROR(SUMIFS(RESERVA!$N$2:$N$2,RESERVA!$H$2:$H$2,"SALIDA",RESERVA!$J$2:$J$2,$B24),0) -> 0 | Y24: =SUM(C24:X24) -> 0 | Z24: =Y24 -> 0
A25: 4.4 | B25: CORTES Y FLETES | C25: =IFERROR(SUMIFS('MGZ121'!$N$2:$N$175,'MGZ121'!H$2:H$175,"SALIDA",'MGZ121'!$J$2:$J$175,$B25),0) -> 0 | D25: =IFERROR(SUMIFS('MGZ BBVA'!$N$2:$N$88,'MGZ BBVA'!$H$2:$H$88,"SALIDA",'MGZ BBVA'!$J$2:$J$88,$B25),0) -> 0 | E25: =IFERROR(SUMIFS('MGZ DOLARES'!$N$2:$N$2,'MGZ DOLARES'!$F$2:$F$2,"SALIDA",'MGZ DOLARES'!$J$2:$J$2,$B25),0) -> 0 | F25: =IFERROR(SUMIFS('MGZ BAJIO'!$N$2:$N$4,'MGZ BAJIO'!$H$2:$H$4,"SALIDA",'MGZ BAJIO'!$J$2:$J$4,$B25),0) -> 0 | G25: =IFERROR(SUMIFS('VICTOR BANAMEX'!$N$2:$N$65,'VICTOR BANAMEX'!$H$2:$H$65,"SALIDA",'VICTOR BANAMEX'!$J$2:$J$65,$B25),0) -> 0 | H25: =IFERROR(SUMIFS('VICTOR BANORTE'!$N$2:$N$9,'VICTOR BANORTE'!$H$2:$H$9,"SALIDA",'VICTOR BANORTE'!$J$2:$J$9,$B25),0) -> 0 | I25: =IFERROR(SUMIFS(RODRIGO!$N$2:$N$2,RODRIGO!$H$2:$H$2,"SALIDA",RODRIGO!$J$2:$J$2,$B25),0) -> 0 | J25: =IFERROR(SUMIFS(MOY!$N$2:$N$12,MOY!$H$2:$H$12,"SALIDA",MOY!$J$2:$J$12,$B25),0) -> 0 | K25: =IFERROR(SUMIFS('NORMA RUTH'!$N$2:$N$12,'NORMA RUTH'!$H$2:$H$12,"SALIDA",'NORMA RUTH'!$J$2:$J$12,$B25),0) -> 0 | L25: =IFERROR(SUMIFS(VALERIA!$N$2:$N$10,VALERIA!$H$2:$H$10,"SALIDA",VALERIA!$J$2:$J$10,$B25),0) -> 0 | M25: =IFERROR(SUMIFS('MANUEL BANAMEX'!$N$2:$N$25,'MANUEL BANAMEX'!$H$2:$H$25,"SALIDA",'MANUEL BANAMEX'!$J$2:$J$25,$B25),0) -> 0 | N25: =IFERROR(SUMIFS(ROBERTO!$N$2:$N$2,ROBERTO!$H$2:$H$2,"SALIDA",ROBERTO!$J$2:$J$2,$B25),0) -> 0 | O25: =IFERROR(SUMIFS(JUAN!$N$2:$N$11,JUAN!$H$2:$H$11,"SALIDA",JUAN!$J$2:$J$11,$B25),0) -> 0 | P25: =IFERROR(SUMIFS('NORMA SANCHEZ'!$N$2:$N$14,'NORMA SANCHEZ'!$H$2:$H$14,"SALIDA",'NORMA SANCHEZ'!$J$2:$J$14,$B25),0) -> 0 | Q25: =IFERROR(SUMIFS('JOSE CARLOS'!$N$2:$N$16,'JOSE CARLOS'!$H$2:$H$16,"SALIDA",'JOSE CARLOS'!$J$2:$J$16,$B25),0) -> 0 | R25: =IFERROR(SUMIFS('LUIS ENRIQUE '!$N$2:$N$21,'LUIS ENRIQUE '!$H$2:$H$21,"SALIDA",'LUIS ENRIQUE '!$J$2:$J$21,$B25),0) -> 0 | S25: =IFERROR(SUMIFS(CESARIA!$N$2:$N$15,CESARIA!$H$2:$H$15,"SALIDA",CESARIA!$J$2:$J$15,$B25),0) -> 0 | T25: =IFERROR(SUMIFS(ALAN!$N$2:$N$14,ALAN!$H$2:$H$14,"SALIDA",ALAN!$J$2:$J$14,$B25),0) -> 0 | U25: =IFERROR(SUMIFS(ELVIA!$N$2:$N$6,ELVIA!$H$2:$H$6,"SALIDA",ELVIA!$J$2:$J$6,$B25),0) -> 0 | V25: =IFERROR(SUMIFS(CAJA!$N$2:$N$586,CAJA!$H$2:$H$586,"SALIDA",CAJA!$J$2:$J$586,$B25),0) -> 144030 | W25: =IFERROR(SUMIFS('CAJA TIGRES'!$N$2:$N$139,'CAJA TIGRES'!$H$2:$H$139,"SALIDA",'CAJA TIGRES'!$J$2:$J$139,$B25),0) -> 0 | X25: =IFERROR(SUMIFS(RESERVA!$N$2:$N$2,RESERVA!$H$2:$H$2,"SALIDA",RESERVA!$J$2:$J$2,$B25),0) -> 0 | Y25: =SUM(C25:X25) -> 144030 | Z25: =Y25 -> 144030
B26: COMPRA DE PIÑAS | C26: =IFERROR(SUMIFS('MGZ121'!$N$2:$N$175,'MGZ121'!H$2:H$175,"SALIDA",'MGZ121'!$J$2:$J$175,$B26),0) -> 0 | D26: =IFERROR(SUMIFS('MGZ BBVA'!$N$2:$N$88,'MGZ BBVA'!$H$2:$H$88,"SALIDA",'MGZ BBVA'!$J$2:$J$88,$B26),0) -> 0 | E26: =IFERROR(SUMIFS('MGZ DOLARES'!$N$2:$N$2,'MGZ DOLARES'!$F$2:$F$2,"SALIDA",'MGZ DOLARES'!$J$2:$J$2,$B26),0) -> 0 | F26: =IFERROR(SUMIFS('MGZ BAJIO'!$N$2:$N$4,'MGZ BAJIO'!$H$2:$H$4,"SALIDA",'MGZ BAJIO'!$J$2:$J$4,$B26),0) -> 0 | G26: =IFERROR(SUMIFS('VICTOR BANAMEX'!$N$2:$N$65,'VICTOR BANAMEX'!$H$2:$H$65,"SALIDA",'VICTOR BANAMEX'!$J$2:$J$65,$B26),0) -> 0 | H26: =IFERROR(SUMIFS('VICTOR BANORTE'!$N$2:$N$9,'VICTOR BANORTE'!$H$2:$H$9,"SALIDA",'VICTOR BANORTE'!$J$2:$J$9,$B26),0) -> 0 | I26: =IFERROR(SUMIFS(RODRIGO!$N$2:$N$2,RODRIGO!$H$2:$H$2,"SALIDA",RODRIGO!$J$2:$J$2,$B26),0) -> 0 | J26: =IFERROR(SUMIFS(MOY!$N$2:$N$12,MOY!$H$2:$H$12,"SALIDA",MOY!$J$2:$J$12,$B26),0) -> 0 | K26: =IFERROR(SUMIFS('NORMA RUTH'!$N$2:$N$12,'NORMA RUTH'!$H$2:$H$12,"SALIDA",'NORMA RUTH'!$J$2:$J$12,$B26),0) -> 0 | L26: =IFERROR(SUMIFS(VALERIA!$N$2:$N$10,VALERIA!$H$2:$H$10,"SALIDA",VALERIA!$J$2:$J$10,$B26),0) -> 0 | M26: =IFERROR(SUMIFS('MANUEL BANAMEX'!$N$2:$N$25,'MANUEL BANAMEX'!$H$2:$H$25,"SALIDA",'MANUEL BANAMEX'!$J$2:$J$25,$B26),0) -> 0 | N26: =IFERROR(SUMIFS(ROBERTO!$N$2:$N$2,ROBERTO!$H$2:$H$2,"SALIDA",ROBERTO!$J$2:$J$2,$B26),0) -> 0 | O26: =IFERROR(SUMIFS(JUAN!$N$2:$N$11,JUAN!$H$2:$H$11,"SALIDA",JUAN!$J$2:$J$11,$B26),0) -> 0 | P26: =IFERROR(SUMIFS('NORMA SANCHEZ'!$N$2:$N$14,'NORMA SANCHEZ'!$H$2:$H$14,"SALIDA",'NORMA SANCHEZ'!$J$2:$J$14,$B26),0) -> 0 | Q26: =IFERROR(SUMIFS('JOSE CARLOS'!$N$2:$N$16,'JOSE CARLOS'!$H$2:$H$16,"SALIDA",'JOSE CARLOS'!$J$2:$J$16,$B26),0) -> 0 | R26: =IFERROR(SUMIFS('LUIS ENRIQUE '!$N$2:$N$21,'LUIS ENRIQUE '!$H$2:$H$21,"SALIDA",'LUIS ENRIQUE '!$J$2:$J$21,$B26),0) -> 0 | S26: =IFERROR(SUMIFS(CESARIA!$N$2:$N$15,CESARIA!$H$2:$H$15,"SALIDA",CESARIA!$J$2:$J$15,$B26),0) -> 0 | T26: =IFERROR(SUMIFS(ALAN!$N$2:$N$14,ALAN!$H$2:$H$14,"SALIDA",ALAN!$J$2:$J$14,$B26),0) -> 0 | U26: =IFERROR(SUMIFS(ELVIA!$N$2:$N$6,ELVIA!$H$2:$H$6,"SALIDA",ELVIA!$J$2:$J$6,$B26),0) -> 0 | V26: =IFERROR(SUMIFS(CAJA!$N$2:$N$586,CAJA!$H$2:$H$586,"SALIDA",CAJA!$J$2:$J$586,$B26),0) -> 0 | W26: =IFERROR(SUMIFS('CAJA TIGRES'!$N$2:$N$139,'CAJA TIGRES'!$H$2:$H$139,"SALIDA",'CAJA TIGRES'!$J$2:$J$139,$B26),0) -> 0 | X26: =IFERROR(SUMIFS(RESERVA!$N$2:$N$2,RESERVA!$H$2:$H$2,"SALIDA",RESERVA!$J$2:$J$2,$B26),0) -> 0 | Y26: =SUM(C26:X26) -> 0 | Z26: =Y26 -> 0
B27: CORTES POMELERO | C27: =IFERROR(SUMIFS('MGZ121'!$N$2:$N$175,'MGZ121'!H$2:H$175,"SALIDA",'MGZ121'!$J$2:$J$175,$B27),0) -> 0 | D27: =IFERROR(SUMIFS('MGZ BBVA'!$N$2:$N$88,'MGZ BBVA'!$H$2:$H$88,"SALIDA",'MGZ BBVA'!$J$2:$J$88,$B27),0) -> 0 | E27: =IFERROR(SUMIFS('MGZ DOLARES'!$N$2:$N$2,'MGZ DOLARES'!$F$2:$F$2,"SALIDA",'MGZ DOLARES'!$J$2:$J$2,$B27),0) -> 0 | F27: =IFERROR(SUMIFS('MGZ BAJIO'!$N$2:$N$4,'MGZ BAJIO'!$H$2:$H$4,"SALIDA",'MGZ BAJIO'!$J$2:$J$4,$B27),0) -> 0 | G27: =IFERROR(SUMIFS('VICTOR BANAMEX'!$N$2:$N$65,'VICTOR BANAMEX'!$H$2:$H$65,"SALIDA",'VICTOR BANAMEX'!$J$2:$J$65,$B27),0) -> 0 | H27: =IFERROR(SUMIFS('VICTOR BANORTE'!$N$2:$N$9,'VICTOR BANORTE'!$H$2:$H$9,"SALIDA",'VICTOR BANORTE'!$J$2:$J$9,$B27),0) -> 0 | I27: =IFERROR(SUMIFS(RODRIGO!$N$2:$N$2,RODRIGO!$H$2:$H$2,"SALIDA",RODRIGO!$J$2:$J$2,$B27),0) -> 0 | J27: =IFERROR(SUMIFS(MOY!$N$2:$N$12,MOY!$H$2:$H$12,"SALIDA",MOY!$J$2:$J$12,$B27),0) -> 0 | K27: =IFERROR(SUMIFS('NORMA RUTH'!$N$2:$N$12,'NORMA RUTH'!$H$2:$H$12,"SALIDA",'NORMA RUTH'!$J$2:$J$12,$B27),0) -> 0 | L27: =IFERROR(SUMIFS(VALERIA!$N$2:$N$10,VALERIA!$H$2:$H$10,"SALIDA",VALERIA!$J$2:$J$10,$B27),0) -> 0 | M27: =IFERROR(SUMIFS('MANUEL BANAMEX'!$N$2:$N$25,'MANUEL BANAMEX'!$H$2:$H$25,"SALIDA",'MANUEL BANAMEX'!$J$2:$J$25,$B27),0) -> 0 | N27: =IFERROR(SUMIFS(ROBERTO!$N$2:$N$2,ROBERTO!$H$2:$H$2,"SALIDA",ROBERTO!$J$2:$J$2,$B27),0) -> 0 | O27: =IFERROR(SUMIFS(JUAN!$N$2:$N$11,JUAN!$H$2:$H$11,"SALIDA",JUAN!$J$2:$J$11,$B27),0) -> 0 | P27: =IFERROR(SUMIFS('NORMA SANCHEZ'!$N$2:$N$14,'NORMA SANCHEZ'!$H$2:$H$14,"SALIDA",'NORMA SANCHEZ'!$J$2:$J$14,$B27),0) -> 0 | Q27: =IFERROR(SUMIFS('JOSE CARLOS'!$N$2:$N$16,'JOSE CARLOS'!$H$2:$H$16,"SALIDA",'JOSE CARLOS'!$J$2:$J$16,$B27),0) -> 0 | R27: =IFERROR(SUMIFS('LUIS ENRIQUE '!$N$2:$N$21,'LUIS ENRIQUE '!$H$2:$H$21,"SALIDA",'LUIS ENRIQUE '!$J$2:$J$21,$B27),0) -> 0 | S27: =IFERROR(SUMIFS(CESARIA!$N$2:$N$15,CESARIA!$H$2:$H$15,"SALIDA",CESARIA!$J$2:$J$15,$B27),0) -> 0 | T27: =IFERROR(SUMIFS(ALAN!$N$2:$N$14,ALAN!$H$2:$H$14,"SALIDA",ALAN!$J$2:$J$14,$B27),0) -> 0 | U27: =IFERROR(SUMIFS(ELVIA!$N$2:$N$6,ELVIA!$H$2:$H$6,"SALIDA",ELVIA!$J$2:$J$6,$B27),0) -> 0 | V27: =IFERROR(SUMIFS(CAJA!$N$2:$N$586,CAJA!$H$2:$H$586,"SALIDA",CAJA!$J$2:$J$586,$B27),0) -> 0 | W27: =IFERROR(SUMIFS('CAJA TIGRES'!$N$2:$N$139,'CAJA TIGRES'!$H$2:$H$139,"SALIDA",'CAJA TIGRES'!$J$2:$J$139,$B27),0) -> 0 | X27: =IFERROR(SUMIFS(RESERVA!$N$2:$N$2,RESERVA!$H$2:$H$2,"SALIDA",RESERVA!$J$2:$J$2,$B27),0) -> 0 | Y27: =SUM(C27:X27) -> 0 | Z27: =Y27 -> 0
B28: PRESTAMO CHOFER | C28: =IFERROR(SUMIFS('MGZ121'!$N$2:$N$175,'MGZ121'!H$2:H$175,"SALIDA",'MGZ121'!$J$2:$J$175,$B28),0) -> 0 | D28: =IFERROR(SUMIFS('MGZ BBVA'!$N$2:$N$88,'MGZ BBVA'!$H$2:$H$88,"SALIDA",'MGZ BBVA'!$J$2:$J$88,$B28),0) -> 0 | E28: =IFERROR(SUMIFS('MGZ DOLARES'!$N$2:$N$2,'MGZ DOLARES'!$F$2:$F$2,"SALIDA",'MGZ DOLARES'!$J$2:$J$2,$B28),0) -> 0 | F28: =IFERROR(SUMIFS('MGZ BAJIO'!$N$2:$N$4,'MGZ BAJIO'!$H$2:$H$4,"SALIDA",'MGZ BAJIO'!$J$2:$J$4,$B28),0) -> 0 | G28: =IFERROR(SUMIFS('VICTOR BANAMEX'!$N$2:$N$65,'VICTOR BANAMEX'!$H$2:$H$65,"SALIDA",'VICTOR BANAMEX'!$J$2:$J$65,$B28),0) -> 0 | H28: =IFERROR(SUMIFS('VICTOR BANORTE'!$N$2:$N$9,'VICTOR BANORTE'!$H$2:$H$9,"SALIDA",'VICTOR BANORTE'!$J$2:$J$9,$B28),0) -> 0 | I28: =IFERROR(SUMIFS(RODRIGO!$N$2:$N$2,RODRIGO!$H$2:$H$2,"SALIDA",RODRIGO!$J$2:$J$2,$B28),0) -> 0 | J28: =IFERROR(SUMIFS(MOY!$N$2:$N$12,MOY!$H$2:$H$12,"SALIDA",MOY!$J$2:$J$12,$B28),0) -> 0 | K28: =IFERROR(SUMIFS('NORMA RUTH'!$N$2:$N$12,'NORMA RUTH'!$H$2:$H$12,"SALIDA",'NORMA RUTH'!$J$2:$J$12,$B28),0) -> 0 | L28: =IFERROR(SUMIFS(VALERIA!$N$2:$N$10,VALERIA!$H$2:$H$10,"SALIDA",VALERIA!$J$2:$J$10,$B28),0) -> 0 | M28: =IFERROR(SUMIFS('MANUEL BANAMEX'!$N$2:$N$25,'MANUEL BANAMEX'!$H$2:$H$25,"SALIDA",'MANUEL BANAMEX'!$J$2:$J$25,$B28),0) -> 0 | N28: =IFERROR(SUMIFS(ROBERTO!$N$2:$N$2,ROBERTO!$H$2:$H$2,"SALIDA",ROBERTO!$J$2:$J$2,$B28),0) -> 0 | O28: =IFERROR(SUMIFS(JUAN!$N$2:$N$11,JUAN!$H$2:$H$11,"SALIDA",JUAN!$J$2:$J$11,$B28),0) -> 0 | P28: =IFERROR(SUMIFS('NORMA SANCHEZ'!$N$2:$N$14,'NORMA SANCHEZ'!$H$2:$H$14,"SALIDA",'NORMA SANCHEZ'!$J$2:$J$14,$B28),0) -> 0 | Q28: =IFERROR(SUMIFS('JOSE CARLOS'!$N$2:$N$16,'JOSE CARLOS'!$H$2:$H$16,"SALIDA",'JOSE CARLOS'!$J$2:$J$16,$B28),0) -> 0 | R28: =IFERROR(SUMIFS('LUIS ENRIQUE '!$N$2:$N$21,'LUIS ENRIQUE '!$H$2:$H$21,"SALIDA",'LUIS ENRIQUE '!$J$2:$J$21,$B28),0) -> 0 | S28: =IFERROR(SUMIFS(CESARIA!$N$2:$N$15,CESARIA!$H$2:$H$15,"SALIDA",CESARIA!$J$2:$J$15,$B28),0) -> 0 | T28: =IFERROR(SUMIFS(ALAN!$N$2:$N$14,ALAN!$H$2:$H$14,"SALIDA",ALAN!$J$2:$J$14,$B28),0) -> 0 | U28: =IFERROR(SUMIFS(ELVIA!$N$2:$N$6,ELVIA!$H$2:$H$6,"SALIDA",ELVIA!$J$2:$J$6,$B28),0) -> 0 | V28: =IFERROR(SUMIFS(CAJA!$N$2:$N$586,CAJA!$H$2:$H$586,"SALIDA",CAJA!$J$2:$J$586,$B28),0) -> 53500 | W28: =IFERROR(SUMIFS('CAJA TIGRES'!$N$2:$N$139,'CAJA TIGRES'!$H$2:$H$139,"SALIDA",'CAJA TIGRES'!$J$2:$J$139,$B28),0) -> 0 | X28: =IFERROR(SUMIFS(RESERVA!$N$2:$N$2,RESERVA!$H$2:$H$2,"SALIDA",RESERVA!$J$2:$J$2,$B28),0) -> 0 | Y28: =SUM(C28:X28) -> 53500 | Z28: =Y28 -> 53500
A29: 5 | B29: OPERACION | C29: =SUM(C30:C48) -> 356709.74 | D29: =SUM(D30:D48) -> 856259.52 | E29: =SUM(E30:E48) -> 0 | F29: =SUM(F30:F48) -> 0 | G29: =SUM(G30:G48) -> 148474.29 | H29: =SUM(H30:H48) -> 0 | I29: =SUM(I30:I48) -> 0 | J29: =SUM(J30:J48) -> 0 | ... Z29: =SUM(Z30:Z48) -> 1862676.6
A30: 5.1 | B30: SERVICIOS MECANICOS | C30: =IFERROR(SUMIFS('MGZ121'!$N$2:$N$175,'MGZ121'!H$2:H$175,"SALIDA",'MGZ121'!$J$2:$J$175,$B30),0) -> 0 | D30: =IFERROR(SUMIFS('MGZ BBVA'!$N$2:$N$88,'MGZ BBVA'!$H$2:$H$88,"SALIDA",'MGZ BBVA'!$J$2:$J$88,$B30),0) -> 49085 | E30: =IFERROR(SUMIFS('MGZ DOLARES'!$N$2:$N$2,'MGZ DOLARES'!$F$2:$F$2,"SALIDA",'MGZ DOLARES'!$J$2:$J$2,$B30),0) -> 0 | F30: =IFERROR(SUMIFS('MGZ BAJIO'!$N$2:$N$4,'MGZ BAJIO'!$H$2:$H$4,"SALIDA",'MGZ BAJIO'!$J$2:$J$4,$B30),0) -> 0 | G30: =IFERROR(SUMIFS('VICTOR BANAMEX'!$N$2:$N$65,'VICTOR BANAMEX'!$H$2:$H$65,"SALIDA",'VICTOR BANAMEX'!$J$2:$J$65,$B30),0) -> 0 | H30: =IFERROR(SUMIFS('VICTOR BANORTE'!$N$2:$N$9,'VICTOR BANORTE'!$H$2:$H$9,"SALIDA",'VICTOR BANORTE'!$J$2:$J$9,$B30),0) -> 0 | I30: =IFERROR(SUMIFS(RODRIGO!$N$2:$N$2,RODRIGO!$H$2:$H$2,"SALIDA",RODRIGO!$J$2:$J$2,$B30),0) -> 0 | J30: =IFERROR(SUMIFS(MOY!$N$2:$N$12,MOY!$H$2:$H$12,"SALIDA",MOY!$J$2:$J$12,$B30),0) -> 0 | K30: =IFERROR(SUMIFS('NORMA RUTH'!$N$2:$N$12,'NORMA RUTH'!$H$2:$H$12,"SALIDA",'NORMA RUTH'!$J$2:$J$12,$B30),0) -> 0 | L30: =IFERROR(SUMIFS(VALERIA!$N$2:$N$10,VALERIA!$H$2:$H$10,"SALIDA",VALERIA!$J$2:$J$10,$B30),0) -> 0 | M30: =IFERROR(SUMIFS('MANUEL BANAMEX'!$N$2:$N$25,'MANUEL BANAMEX'!$H$2:$H$25,"SALIDA",'MANUEL BANAMEX'!$J$2:$J$25,$B30),0) -> 0 | N30: =IFERROR(SUMIFS(ROBERTO!$N$2:$N$2,ROBERTO!$H$2:$H$2,"SALIDA",ROBERTO!$J$2:$J$2,$B30),0) -> 0 | O30: =IFERROR(SUMIFS(JUAN!$N$2:$N$11,JUAN!$H$2:$H$11,"SALIDA",JUAN!$J$2:$J$11,$B30),0) -> 0 | P30: =IFERROR(SUMIFS('NORMA SANCHEZ'!$N$2:$N$14,'NORMA SANCHEZ'!$H$2:$H$14,"SALIDA",'NORMA SANCHEZ'!$J$2:$J$14,$B30),0) -> 0 | Q30: =IFERROR(SUMIFS('JOSE CARLOS'!$N$2:$N$16,'JOSE CARLOS'!$H$2:$H$16,"SALIDA",'JOSE CARLOS'!$J$2:$J$16,$B30),0) -> 0 | R30: =IFERROR(SUMIFS('LUIS ENRIQUE '!$N$2:$N$21,'LUIS ENRIQUE '!$H$2:$H$21,"SALIDA",'LUIS ENRIQUE '!$J$2:$J$21,$B30),0) -> 0 | S30: =IFERROR(SUMIFS(CESARIA!$N$2:$N$15,CESARIA!$H$2:$H$15,"SALIDA",CESARIA!$J$2:$J$15,$B30),0) -> 0 | T30: =IFERROR(SUMIFS(ALAN!$N$2:$N$14,ALAN!$H$2:$H$14,"SALIDA",ALAN!$J$2:$J$14,$B30),0) -> 0 | U30: =IFERROR(SUMIFS(ELVIA!$N$2:$N$6,ELVIA!$H$2:$H$6,"SALIDA",ELVIA!$J$2:$J$6,$B30),0) -> 0 | V30: =IFERROR(SUMIFS(CAJA!$N$2:$N$586,CAJA!$H$2:$H$586,"SALIDA",CAJA!$J$2:$J$586,$B30),0) -> 27365 | W30: =IFERROR(SUMIFS('CAJA TIGRES'!$N$2:$N$139,'CAJA TIGRES'!$H$2:$H$139,"SALIDA",'CAJA TIGRES'!$J$2:$J$139,$B30),0) -> 24395 | X30: =IFERROR(SUMIFS(RESERVA!$N$2:$N$2,RESERVA!$H$2:$H$2,"SALIDA",RESERVA!$J$2:$J$2,$B30),0) -> 0 | Y30: =SUM(C30:X30) -> 100845 | Z30: =Y30 -> 100845
A31: 5.2 | B31: REFACCIONES MAQUINARIA Y VEHICULOS | C31: =IFERROR(SUMIFS('MGZ121'!$N$2:$N$175,'MGZ121'!H$2:H$175,"SALIDA",'MGZ121'!$J$2:$J$175,$B31),0) -> 42305 | D31: =IFERROR(SUMIFS('MGZ BBVA'!$N$2:$N$88,'MGZ BBVA'!$H$2:$H$88,"SALIDA",'MGZ BBVA'!$J$2:$J$88,$B31),0) -> 226545.09 | E31: =IFERROR(SUMIFS('MGZ DOLARES'!$N$2:$N$2,'MGZ DOLARES'!$F$2:$F$2,"SALIDA",'MGZ DOLARES'!$J$2:$J$2,$B31),0) -> 0 | F31: =IFERROR(SUMIFS('MGZ BAJIO'!$N$2:$N$4,'MGZ BAJIO'!$H$2:$H$4,"SALIDA",'MGZ BAJIO'!$J$2:$J$4,$B31),0) -> 0 | G31: =IFERROR(SUMIFS('VICTOR BANAMEX'!$N$2:$N$65,'VICTOR BANAMEX'!$H$2:$H$65,"SALIDA",'VICTOR BANAMEX'!$J$2:$J$65,$B31),0) -> 0 | H31: =IFERROR(SUMIFS('VICTOR BANORTE'!$N$2:$N$9,'VICTOR BANORTE'!$H$2:$H$9,"SALIDA",'VICTOR BANORTE'!$J$2:$J$9,$B31),0) -> 0 | I31: =IFERROR(SUMIFS(RODRIGO!$N$2:$N$2,RODRIGO!$H$2:$H$2,"SALIDA",RODRIGO!$J$2:$J$2,$B31),0) -> 0 | J31: =IFERROR(SUMIFS(MOY!$N$2:$N$12,MOY!$H$2:$H$12,"SALIDA",MOY!$J$2:$J$12,$B31),0) -> 0 | K31: =IFERROR(SUMIFS('NORMA RUTH'!$N$2:$N$12,'NORMA RUTH'!$H$2:$H$12,"SALIDA",'NORMA RUTH'!$J$2:$J$12,$B31),0) -> 0 | L31: =IFERROR(SUMIFS(VALERIA!$N$2:$N$10,VALERIA!$H$2:$H$10,"SALIDA",VALERIA!$J$2:$J$10,$B31),0) -> 0 | M31: =IFERROR(SUMIFS('MANUEL BANAMEX'!$N$2:$N$25,'MANUEL BANAMEX'!$H$2:$H$25,"SALIDA",'MANUEL BANAMEX'!$J$2:$J$25,$B31),0) -> 7000 | N31: =IFERROR(SUMIFS(ROBERTO!$N$2:$N$2,ROBERTO!$H$2:$H$2,"SALIDA",ROBERTO!$J$2:$J$2,$B31),0) -> 0 | O31: =IFERROR(SUMIFS(JUAN!$N$2:$N$11,JUAN!$H$2:$H$11,"SALIDA",JUAN!$J$2:$J$11,$B31),0) -> 0 | P31: =IFERROR(SUMIFS('NORMA SANCHEZ'!$N$2:$N$14,'NORMA SANCHEZ'!$H$2:$H$14,"SALIDA",'NORMA SANCHEZ'!$J$2:$J$14,$B31),0) -> 0 | Q31: =IFERROR(SUMIFS('JOSE CARLOS'!$N$2:$N$16,'JOSE CARLOS'!$H$2:$H$16,"SALIDA",'JOSE CARLOS'!$J$2:$J$16,$B31),0) -> 0 | R31: =IFERROR(SUMIFS('LUIS ENRIQUE '!$N$2:$N$21,'LUIS ENRIQUE '!$H$2:$H$21,"SALIDA",'LUIS ENRIQUE '!$J$2:$J$21,$B31),0) -> 0 | S31: =IFERROR(SUMIFS(CESARIA!$N$2:$N$15,CESARIA!$H$2:$H$15,"SALIDA",CESARIA!$J$2:$J$15,$B31),0) -> 0 | T31: =IFERROR(SUMIFS(ALAN!$N$2:$N$14,ALAN!$H$2:$H$14,"SALIDA",ALAN!$J$2:$J$14,$B31),0) -> 0 | U31: =IFERROR(SUMIFS(ELVIA!$N$2:$N$6,ELVIA!$H$2:$H$6,"SALIDA",ELVIA!$J$2:$J$6,$B31),0) -> 0 | V31: =IFERROR(SUMIFS(CAJA!$N$2:$N$586,CAJA!$H$2:$H$586,"SALIDA",CAJA!$J$2:$J$586,$B31),0) -> 22745 | W31: =IFERROR(SUMIFS('CAJA TIGRES'!$N$2:$N$139,'CAJA TIGRES'!$H$2:$H$139,"SALIDA",'CAJA TIGRES'!$J$2:$J$139,$B31),0) -> 8780 | X31: =IFERROR(SUMIFS(RESERVA!$N$2:$N$2,RESERVA!$H$2:$H$2,"SALIDA",RESERVA!$J$2:$J$2,$B31),0) -> 0 | Y31: =SUM(C31:X31) -> 307375.09 | Z31: =Y31 -> 307375.09
A32: 5.3 | B32: COMBUSTIBLE | C32: =IFERROR(SUMIFS('MGZ121'!$N$2:$N$175,'MGZ121'!H$2:H$175,"SALIDA",'MGZ121'!$J$2:$J$175,$B32),0) -> 286868.91 | D32: =IFERROR(SUMIFS('MGZ BBVA'!$N$2:$N$88,'MGZ BBVA'!$H$2:$H$88,"SALIDA",'MGZ BBVA'!$J$2:$J$88,$B32),0) -> 508798.77 | E32: =IFERROR(SUMIFS('MGZ DOLARES'!$N$2:$N$2,'MGZ DOLARES'!$F$2:$F$2,"SALIDA",'MGZ DOLARES'!$J$2:$J$2,$B32),0) -> 0 | F32: =IFERROR(SUMIFS('MGZ BAJIO'!$N$2:$N$4,'MGZ BAJIO'!$H$2:$H$4,"SALIDA",'MGZ BAJIO'!$J$2:$J$4,$B32),0) -> 0 | G32: =IFERROR(SUMIFS('VICTOR BANAMEX'!$N$2:$N$65,'VICTOR BANAMEX'!$H$2:$H$65,"SALIDA",'VICTOR BANAMEX'!$J$2:$J$65,$B32),0) -> 0 | H32: =IFERROR(SUMIFS('VICTOR BANORTE'!$N$2:$N$9,'VICTOR BANORTE'!$H$2:$H$9,"SALIDA",'VICTOR BANORTE'!$J$2:$J$9,$B32),0) -> 0 | I32: =IFERROR(SUMIFS(RODRIGO!$N$2:$N$2,RODRIGO!$H$2:$H$2,"SALIDA",RODRIGO!$J$2:$J$2,$B32),0) -> 0 | J32: =IFERROR(SUMIFS(MOY!$N$2:$N$12,MOY!$H$2:$H$12,"SALIDA",MOY!$J$2:$J$12,$B32),0) -> 0 | K32: =IFERROR(SUMIFS('NORMA RUTH'!$N$2:$N$12,'NORMA RUTH'!$H$2:$H$12,"SALIDA",'NORMA RUTH'!$J$2:$J$12,$B32),0) -> 0 | L32: =IFERROR(SUMIFS(VALERIA!$N$2:$N$10,VALERIA!$H$2:$H$10,"SALIDA",VALERIA!$J$2:$J$10,$B32),0) -> 0 | M32: =IFERROR(SUMIFS('MANUEL BANAMEX'!$N$2:$N$25,'MANUEL BANAMEX'!$H$2:$H$25,"SALIDA",'MANUEL BANAMEX'!$J$2:$J$25,$B32),0) -> 0 | N32: =IFERROR(SUMIFS(ROBERTO!$N$2:$N$2,ROBERTO!$H$2:$H$2,"SALIDA",ROBERTO!$J$2:$J$2,$B32),0) -> 0 | O32: =IFERROR(SUMIFS(JUAN!$N$2:$N$11,JUAN!$H$2:$H$11,"SALIDA",JUAN!$J$2:$J$11,$B32),0) -> 0 | P32: =IFERROR(SUMIFS('NORMA SANCHEZ'!$N$2:$N$14,'NORMA SANCHEZ'!$H$2:$H$14,"SALIDA",'NORMA SANCHEZ'!$J$2:$J$14,$B32),0) -> 0 | Q32: =IFERROR(SUMIFS('JOSE CARLOS'!$N$2:$N$16,'JOSE CARLOS'!$H$2:$H$16,"SALIDA",'JOSE CARLOS'!$J$2:$J$16,$B32),0) -> 0 | R32: =IFERROR(SUMIFS('LUIS ENRIQUE '!$N$2:$N$21,'LUIS ENRIQUE '!$H$2:$H$21,"SALIDA",'LUIS ENRIQUE '!$J$2:$J$21,$B32),0) -> 0 | S32: =IFERROR(SUMIFS(CESARIA!$N$2:$N$15,CESARIA!$H$2:$H$15,"SALIDA",CESARIA!$J$2:$J$15,$B32),0) -> 0 | T32: =IFERROR(SUMIFS(ALAN!$N$2:$N$14,ALAN!$H$2:$H$14,"SALIDA",ALAN!$J$2:$J$14,$B32),0) -> 0 | U32: =IFERROR(SUMIFS(ELVIA!$N$2:$N$6,ELVIA!$H$2:$H$6,"SALIDA",ELVIA!$J$2:$J$6,$B32),0) -> 0 | V32: =IFERROR(SUMIFS(CAJA!$N$2:$N$586,CAJA!$H$2:$H$586,"SALIDA",CAJA!$J$2:$J$586,$B32),0) -> 500 | W32: =IFERROR(SUMIFS('CAJA TIGRES'!$N$2:$N$139,'CAJA TIGRES'!$H$2:$H$139,"SALIDA",'CAJA TIGRES'!$J$2:$J$139,$B32),0) -> 0 | X32: =IFERROR(SUMIFS(RESERVA!$N$2:$N$2,RESERVA!$H$2:$H$2,"SALIDA",RESERVA!$J$2:$J$2,$B32),0) -> 0 | Y32: =SUM(C32:X32) -> 796167.68 | Z32: =Y32 -> 796167.68
A33: 5.4 | B33: MATERIALES VARIOS | C33: =IFERROR(SUMIFS('MGZ121'!$N$2:$N$175,'MGZ121'!H$2:H$175,"SALIDA",'MGZ121'!$J$2:$J$175,$B33),0) -> 17920 | D33: =IFERROR(SUMIFS('MGZ BBVA'!$N$2:$N$88,'MGZ BBVA'!$H$2:$H$88,"SALIDA",'MGZ BBVA'!$J$2:$J$88,$B33),0) -> 0 | E33: =IFERROR(SUMIFS('MGZ DOLARES'!$N$2:$N$2,'MGZ DOLARES'!$F$2:$F$2,"SALIDA",'MGZ DOLARES'!$J$2:$J$2,$B33),0) -> 0 | F33: =IFERROR(SUMIFS('MGZ BAJIO'!$N$2:$N$4,'MGZ BAJIO'!$H$2:$H$4,"SALIDA",'MGZ BAJIO'!$J$2:$J$4,$B33),0) -> 0 | G33: =IFERROR(SUMIFS('VICTOR BANAMEX'!$N$2:$N$65,'VICTOR BANAMEX'!$H$2:$H$65,"SALIDA",'VICTOR BANAMEX'!$J$2:$J$65,$B33),0) -> 0 | H33: =IFERROR(SUMIFS('VICTOR BANORTE'!$N$2:$N$9,'VICTOR BANORTE'!$H$2:$H$9,"SALIDA",'VICTOR BANORTE'!$J$2:$J$9,$B33),0) -> 0 | I33: =IFERROR(SUMIFS(RODRIGO!$N$2:$N$2,RODRIGO!$H$2:$H$2,"SALIDA",RODRIGO!$J$2:$J$2,$B33),0) -> 0 | J33: =IFERROR(SUMIFS(MOY!$N$2:$N$12,MOY!$H$2:$H$12,"SALIDA",MOY!$J$2:$J$12,$B33),0) -> 0 | K33: =IFERROR(SUMIFS('NORMA RUTH'!$N$2:$N$12,'NORMA RUTH'!$H$2:$H$12,"SALIDA",'NORMA RUTH'!$J$2:$J$12,$B33),0) -> 0 | L33: =IFERROR(SUMIFS(VALERIA!$N$2:$N$10,VALERIA!$H$2:$H$10,"SALIDA",VALERIA!$J$2:$J$10,$B33),0) -> 0 | M33: =IFERROR(SUMIFS('MANUEL BANAMEX'!$N$2:$N$25,'MANUEL BANAMEX'!$H$2:$H$25,"SALIDA",'MANUEL BANAMEX'!$J$2:$J$25,$B33),0) -> 0 | N33: =IFERROR(SUMIFS(ROBERTO!$N$2:$N$2,ROBERTO!$H$2:$H$2,"SALIDA",ROBERTO!$J$2:$J$2,$B33),0) -> 0 | O33: =IFERROR(SUMIFS(JUAN!$N$2:$N$11,JUAN!$H$2:$H$11,"SALIDA",JUAN!$J$2:$J$11,$B33),0) -> 0 | P33: =IFERROR(SUMIFS('NORMA SANCHEZ'!$N$2:$N$14,'NORMA SANCHEZ'!$H$2:$H$14,"SALIDA",'NORMA SANCHEZ'!$J$2:$J$14,$B33),0) -> 0 | Q33: =IFERROR(SUMIFS('JOSE CARLOS'!$N$2:$N$16,'JOSE CARLOS'!$H$2:$H$16,"SALIDA",'JOSE CARLOS'!$J$2:$J$16,$B33),0) -> 0 | R33: =IFERROR(SUMIFS('LUIS ENRIQUE '!$N$2:$N$21,'LUIS ENRIQUE '!$H$2:$H$21,"SALIDA",'LUIS ENRIQUE '!$J$2:$J$21,$B33),0) -> 0 | S33: =IFERROR(SUMIFS(CESARIA!$N$2:$N$15,CESARIA!$H$2:$H$15,"SALIDA",CESARIA!$J$2:$J$15,$B33),0) -> 0 | T33: =IFERROR(SUMIFS(ALAN!$N$2:$N$14,ALAN!$H$2:$H$14,"SALIDA",ALAN!$J$2:$J$14,$B33),0) -> 0 | U33: =IFERROR(SUMIFS(ELVIA!$N$2:$N$6,ELVIA!$H$2:$H$6,"SALIDA",ELVIA!$J$2:$J$6,$B33),0) -> 0 | V33: =IFERROR(SUMIFS(CAJA!$N$2:$N$586,CAJA!$H$2:$H$586,"SALIDA",CAJA!$J$2:$J$586,$B33),0) -> 11311 | W33: =IFERROR(SUMIFS('CAJA TIGRES'!$N$2:$N$139,'CAJA TIGRES'!$H$2:$H$139,"SALIDA",'CAJA TIGRES'!$J$2:$J$139,$B33),0) -> 2695 | X33: =IFERROR(SUMIFS(RESERVA!$N$2:$N$2,RESERVA!$H$2:$H$2,"SALIDA",RESERVA!$J$2:$J$2,$B33),0) -> 0 | Y33: =SUM(C33:X33) -> 31926 | Z33: =Y33 -> 31926
A34: 5.5 | B34: GANADERIA | C34: =IFERROR(SUMIFS('MGZ121'!$N$2:$N$175,'MGZ121'!H$2:H$175,"SALIDA",'MGZ121'!$J$2:$J$175,$B34),0) -> 0 | D34: =IFERROR(SUMIFS('MGZ BBVA'!$N$2:$N$88,'MGZ BBVA'!$H$2:$H$88,"SALIDA",'MGZ BBVA'!$J$2:$J$88,$B34),0) -> 0 | E34: =IFERROR(SUMIFS('MGZ DOLARES'!$N$2:$N$2,'MGZ DOLARES'!$F$2:$F$2,"SALIDA",'MGZ DOLARES'!$J$2:$J$2,$B34),0) -> 0 | F34: =IFERROR(SUMIFS('MGZ BAJIO'!$N$2:$N$4,'MGZ BAJIO'!$H$2:$H$4,"SALIDA",'MGZ BAJIO'!$J$2:$J$4,$B34),0) -> 0 | G34: =IFERROR(SUMIFS('VICTOR BANAMEX'!$N$2:$N$65,'VICTOR BANAMEX'!$H$2:$H$65,"SALIDA",'VICTOR BANAMEX'!$J$2:$J$65,$B34),0) -> 114880 | H34: =IFERROR(SUMIFS('VICTOR BANORTE'!$N$2:$N$9,'VICTOR BANORTE'!$H$2:$H$9,"SALIDA",'VICTOR BANORTE'!$J$2:$J$9,$B34),0) -> 0 | I34: =IFERROR(SUMIFS(RODRIGO!$N$2:$N$2,RODRIGO!$H$2:$H$2,"SALIDA",RODRIGO!$J$2:$J$2,$B34),0) -> 0 | J34: =IFERROR(SUMIFS(MOY!$N$2:$N$12,MOY!$H$2:$H$12,"SALIDA",MOY!$J$2:$J$12,$B34),0) -> 0 | K34: =IFERROR(SUMIFS('NORMA RUTH'!$N$2:$N$12,'NORMA RUTH'!$H$2:$H$12,"SALIDA",'NORMA RUTH'!$J$2:$J$12,$B34),0) -> 0 | L34: =IFERROR(SUMIFS(VALERIA!$N$2:$N$10,VALERIA!$H$2:$H$10,"SALIDA",VALERIA!$J$2:$J$10,$B34),0) -> 0 | M34: =IFERROR(SUMIFS('MANUEL BANAMEX'!$N$2:$N$25,'MANUEL BANAMEX'!$H$2:$H$25,"SALIDA",'MANUEL BANAMEX'!$J$2:$J$25,$B34),0) -> 0 | N34: =IFERROR(SUMIFS(ROBERTO!$N$2:$N$2,ROBERTO!$H$2:$H$2,"SALIDA",ROBERTO!$J$2:$J$2,$B34),0) -> 0 | O34: =IFERROR(SUMIFS(JUAN!$N$2:$N$11,JUAN!$H$2:$H$11,"SALIDA",JUAN!$J$2:$J$11,$B34),0) -> 0 | P34: =IFERROR(SUMIFS('NORMA SANCHEZ'!$N$2:$N$14,'NORMA SANCHEZ'!$H$2:$H$14,"SALIDA",'NORMA SANCHEZ'!$J$2:$J$14,$B34),0) -> 0 | Q34: =IFERROR(SUMIFS('JOSE CARLOS'!$N$2:$N$16,'JOSE CARLOS'!$H$2:$H$16,"SALIDA",'JOSE CARLOS'!$J$2:$J$16,$B34),0) -> 0 | R34: =IFERROR(SUMIFS('LUIS ENRIQUE '!$N$2:$N$21,'LUIS ENRIQUE '!$H$2:$H$21,"SALIDA",'LUIS ENRIQUE '!$J$2:$J$21,$B34),0) -> 0 | S34: =IFERROR(SUMIFS(CESARIA!$N$2:$N$15,CESARIA!$H$2:$H$15,"SALIDA",CESARIA!$J$2:$J$15,$B34),0) -> 0 | T34: =IFERROR(SUMIFS(ALAN!$N$2:$N$14,ALAN!$H$2:$H$14,"SALIDA",ALAN!$J$2:$J$14,$B34),0) -> 0 | U34: =IFERROR(SUMIFS(ELVIA!$N$2:$N$6,ELVIA!$H$2:$H$6,"SALIDA",ELVIA!$J$2:$J$6,$B34),0) -> 0 | V34: =IFERROR(SUMIFS(CAJA!$N$2:$N$586,CAJA!$H$2:$H$586,"SALIDA",CAJA!$J$2:$J$586,$B34),0) -> 117055 | W34: =IFERROR(SUMIFS('CAJA TIGRES'!$N$2:$N$139,'CAJA TIGRES'!$H$2:$H$139,"SALIDA",'CAJA TIGRES'!$J$2:$J$139,$B34),0) -> 28235 | X34: =IFERROR(SUMIFS(RESERVA!$N$2:$N$2,RESERVA!$H$2:$H$2,"SALIDA",RESERVA!$J$2:$J$2,$B34),0) -> 0 | Y34: =SUM(C34:X34) -> 260170 | Z34: =Y34 -> 260170
A35: 5.6 | B35: RIEGO Y POZOS | C35: =IFERROR(SUMIFS('MGZ121'!$N$2:$N$175,'MGZ121'!H$2:H$175,"SALIDA",'MGZ121'!$J$2:$J$175,$B35),0) -> 0 | D35: =IFERROR(SUMIFS('MGZ BBVA'!$N$2:$N$88,'MGZ BBVA'!$H$2:$H$88,"SALIDA",'MGZ BBVA'!$J$2:$J$88,$B35),0) -> 0 | E35: =IFERROR(SUMIFS('MGZ DOLARES'!$N$2:$N$2,'MGZ DOLARES'!$F$2:$F$2,"SALIDA",'MGZ DOLARES'!$J$2:$J$2,$B35),0) -> 0 | F35: =IFERROR(SUMIFS('MGZ BAJIO'!$N$2:$N$4,'MGZ BAJIO'!$H$2:$H$4,"SALIDA",'MGZ BAJIO'!$J$2:$J$4,$B35),0) -> 0 | G35: =IFERROR(SUMIFS('VICTOR BANAMEX'!$N$2:$N$65,'VICTOR BANAMEX'!$H$2:$H$65,"SALIDA",'VICTOR BANAMEX'!$J$2:$J$65,$B35),0) -> 0 | H35: =IFERROR(SUMIFS('VICTOR BANORTE'!$N$2:$N$9,'VICTOR BANORTE'!$H$2:$H$9,"SALIDA",'VICTOR BANORTE'!$J$2:$J$9,$B35),0) -> 0 | I35: =IFERROR(SUMIFS(RODRIGO!$N$2:$N$2,RODRIGO!$H$2:$H$2,"SALIDA",RODRIGO!$J$2:$J$2,$B35),0) -> 0 | J35: =IFERROR(SUMIFS(MOY!$N$2:$N$12,MOY!$H$2:$H$12,"SALIDA",MOY!$J$2:$J$12,$B35),0) -> 0 | K35: =IFERROR(SUMIFS('NORMA RUTH'!$N$2:$N$12,'NORMA RUTH'!$H$2:$H$12,"SALIDA",'NORMA RUTH'!$J$2:$J$12,$B35),0) -> 0 | L35: =IFERROR(SUMIFS(VALERIA!$N$2:$N$10,VALERIA!$H$2:$H$10,"SALIDA",VALERIA!$J$2:$J$10,$B35),0) -> 0 | M35: =IFERROR(SUMIFS('MANUEL BANAMEX'!$N$2:$N$25,'MANUEL BANAMEX'!$H$2:$H$25,"SALIDA",'MANUEL BANAMEX'!$J$2:$J$25,$B35),0) -> 0 | N35: =IFERROR(SUMIFS(ROBERTO!$N$2:$N$2,ROBERTO!$H$2:$H$2,"SALIDA",ROBERTO!$J$2:$J$2,$B35),0) -> 0 | O35: =IFERROR(SUMIFS(JUAN!$N$2:$N$11,JUAN!$H$2:$H$11,"SALIDA",JUAN!$J$2:$J$11,$B35),0) -> 0 | P35: =IFERROR(SUMIFS('NORMA SANCHEZ'!$N$2:$N$14,'NORMA SANCHEZ'!$H$2:$H$14,"SALIDA",'NORMA SANCHEZ'!$J$2:$J$14,$B35),0) -> 0 | Q35: =IFERROR(SUMIFS('JOSE CARLOS'!$N$2:$N$16,'JOSE CARLOS'!$H$2:$H$16,"SALIDA",'JOSE CARLOS'!$J$2:$J$16,$B35),0) -> 0 | R35: =IFERROR(SUMIFS('LUIS ENRIQUE '!$N$2:$N$21,'LUIS ENRIQUE '!$H$2:$H$21,"SALIDA",'LUIS ENRIQUE '!$J$2:$J$21,$B35),0) -> 0 | S35: =IFERROR(SUMIFS(CESARIA!$N$2:$N$15,CESARIA!$H$2:$H$15,"SALIDA",CESARIA!$J$2:$J$15,$B35),0) -> 0 | T35: =IFERROR(SUMIFS(ALAN!$N$2:$N$14,ALAN!$H$2:$H$14,"SALIDA",ALAN!$J$2:$J$14,$B35),0) -> 0 | U35: =IFERROR(SUMIFS(ELVIA!$N$2:$N$6,ELVIA!$H$2:$H$6,"SALIDA",ELVIA!$J$2:$J$6,$B35),0) -> 0 | V35: =IFERROR(SUMIFS(CAJA!$N$2:$N$586,CAJA!$H$2:$H$586,"SALIDA",CAJA!$J$2:$J$586,$B35),0) -> 15400 | W35: =IFERROR(SUMIFS('CAJA TIGRES'!$N$2:$N$139,'CAJA TIGRES'!$H$2:$H$139,"SALIDA",'CAJA TIGRES'!$J$2:$J$139,$B35),0) -> 0 | X35: =IFERROR(SUMIFS(RESERVA!$N$2:$N$2,RESERVA!$H$2:$H$2,"SALIDA",RESERVA!$J$2:$J$2,$B35),0) -> 0 | Y35: =SUM(C35:X35) -> 15400 | Z35: =Y35 -> 15400
A36: 5.7 | B36: ENERGIA ELECTRICA, AGUA, GAS Y OXIGENO GRUPOS | C36: =IFERROR(SUMIFS('MGZ121'!$N$2:$N$175,'MGZ121'!H$2:H$175,"SALIDA",'MGZ121'!$J$2:$J$175,$B36),0) -> 0 | D36: =IFERROR(SUMIFS('MGZ BBVA'!$N$2:$N$88,'MGZ BBVA'!$H$2:$H$88,"SALIDA",'MGZ BBVA'!$J$2:$J$88,$B36),0) -> 0 | E36: =IFERROR(SUMIFS('MGZ DOLARES'!$N$2:$N$2,'MGZ DOLARES'!$F$2:$F$2,"SALIDA",'MGZ DOLARES'!$J$2:$J$2,$B36),0) -> 0 | F36: =IFERROR(SUMIFS('MGZ BAJIO'!$N$2:$N$4,'MGZ BAJIO'!$H$2:$H$4,"SALIDA",'MGZ BAJIO'!$J$2:$J$4,$B36),0) -> 0 | G36: =IFERROR(SUMIFS('VICTOR BANAMEX'!$N$2:$N$65,'VICTOR BANAMEX'!$H$2:$H$65,"SALIDA",'VICTOR BANAMEX'!$J$2:$J$65,$B36),0) -> 0 | H36: =IFERROR(SUMIFS('VICTOR BANORTE'!$N$2:$N$9,'VICTOR BANORTE'!$H$2:$H$9,"SALIDA",'VICTOR BANORTE'!$J$2:$J$9,$B36),0) -> 0 | I36: =IFERROR(SUMIFS(RODRIGO!$N$2:$N$2,RODRIGO!$H$2:$H$2,"SALIDA",RODRIGO!$J$2:$J$2,$B36),0) -> 0 | J36: =IFERROR(SUMIFS(MOY!$N$2:$N$12,MOY!$H$2:$H$12,"SALIDA",MOY!$J$2:$J$12,$B36),0) -> 0 | K36: =IFERROR(SUMIFS('NORMA RUTH'!$N$2:$N$12,'NORMA RUTH'!$H$2:$H$12,"SALIDA",'NORMA RUTH'!$J$2:$J$12,$B36),0) -> 0 | L36: =IFERROR(SUMIFS(VALERIA!$N$2:$N$10,VALERIA!$H$2:$H$10,"SALIDA",VALERIA!$J$2:$J$10,$B36),0) -> 0 | M36: =IFERROR(SUMIFS('MANUEL BANAMEX'!$N$2:$N$25,'MANUEL BANAMEX'!$H$2:$H$25,"SALIDA",'MANUEL BANAMEX'!$J$2:$J$25,$B36),0) -> 21673 | N36: =IFERROR(SUMIFS(ROBERTO!$N$2:$N$2,ROBERTO!$H$2:$H$2,"SALIDA",ROBERTO!$J$2:$J$2,$B36),0) -> 0 | O36: =IFERROR(SUMIFS(JUAN!$N$2:$N$11,JUAN!$H$2:$H$11,"SALIDA",JUAN!$J$2:$J$11,$B36),0) -> 0 | P36: =IFERROR(SUMIFS('NORMA SANCHEZ'!$N$2:$N$14,'NORMA SANCHEZ'!$H$2:$H$14,"SALIDA",'NORMA SANCHEZ'!$J$2:$J$14,$B36),0) -> 0 | Q36: =IFERROR(SUMIFS('JOSE CARLOS'!$N$2:$N$16,'JOSE CARLOS'!$H$2:$H$16,"SALIDA",'JOSE CARLOS'!$J$2:$J$16,$B36),0) -> 0 | R36: =IFERROR(SUMIFS('LUIS ENRIQUE '!$N$2:$N$21,'LUIS ENRIQUE '!$H$2:$H$21,"SALIDA",'LUIS ENRIQUE '!$J$2:$J$21,$B36),0) -> 0 | S36: =IFERROR(SUMIFS(CESARIA!$N$2:$N$15,CESARIA!$H$2:$H$15,"SALIDA",CESARIA!$J$2:$J$15,$B36),0) -> 0 | T36: =IFERROR(SUMIFS(ALAN!$N$2:$N$14,ALAN!$H$2:$H$14,"SALIDA",ALAN!$J$2:$J$14,$B36),0) -> 0 | U36: =IFERROR(SUMIFS(ELVIA!$N$2:$N$6,ELVIA!$H$2:$H$6,"SALIDA",ELVIA!$J$2:$J$6,$B36),0) -> 0 | V36: =IFERROR(SUMIFS(CAJA!$N$2:$N$586,CAJA!$H$2:$H$586,"SALIDA",CAJA!$J$2:$J$586,$B36),0) -> 15678 | W36: =IFERROR(SUMIFS('CAJA TIGRES'!$N$2:$N$139,'CAJA TIGRES'!$H$2:$H$139,"SALIDA",'CAJA TIGRES'!$J$2:$J$139,$B36),0) -> 2140 | X36: =IFERROR(SUMIFS(RESERVA!$N$2:$N$2,RESERVA!$H$2:$H$2,"SALIDA",RESERVA!$J$2:$J$2,$B36),0) -> 0 | Y36: =SUM(C36:X36) -> 39491 | Z36: =Y36 -> 39491
A37: 5.8 | B37: TELEFONOS | C37: =IFERROR(SUMIFS('MGZ121'!$N$2:$N$175,'MGZ121'!H$2:H$175,"SALIDA",'MGZ121'!$J$2:$J$175,$B37),0) -> 0 | D37: =IFERROR(SUMIFS('MGZ BBVA'!$N$2:$N$88,'MGZ BBVA'!$H$2:$H$88,"SALIDA",'MGZ BBVA'!$J$2:$J$88,$B37),0) -> 58 | E37: =IFERROR(SUMIFS('MGZ DOLARES'!$N$2:$N$2,'MGZ DOLARES'!$F$2:$F$2,"SALIDA",'MGZ DOLARES'!$J$2:$J$2,$B37),0) -> 0 | F37: =IFERROR(SUMIFS('MGZ BAJIO'!$N$2:$N$4,'MGZ BAJIO'!$H$2:$H$4,"SALIDA",'MGZ BAJIO'!$J$2:$J$4,$B37),0) -> 0 | G37: =IFERROR(SUMIFS('VICTOR BANAMEX'!$N$2:$N$65,'VICTOR BANAMEX'!$H$2:$H$65,"SALIDA",'VICTOR BANAMEX'!$J$2:$J$65,$B37),0) -> 0 | H37: =IFERROR(SUMIFS('VICTOR BANORTE'!$N$2:$N$9,'VICTOR BANORTE'!$H$2:$H$9,"SALIDA",'VICTOR BANORTE'!$J$2:$J$9,$B37),0) -> 0 | I37: =IFERROR(SUMIFS(RODRIGO!$N$2:$N$2,RODRIGO!$H$2:$H$2,"SALIDA",RODRIGO!$J$2:$J$2,$B37),0) -> 0 | J37: =IFERROR(SUMIFS(MOY!$N$2:$N$12,MOY!$H$2:$H$12,"SALIDA",MOY!$J$2:$J$12,$B37),0) -> 0 | K37: =IFERROR(SUMIFS('NORMA RUTH'!$N$2:$N$12,'NORMA RUTH'!$H$2:$H$12,"SALIDA",'NORMA RUTH'!$J$2:$J$12,$B37),0) -> 0 | L37: =IFERROR(SUMIFS(VALERIA!$N$2:$N$10,VALERIA!$H$2:$H$10,"SALIDA",VALERIA!$J$2:$J$10,$B37),0) -> 0 | M37: =IFERROR(SUMIFS('MANUEL BANAMEX'!$N$2:$N$25,'MANUEL BANAMEX'!$H$2:$H$25,"SALIDA",'MANUEL BANAMEX'!$J$2:$J$25,$B37),0) -> 10112 | N37: =IFERROR(SUMIFS(ROBERTO!$N$2:$N$2,ROBERTO!$H$2:$H$2,"SALIDA",ROBERTO!$J$2:$J$2,$B37),0) -> 0 | O37: =IFERROR(SUMIFS(JUAN!$N$2:$N$11,JUAN!$H$2:$H$11,"SALIDA",JUAN!$J$2:$J$11,$B37),0) -> 0 | P37: =IFERROR(SUMIFS('NORMA SANCHEZ'!$N$2:$N$14,'NORMA SANCHEZ'!$H$2:$H$14,"SALIDA",'NORMA SANCHEZ'!$J$2:$J$14,$B37),0) -> 0 | Q37: =IFERROR(SUMIFS('JOSE CARLOS'!$N$2:$N$16,'JOSE CARLOS'!$H$2:$H$16,"SALIDA",'JOSE CARLOS'!$J$2:$J$16,$B37),0) -> 0 | R37: =IFERROR(SUMIFS('LUIS ENRIQUE '!$N$2:$N$21,'LUIS ENRIQUE '!$H$2:$H$21,"SALIDA",'LUIS ENRIQUE '!$J$2:$J$21,$B37),0) -> 0 | S37: =IFERROR(SUMIFS(CESARIA!$N$2:$N$15,CESARIA!$H$2:$H$15,"SALIDA",CESARIA!$J$2:$J$15,$B37),0) -> 0 | T37: =IFERROR(SUMIFS(ALAN!$N$2:$N$14,ALAN!$H$2:$H$14,"SALIDA",ALAN!$J$2:$J$14,$B37),0) -> 0 | U37: =IFERROR(SUMIFS(ELVIA!$N$2:$N$6,ELVIA!$H$2:$H$6,"SALIDA",ELVIA!$J$2:$J$6,$B37),0) -> 0 | V37: =IFERROR(SUMIFS(CAJA!$N$2:$N$586,CAJA!$H$2:$H$586,"SALIDA",CAJA!$J$2:$J$586,$B37),0) -> 0 | W37: =IFERROR(SUMIFS('CAJA TIGRES'!$N$2:$N$139,'CAJA TIGRES'!$H$2:$H$139,"SALIDA",'CAJA TIGRES'!$J$2:$J$139,$B37),0) -> 0 | X37: =IFERROR(SUMIFS(RESERVA!$N$2:$N$2,RESERVA!$H$2:$H$2,"SALIDA",RESERVA!$J$2:$J$2,$B37),0) -> 0 | Y37: =SUM(C37:X37) -> 10170 | Z37: =Y37 -> 10170
A38: 5.9 | B38: VARIOS OPERACIÓN | C38: =IFERROR(SUMIFS('MGZ121'!$N$2:$N$175,'MGZ121'!H$2:H$175,"SALIDA",'MGZ121'!$J$2:$J$175,$B38),0) -> 9615.83 | D38: =IFERROR(SUMIFS('MGZ BBVA'!$N$2:$N$88,'MGZ BBVA'!$H$2:$H$88,"SALIDA",'MGZ BBVA'!$J$2:$J$88,$B38),0) -> 42768.66 | E38: =IFERROR(SUMIFS('MGZ DOLARES'!$N$2:$N$2,'MGZ DOLARES'!$F$2:$F$2,"SALIDA",'MGZ DOLARES'!$J$2:$J$2,$B38),0) -> 0 | F38: =IFERROR(SUMIFS('MGZ BAJIO'!$N$2:$N$4,'MGZ BAJIO'!$H$2:$H$4,"SALIDA",'MGZ BAJIO'!$J$2:$J$4,$B38),0) -> 0 | G38: =IFERROR(SUMIFS('VICTOR BANAMEX'!$N$2:$N$65,'VICTOR BANAMEX'!$H$2:$H$65,"SALIDA",'VICTOR BANAMEX'!$J$2:$J$65,$B38),0) -> 33594.293 | H38: =IFERROR(SUMIFS('VICTOR BANORTE'!$N$2:$N$9,'VICTOR BANORTE'!$H$2:$H$9,"SALIDA",'VICTOR BANORTE'!$J$2:$J$9,$B38),0) -> 0 | I38: =IFERROR(SUMIFS(RODRIGO!$N$2:$N$2,RODRIGO!$H$2:$H$2,"SALIDA",RODRIGO!$J$2:$J$2,$B38),0) -> 0 | J38: =IFERROR(SUMIFS(MOY!$N$2:$N$12,MOY!$H$2:$H$12,"SALIDA",MOY!$J$2:$J$12,$B38),0) -> 0 | K38: =IFERROR(SUMIFS('NORMA RUTH'!$N$2:$N$12,'NORMA RUTH'!$H$2:$H$12,"SALIDA",'NORMA RUTH'!$J$2:$J$12,$B38),0) -> 0 | L38: =IFERROR(SUMIFS(VALERIA!$N$2:$N$10,VALERIA!$H$2:$H$10,"SALIDA",VALERIA!$J$2:$J$10,$B38),0) -> 0 | M38: =IFERROR(SUMIFS('MANUEL BANAMEX'!$N$2:$N$25,'MANUEL BANAMEX'!$H$2:$H$25,"SALIDA",'MANUEL BANAMEX'!$J$2:$J$25,$B38),0) -> 0 | N38: =IFERROR(SUMIFS(ROBERTO!$N$2:$N$2,ROBERTO!$H$2:$H$2,"SALIDA",ROBERTO!$J$2:$J$2,$B38),0) -> 0 | O38: =IFERROR(SUMIFS(JUAN!$N$2:$N$11,JUAN!$H$2:$H$11,"SALIDA",JUAN!$J$2:$J$11,$B38),0) -> 0 | P38: =IFERROR(SUMIFS('NORMA SANCHEZ'!$N$2:$N$14,'NORMA SANCHEZ'!$H$2:$H$14,"SALIDA",'NORMA SANCHEZ'!$J$2:$J$14,$B38),0) -> 0 | Q38: =IFERROR(SUMIFS('JOSE CARLOS'!$N$2:$N$16,'JOSE CARLOS'!$H$2:$H$16,"SALIDA",'JOSE CARLOS'!$J$2:$J$16,$B38),0) -> 0 | R38: =IFERROR(SUMIFS('LUIS ENRIQUE '!$N$2:$N$21,'LUIS ENRIQUE '!$H$2:$H$21,"SALIDA",'LUIS ENRIQUE '!$J$2:$J$21,$B38),0) -> 0 | S38: =IFERROR(SUMIFS(CESARIA!$N$2:$N$15,CESARIA!$H$2:$H$15,"SALIDA",CESARIA!$J$2:$J$15,$B38),0) -> 0 | T38: =IFERROR(SUMIFS(ALAN!$N$2:$N$14,ALAN!$H$2:$H$14,"SALIDA",ALAN!$J$2:$J$14,$B38),0) -> 0 | U38: =IFERROR(SUMIFS(ELVIA!$N$2:$N$6,ELVIA!$H$2:$H$6,"SALIDA",ELVIA!$J$2:$J$6,$B38),0) -> 0 | V38: =IFERROR(SUMIFS(CAJA!$N$2:$N$586,CAJA!$H$2:$H$586,"SALIDA",CAJA!$J$2:$J$586,$B38),0) -> 90608 | W38: =IFERROR(SUMIFS('CAJA TIGRES'!$N$2:$N$139,'CAJA TIGRES'!$H$2:$H$139,"SALIDA",'CAJA TIGRES'!$J$2:$J$139,$B38),0) -> 54237 | X38: =IFERROR(SUMIFS(RESERVA!$N$2:$N$2,RESERVA!$H$2:$H$2,"SALIDA",RESERVA!$J$2:$J$2,$B38),0) -> 0 | Y38: =SUM(C38:X38) -> 230823.78 | Z38: =Y38 -> 230823.78
A39: 5.1 | B39: TENENCIAS | C39: =IFERROR(SUMIFS('MGZ121'!$N$2:$N$175,'MGZ121'!H$2:H$175,"SALIDA",'MGZ121'!$J$2:$J$175,$B39),0) -> 0 | D39: =IFERROR(SUMIFS('MGZ BBVA'!$N$2:$N$88,'MGZ BBVA'!$H$2:$H$88,"SALIDA",'MGZ BBVA'!$J$2:$J$88,$B39),0) -> 0 | E39: =IFERROR(SUMIFS('MGZ DOLARES'!$N$2:$N$2,'MGZ DOLARES'!$F$2:$F$2,"SALIDA",'MGZ DOLARES'!$J$2:$J$2,$B39),0) -> 0 | F39: =IFERROR(SUMIFS('MGZ BAJIO'!$N$2:$N$4,'MGZ BAJIO'!$H$2:$H$4,"SALIDA",'MGZ BAJIO'!$J$2:$J$4,$B39),0) -> 0 | G39: =IFERROR(SUMIFS('VICTOR BANAMEX'!$N$2:$N$65,'VICTOR BANAMEX'!$H$2:$H$65,"SALIDA",'VICTOR BANAMEX'!$J$2:$J$65,$B39),0) -> 0 | H39: =IFERROR(SUMIFS('VICTOR BANORTE'!$N$2:$N$9,'VICTOR BANORTE'!$H$2:$H$9,"SALIDA",'VICTOR BANORTE'!$J$2:$J$9,$B39),0) -> 0 | I39: =IFERROR(SUMIFS(RODRIGO!$N$2:$N$2,RODRIGO!$H$2:$H$2,"SALIDA",RODRIGO!$J$2:$J$2,$B39),0) -> 0 | J39: =IFERROR(SUMIFS(MOY!$N$2:$N$12,MOY!$H$2:$H$12,"SALIDA",MOY!$J$2:$J$12,$B39),0) -> 0 | K39: =IFERROR(SUMIFS('NORMA RUTH'!$N$2:$N$12,'NORMA RUTH'!$H$2:$H$12,"SALIDA",'NORMA RUTH'!$J$2:$J$12,$B39),0) -> 0 | L39: =IFERROR(SUMIFS(VALERIA!$N$2:$N$10,VALERIA!$H$2:$H$10,"SALIDA",VALERIA!$J$2:$J$10,$B39),0) -> 0 | M39: =IFERROR(SUMIFS('MANUEL BANAMEX'!$N$2:$N$25,'MANUEL BANAMEX'!$H$2:$H$25,"SALIDA",'MANUEL BANAMEX'!$J$2:$J$25,$B39),0) -> 0 | N39: =IFERROR(SUMIFS(ROBERTO!$N$2:$N$2,ROBERTO!$H$2:$H$2,"SALIDA",ROBERTO!$J$2:$J$2,$B39),0) -> 0 | O39: =IFERROR(SUMIFS(JUAN!$N$2:$N$11,JUAN!$H$2:$H$11,"SALIDA",JUAN!$J$2:$J$11,$B39),0) -> 0 | P39: =IFERROR(SUMIFS('NORMA SANCHEZ'!$N$2:$N$14,'NORMA SANCHEZ'!$H$2:$H$14,"SALIDA",'NORMA SANCHEZ'!$J$2:$J$14,$B39),0) -> 0 | Q39: =IFERROR(SUMIFS('JOSE CARLOS'!$N$2:$N$16,'JOSE CARLOS'!$H$2:$H$16,"SALIDA",'JOSE CARLOS'!$J$2:$J$16,$B39),0) -> 0 | R39: =IFERROR(SUMIFS('LUIS ENRIQUE '!$N$2:$N$21,'LUIS ENRIQUE '!$H$2:$H$21,"SALIDA",'LUIS ENRIQUE '!$J$2:$J$21,$B39),0) -> 0 | S39: =IFERROR(SUMIFS(CESARIA!$N$2:$N$15,CESARIA!$H$2:$H$15,"SALIDA",CESARIA!$J$2:$J$15,$B39),0) -> 0 | T39: =IFERROR(SUMIFS(ALAN!$N$2:$N$14,ALAN!$H$2:$H$14,"SALIDA",ALAN!$J$2:$J$14,$B39),0) -> 0 | U39: =IFERROR(SUMIFS(ELVIA!$N$2:$N$6,ELVIA!$H$2:$H$6,"SALIDA",ELVIA!$J$2:$J$6,$B39),0) -> 0 | V39: =IFERROR(SUMIFS(CAJA!$N$2:$N$586,CAJA!$H$2:$H$586,"SALIDA",CAJA!$J$2:$J$586,$B39),0) -> 0 | W39: =IFERROR(SUMIFS('CAJA TIGRES'!$N$2:$N$139,'CAJA TIGRES'!$H$2:$H$139,"SALIDA",'CAJA TIGRES'!$J$2:$J$139,$B39),0) -> 0 | X39: =IFERROR(SUMIFS(RESERVA!$N$2:$N$2,RESERVA!$H$2:$H$2,"SALIDA",RESERVA!$J$2:$J$2,$B39),0) -> 0 | Y39: =SUM(C39:X39) -> 0 | Z39: =Y39 -> 0
B40: SEGUROS CAMPO | C40: =IFERROR(SUMIFS('MGZ121'!$N$2:$N$175,'MGZ121'!H$2:H$175,"SALIDA",'MGZ121'!$J$2:$J$175,$B40),0) -> 0 | D40: =IFERROR(SUMIFS('MGZ BBVA'!$N$2:$N$88,'MGZ BBVA'!$H$2:$H$88,"SALIDA",'MGZ BBVA'!$J$2:$J$88,$B40),0) -> 0 | E40: =IFERROR(SUMIFS('MGZ DOLARES'!$N$2:$N$2,'MGZ DOLARES'!$F$2:$F$2,"SALIDA",'MGZ DOLARES'!$J$2:$J$2,$B40),0) -> 0 | F40: =IFERROR(SUMIFS('MGZ BAJIO'!$N$2:$N$4,'MGZ BAJIO'!$H$2:$H$4,"SALIDA",'MGZ BAJIO'!$J$2:$J$4,$B40),0) -> 0 | G40: =IFERROR(SUMIFS('VICTOR BANAMEX'!$N$2:$N$65,'VICTOR BANAMEX'!$H$2:$H$65,"SALIDA",'VICTOR BANAMEX'!$J$2:$J$65,$B40),0) -> 0 | H40: =IFERROR(SUMIFS('VICTOR BANORTE'!$N$2:$N$9,'VICTOR BANORTE'!$H$2:$H$9,"SALIDA",'VICTOR BANORTE'!$J$2:$J$9,$B40),0) -> 0 | I40: =IFERROR(SUMIFS(RODRIGO!$N$2:$N$2,RODRIGO!$H$2:$H$2,"SALIDA",RODRIGO!$J$2:$J$2,$B40),0) -> 0 | J40: =IFERROR(SUMIFS(MOY!$N$2:$N$12,MOY!$H$2:$H$12,"SALIDA",MOY!$J$2:$J$12,$B40),0) -> 0 | K40: =IFERROR(SUMIFS('NORMA RUTH'!$N$2:$N$12,'NORMA RUTH'!$H$2:$H$12,"SALIDA",'NORMA RUTH'!$J$2:$J$12,$B40),0) -> 0 | L40: =IFERROR(SUMIFS(VALERIA!$N$2:$N$10,VALERIA!$H$2:$H$10,"SALIDA",VALERIA!$J$2:$J$10,$B40),0) -> 0 | M40: =IFERROR(SUMIFS('MANUEL BANAMEX'!$N$2:$N$25,'MANUEL BANAMEX'!$H$2:$H$25,"SALIDA",'MANUEL BANAMEX'!$J$2:$J$25,$B40),0) -> 0 | N40: =IFERROR(SUMIFS(ROBERTO!$N$2:$N$2,ROBERTO!$H$2:$H$2,"SALIDA",ROBERTO!$J$2:$J$2,$B40),0) -> 0 | O40: =IFERROR(SUMIFS(JUAN!$N$2:$N$11,JUAN!$H$2:$H$11,"SALIDA",JUAN!$J$2:$J$11,$B40),0) -> 0 | P40: =IFERROR(SUMIFS('NORMA SANCHEZ'!$N$2:$N$14,'NORMA SANCHEZ'!$H$2:$H$14,"SALIDA",'NORMA SANCHEZ'!$J$2:$J$14,$B40),0) -> 0 | Q40: =IFERROR(SUMIFS('JOSE CARLOS'!$N$2:$N$16,'JOSE CARLOS'!$H$2:$H$16,"SALIDA",'JOSE CARLOS'!$J$2:$J$16,$B40),0) -> 0 | R40: =IFERROR(SUMIFS('LUIS ENRIQUE '!$N$2:$N$21,'LUIS ENRIQUE '!$H$2:$H$21,"SALIDA",'LUIS ENRIQUE '!$J$2:$J$21,$B40),0) -> 0 | S40: =IFERROR(SUMIFS(CESARIA!$N$2:$N$15,CESARIA!$H$2:$H$15,"SALIDA",CESARIA!$J$2:$J$15,$B40),0) -> 0 | T40: =IFERROR(SUMIFS(ALAN!$N$2:$N$14,ALAN!$H$2:$H$14,"SALIDA",ALAN!$J$2:$J$14,$B40),0) -> 0 | U40: =IFERROR(SUMIFS(ELVIA!$N$2:$N$6,ELVIA!$H$2:$H$6,"SALIDA",ELVIA!$J$2:$J$6,$B40),0) -> 0 | V40: =IFERROR(SUMIFS(CAJA!$N$2:$N$586,CAJA!$H$2:$H$586,"SALIDA",CAJA!$J$2:$J$586,$B40),0) -> 0 | W40: =IFERROR(SUMIFS('CAJA TIGRES'!$N$2:$N$139,'CAJA TIGRES'!$H$2:$H$139,"SALIDA",'CAJA TIGRES'!$J$2:$J$139,$B40),0) -> 0 | X40: =IFERROR(SUMIFS(RESERVA!$N$2:$N$2,RESERVA!$H$2:$H$2,"SALIDA",RESERVA!$J$2:$J$2,$B40),0) -> 0 | Y40: =SUM(C40:X40) -> 0 | Z40: =Y40 -> 0
B41: MMTO EQUIPOS | C41: =IFERROR(SUMIFS('MGZ121'!$N$2:$N$175,'MGZ121'!H$2:H$175,"SALIDA",'MGZ121'!$J$2:$J$175,$B41),0) -> 0 | D41: =IFERROR(SUMIFS('MGZ BBVA'!$N$2:$N$88,'MGZ BBVA'!$H$2:$H$88,"SALIDA",'MGZ BBVA'!$J$2:$J$88,$B41),0) -> 0 | E41: =IFERROR(SUMIFS('MGZ DOLARES'!$N$2:$N$2,'MGZ DOLARES'!$F$2:$F$2,"SALIDA",'MGZ DOLARES'!$J$2:$J$2,$B41),0) -> 0 | F41: =IFERROR(SUMIFS('MGZ BAJIO'!$N$2:$N$4,'MGZ BAJIO'!$H$2:$H$4,"SALIDA",'MGZ BAJIO'!$J$2:$J$4,$B41),0) -> 0 | G41: =IFERROR(SUMIFS('VICTOR BANAMEX'!$N$2:$N$65,'VICTOR BANAMEX'!$H$2:$H$65,"SALIDA",'VICTOR BANAMEX'!$J$2:$J$65,$B41),0) -> 0 | H41: =IFERROR(SUMIFS('VICTOR BANORTE'!$N$2:$N$9,'VICTOR BANORTE'!$H$2:$H$9,"SALIDA",'VICTOR BANORTE'!$J$2:$J$9,$B41),0) -> 0 | I41: =IFERROR(SUMIFS(RODRIGO!$N$2:$N$2,RODRIGO!$H$2:$H$2,"SALIDA",RODRIGO!$J$2:$J$2,$B41),0) -> 0 | J41: =IFERROR(SUMIFS(MOY!$N$2:$N$12,MOY!$H$2:$H$12,"SALIDA",MOY!$J$2:$J$12,$B41),0) -> 0 | K41: =IFERROR(SUMIFS('NORMA RUTH'!$N$2:$N$12,'NORMA RUTH'!$H$2:$H$12,"SALIDA",'NORMA RUTH'!$J$2:$J$12,$B41),0) -> 0 | L41: =IFERROR(SUMIFS(VALERIA!$N$2:$N$10,VALERIA!$H$2:$H$10,"SALIDA",VALERIA!$J$2:$J$10,$B41),0) -> 0 | M41: =IFERROR(SUMIFS('MANUEL BANAMEX'!$N$2:$N$25,'MANUEL BANAMEX'!$H$2:$H$25,"SALIDA",'MANUEL BANAMEX'!$J$2:$J$25,$B41),0) -> 0 | N41: =IFERROR(SUMIFS(ROBERTO!$N$2:$N$2,ROBERTO!$H$2:$H$2,"SALIDA",ROBERTO!$J$2:$J$2,$B41),0) -> 0 | O41: =IFERROR(SUMIFS(JUAN!$N$2:$N$11,JUAN!$H$2:$H$11,"SALIDA",JUAN!$J$2:$J$11,$B41),0) -> 0 | P41: =IFERROR(SUMIFS('NORMA SANCHEZ'!$N$2:$N$14,'NORMA SANCHEZ'!$H$2:$H$14,"SALIDA",'NORMA SANCHEZ'!$J$2:$J$14,$B41),0) -> 0 | Q41: =IFERROR(SUMIFS('JOSE CARLOS'!$N$2:$N$16,'JOSE CARLOS'!$H$2:$H$16,"SALIDA",'JOSE CARLOS'!$J$2:$J$16,$B41),0) -> 0 | R41: =IFERROR(SUMIFS('LUIS ENRIQUE '!$N$2:$N$21,'LUIS ENRIQUE '!$H$2:$H$21,"SALIDA",'LUIS ENRIQUE '!$J$2:$J$21,$B41),0) -> 0 | S41: =IFERROR(SUMIFS(CESARIA!$N$2:$N$15,CESARIA!$H$2:$H$15,"SALIDA",CESARIA!$J$2:$J$15,$B41),0) -> 0 | T41: =IFERROR(SUMIFS(ALAN!$N$2:$N$14,ALAN!$H$2:$H$14,"SALIDA",ALAN!$J$2:$J$14,$B41),0) -> 0 | U41: =IFERROR(SUMIFS(ELVIA!$N$2:$N$6,ELVIA!$H$2:$H$6,"SALIDA",ELVIA!$J$2:$J$6,$B41),0) -> 0 | V41: =IFERROR(SUMIFS(CAJA!$N$2:$N$586,CAJA!$H$2:$H$586,"SALIDA",CAJA!$J$2:$J$586,$B41),0) -> 745 | W41: =IFERROR(SUMIFS('CAJA TIGRES'!$N$2:$N$139,'CAJA TIGRES'!$H$2:$H$139,"SALIDA",'CAJA TIGRES'!$J$2:$J$139,$B41),0) -> 0 | X41: =IFERROR(SUMIFS(RESERVA!$N$2:$N$2,RESERVA!$H$2:$H$2,"SALIDA",RESERVA!$J$2:$J$2,$B41),0) -> 0 | Y41: =SUM(C41:X41) -> 745 | Z41: =Y41 -> 745
B42: LLANTAS Y SERVICIOS ALINEACION-BALANCEO | C42: =IFERROR(SUMIFS('MGZ121'!$N$2:$N$175,'MGZ121'!H$2:H$175,"SALIDA",'MGZ121'!$J$2:$J$175,$B42),0) -> 0 | D42: =IFERROR(SUMIFS('MGZ BBVA'!$N$2:$N$88,'MGZ BBVA'!$H$2:$H$88,"SALIDA",'MGZ BBVA'!$J$2:$J$88,$B42),0) -> 29004 | E42: =IFERROR(SUMIFS('MGZ DOLARES'!$N$2:$N$2,'MGZ DOLARES'!$F$2:$F$2,"SALIDA",'MGZ DOLARES'!$J$2:$J$2,$B42),0) -> 0 | F42: =IFERROR(SUMIFS('MGZ BAJIO'!$N$2:$N$4,'MGZ BAJIO'!$H$2:$H$4,"SALIDA",'MGZ BAJIO'!$J$2:$J$4,$B42),0) -> 0 | G42: =IFERROR(SUMIFS('VICTOR BANAMEX'!$N$2:$N$65,'VICTOR BANAMEX'!$H$2:$H$65,"SALIDA",'VICTOR BANAMEX'!$J$2:$J$65,$B42),0) -> 0 | H42: =IFERROR(SUMIFS('VICTOR BANORTE'!$N$2:$N$9,'VICTOR BANORTE'!$H$2:$H$9,"SALIDA",'VICTOR BANORTE'!$J$2:$J$9,$B42),0) -> 0 | I42: =IFERROR(SUMIFS(RODRIGO!$N$2:$N$2,RODRIGO!$H$2:$H$2,"SALIDA",RODRIGO!$J$2:$J$2,$B42),0) -> 0 | J42: =IFERROR(SUMIFS(MOY!$N$2:$N$12,MOY!$H$2:$H$12,"SALIDA",MOY!$J$2:$J$12,$B42),0) -> 0 | K42: =IFERROR(SUMIFS('NORMA RUTH'!$N$2:$N$12,'NORMA RUTH'!$H$2:$H$12,"SALIDA",'NORMA RUTH'!$J$2:$J$12,$B42),0) -> 0 | L42: =IFERROR(SUMIFS(VALERIA!$N$2:$N$10,VALERIA!$H$2:$H$10,"SALIDA",VALERIA!$J$2:$J$10,$B42),0) -> 0 | M42: =IFERROR(SUMIFS('MANUEL BANAMEX'!$N$2:$N$25,'MANUEL BANAMEX'!$H$2:$H$25,"SALIDA",'MANUEL BANAMEX'!$J$2:$J$25,$B42),0) -> 0 | N42: =IFERROR(SUMIFS(ROBERTO!$N$2:$N$2,ROBERTO!$H$2:$H$2,"SALIDA",ROBERTO!$J$2:$J$2,$B42),0) -> 0 | O42: =IFERROR(SUMIFS(JUAN!$N$2:$N$11,JUAN!$H$2:$H$11,"SALIDA",JUAN!$J$2:$J$11,$B42),0) -> 0 | P42: =IFERROR(SUMIFS('NORMA SANCHEZ'!$N$2:$N$14,'NORMA SANCHEZ'!$H$2:$H$14,"SALIDA",'NORMA SANCHEZ'!$J$2:$J$14,$B42),0) -> 0 | Q42: =IFERROR(SUMIFS('JOSE CARLOS'!$N$2:$N$16,'JOSE CARLOS'!$H$2:$H$16,"SALIDA",'JOSE CARLOS'!$J$2:$J$16,$B42),0) -> 0 | R42: =IFERROR(SUMIFS('LUIS ENRIQUE '!$N$2:$N$21,'LUIS ENRIQUE '!$H$2:$H$21,"SALIDA",'LUIS ENRIQUE '!$J$2:$J$21,$B42),0) -> 0 | S42: =IFERROR(SUMIFS(CESARIA!$N$2:$N$15,CESARIA!$H$2:$H$15,"SALIDA",CESARIA!$J$2:$J$15,$B42),0) -> 0 | T42: =IFERROR(SUMIFS(ALAN!$N$2:$N$14,ALAN!$H$2:$H$14,"SALIDA",ALAN!$J$2:$J$14,$B42),0) -> 0 | U42: =IFERROR(SUMIFS(ELVIA!$N$2:$N$6,ELVIA!$H$2:$H$6,"SALIDA",ELVIA!$J$2:$J$6,$B42),0) -> 0 | V42: =IFERROR(SUMIFS(CAJA!$N$2:$N$586,CAJA!$H$2:$H$586,"SALIDA",CAJA!$J$2:$J$586,$B42),0) -> 0 | W42: =IFERROR(SUMIFS('CAJA TIGRES'!$N$2:$N$139,'CAJA TIGRES'!$H$2:$H$139,"SALIDA",'CAJA TIGRES'!$J$2:$J$139,$B42),0) -> 0 | X42: =IFERROR(SUMIFS(RESERVA!$N$2:$N$2,RESERVA!$H$2:$H$2,"SALIDA",RESERVA!$J$2:$J$2,$B42),0) -> 0 | Y42: =SUM(C42:X42) -> 29004 | Z42: =Y42 -> 29004
B43: LAVADO Y ENGRASADO VEHICULOS | C43: =IFERROR(SUMIFS('MGZ121'!$N$2:$N$175,'MGZ121'!H$2:H$175,"SALIDA",'MGZ121'!$J$2:$J$175,$B43),0) -> 0 | D43: =IFERROR(SUMIFS('MGZ BBVA'!$N$2:$N$88,'MGZ BBVA'!$H$2:$H$88,"SALIDA",'MGZ BBVA'!$J$2:$J$88,$B43),0) -> 0 | E43: =IFERROR(SUMIFS('MGZ DOLARES'!$N$2:$N$2,'MGZ DOLARES'!$F$2:$F$2,"SALIDA",'MGZ DOLARES'!$J$2:$J$2,$B43),0) -> 0 | F43: =IFERROR(SUMIFS('MGZ BAJIO'!$N$2:$N$4,'MGZ BAJIO'!$H$2:$H$4,"SALIDA",'MGZ BAJIO'!$J$2:$J$4,$B43),0) -> 0 | G43: =IFERROR(SUMIFS('VICTOR BANAMEX'!$N$2:$N$65,'VICTOR BANAMEX'!$H$2:$H$65,"SALIDA",'VICTOR BANAMEX'!$J$2:$J$65,$B43),0) -> 0 | H43: =IFERROR(SUMIFS('VICTOR BANORTE'!$N$2:$N$9,'VICTOR BANORTE'!$H$2:$H$9,"SALIDA",'VICTOR BANORTE'!$J$2:$J$9,$B43),0) -> 0 | I43: =IFERROR(SUMIFS(RODRIGO!$N$2:$N$2,RODRIGO!$H$2:$H$2,"SALIDA",RODRIGO!$J$2:$J$2,$B43),0) -> 0 | J43: =IFERROR(SUMIFS(MOY!$N$2:$N$12,MOY!$H$2:$H$12,"SALIDA",MOY!$J$2:$J$12,$B43),0) -> 0 | K43: =IFERROR(SUMIFS('NORMA RUTH'!$N$2:$N$12,'NORMA RUTH'!$H$2:$H$12,"SALIDA",'NORMA RUTH'!$J$2:$J$12,$B43),0) -> 0 | L43: =IFERROR(SUMIFS(VALERIA!$N$2:$N$10,VALERIA!$H$2:$H$10,"SALIDA",VALERIA!$J$2:$J$10,$B43),0) -> 0 | M43: =IFERROR(SUMIFS('MANUEL BANAMEX'!$N$2:$N$25,'MANUEL BANAMEX'!$H$2:$H$25,"SALIDA",'MANUEL BANAMEX'!$J$2:$J$25,$B43),0) -> 0 | N43: =IFERROR(SUMIFS(ROBERTO!$N$2:$N$2,ROBERTO!$H$2:$H$2,"SALIDA",ROBERTO!$J$2:$J$2,$B43),0) -> 0 | O43: =IFERROR(SUMIFS(JUAN!$N$2:$N$11,JUAN!$H$2:$H$11,"SALIDA",JUAN!$J$2:$J$11,$B43),0) -> 0 | P43: =IFERROR(SUMIFS('NORMA SANCHEZ'!$N$2:$N$14,'NORMA SANCHEZ'!$H$2:$H$14,"SALIDA",'NORMA SANCHEZ'!$J$2:$J$14,$B43),0) -> 0 | Q43: =IFERROR(SUMIFS('JOSE CARLOS'!$N$2:$N$16,'JOSE CARLOS'!$H$2:$H$16,"SALIDA",'JOSE CARLOS'!$J$2:$J$16,$B43),0) -> 0 | R43: =IFERROR(SUMIFS('LUIS ENRIQUE '!$N$2:$N$21,'LUIS ENRIQUE '!$H$2:$H$21,"SALIDA",'LUIS ENRIQUE '!$J$2:$J$21,$B43),0) -> 0 | S43: =IFERROR(SUMIFS(CESARIA!$N$2:$N$15,CESARIA!$H$2:$H$15,"SALIDA",CESARIA!$J$2:$J$15,$B43),0) -> 0 | T43: =IFERROR(SUMIFS(ALAN!$N$2:$N$14,ALAN!$H$2:$H$14,"SALIDA",ALAN!$J$2:$J$14,$B43),0) -> 0 | U43: =IFERROR(SUMIFS(ELVIA!$N$2:$N$6,ELVIA!$H$2:$H$6,"SALIDA",ELVIA!$J$2:$J$6,$B43),0) -> 0 | V43: =IFERROR(SUMIFS(CAJA!$N$2:$N$586,CAJA!$H$2:$H$586,"SALIDA",CAJA!$J$2:$J$586,$B43),0) -> 6670 | W43: =IFERROR(SUMIFS('CAJA TIGRES'!$N$2:$N$139,'CAJA TIGRES'!$H$2:$H$139,"SALIDA",'CAJA TIGRES'!$J$2:$J$139,$B43),0) -> 750 | X43: =IFERROR(SUMIFS(RESERVA!$N$2:$N$2,RESERVA!$H$2:$H$2,"SALIDA",RESERVA!$J$2:$J$2,$B43),0) -> 0 | Y43: =SUM(C43:X43) -> 7420 | Z43: =Y43 -> 7420
B44: RENTA TIERRAS | C44: =IFERROR(SUMIFS('MGZ121'!$N$2:$N$175,'MGZ121'!H$2:H$175,"SALIDA",'MGZ121'!$J$2:$J$175,$B44),0) -> 0 | D44: =IFERROR(SUMIFS('MGZ BBVA'!$N$2:$N$88,'MGZ BBVA'!$H$2:$H$88,"SALIDA",'MGZ BBVA'!$J$2:$J$88,$B44),0) -> 0 | E44: =IFERROR(SUMIFS('MGZ DOLARES'!$N$2:$N$2,'MGZ DOLARES'!$F$2:$F$2,"SALIDA",'MGZ DOLARES'!$J$2:$J$2,$B44),0) -> 0 | F44: =IFERROR(SUMIFS('MGZ BAJIO'!$N$2:$N$4,'MGZ BAJIO'!$H$2:$H$4,"SALIDA",'MGZ BAJIO'!$J$2:$J$4,$B44),0) -> 0 | G44: =IFERROR(SUMIFS('VICTOR BANAMEX'!$N$2:$N$65,'VICTOR BANAMEX'!$H$2:$H$65,"SALIDA",'VICTOR BANAMEX'!$J$2:$J$65,$B44),0) -> 0 | H44: =IFERROR(SUMIFS('VICTOR BANORTE'!$N$2:$N$9,'VICTOR BANORTE'!$H$2:$H$9,"SALIDA",'VICTOR BANORTE'!$J$2:$J$9,$B44),0) -> 0 | I44: =IFERROR(SUMIFS(RODRIGO!$N$2:$N$2,RODRIGO!$H$2:$H$2,"SALIDA",RODRIGO!$J$2:$J$2,$B44),0) -> 0 | J44: =IFERROR(SUMIFS(MOY!$N$2:$N$12,MOY!$H$2:$H$12,"SALIDA",MOY!$J$2:$J$12,$B44),0) -> 0 | K44: =IFERROR(SUMIFS('NORMA RUTH'!$N$2:$N$12,'NORMA RUTH'!$H$2:$H$12,"SALIDA",'NORMA RUTH'!$J$2:$J$12,$B44),0) -> 0 | L44: =IFERROR(SUMIFS(VALERIA!$N$2:$N$10,VALERIA!$H$2:$H$10,"SALIDA",VALERIA!$J$2:$J$10,$B44),0) -> 0 | M44: =IFERROR(SUMIFS('MANUEL BANAMEX'!$N$2:$N$25,'MANUEL BANAMEX'!$H$2:$H$25,"SALIDA",'MANUEL BANAMEX'!$J$2:$J$25,$B44),0) -> 0 | N44: =IFERROR(SUMIFS(ROBERTO!$N$2:$N$2,ROBERTO!$H$2:$H$2,"SALIDA",ROBERTO!$J$2:$J$2,$B44),0) -> 0 | O44: =IFERROR(SUMIFS(JUAN!$N$2:$N$11,JUAN!$H$2:$H$11,"SALIDA",JUAN!$J$2:$J$11,$B44),0) -> 0 | P44: =IFERROR(SUMIFS('NORMA SANCHEZ'!$N$2:$N$14,'NORMA SANCHEZ'!$H$2:$H$14,"SALIDA",'NORMA SANCHEZ'!$J$2:$J$14,$B44),0) -> 0 | Q44: =IFERROR(SUMIFS('JOSE CARLOS'!$N$2:$N$16,'JOSE CARLOS'!$H$2:$H$16,"SALIDA",'JOSE CARLOS'!$J$2:$J$16,$B44),0) -> 0 | R44: =IFERROR(SUMIFS('LUIS ENRIQUE '!$N$2:$N$21,'LUIS ENRIQUE '!$H$2:$H$21,"SALIDA",'LUIS ENRIQUE '!$J$2:$J$21,$B44),0) -> 0 | S44: =IFERROR(SUMIFS(CESARIA!$N$2:$N$15,CESARIA!$H$2:$H$15,"SALIDA",CESARIA!$J$2:$J$15,$B44),0) -> 0 | T44: =IFERROR(SUMIFS(ALAN!$N$2:$N$14,ALAN!$H$2:$H$14,"SALIDA",ALAN!$J$2:$J$14,$B44),0) -> 0 | U44: =IFERROR(SUMIFS(ELVIA!$N$2:$N$6,ELVIA!$H$2:$H$6,"SALIDA",ELVIA!$J$2:$J$6,$B44),0) -> 0 | V44: =IFERROR(SUMIFS(CAJA!$N$2:$N$586,CAJA!$H$2:$H$586,"SALIDA",CAJA!$J$2:$J$586,$B44),0) -> 0 | W44: =IFERROR(SUMIFS('CAJA TIGRES'!$N$2:$N$139,'CAJA TIGRES'!$H$2:$H$139,"SALIDA",'CAJA TIGRES'!$J$2:$J$139,$B44),0) -> 0 | X44: =IFERROR(SUMIFS(RESERVA!$N$2:$N$2,RESERVA!$H$2:$H$2,"SALIDA",RESERVA!$J$2:$J$2,$B44),0) -> 0 | Y44: =SUM(C44:X44) -> 0 | Z44: =Y44 -> 0
B45: ARRENDAMIENTO OFICINA/BODEGA | C45: =IFERROR(SUMIFS('MGZ121'!$N$2:$N$175,'MGZ121'!H$2:H$175,"SALIDA",'MGZ121'!$J$2:$J$175,$B45),0) -> 0 | D45: =IFERROR(SUMIFS('MGZ BBVA'!$N$2:$N$88,'MGZ BBVA'!$H$2:$H$88,"SALIDA",'MGZ BBVA'!$J$2:$J$88,$B45),0) -> 0 | E45: =IFERROR(SUMIFS('MGZ DOLARES'!$N$2:$N$2,'MGZ DOLARES'!$F$2:$F$2,"SALIDA",'MGZ DOLARES'!$J$2:$J$2,$B45),0) -> 0 | F45: =IFERROR(SUMIFS('MGZ BAJIO'!$N$2:$N$4,'MGZ BAJIO'!$H$2:$H$4,"SALIDA",'MGZ BAJIO'!$J$2:$J$4,$B45),0) -> 0 | G45: =IFERROR(SUMIFS('VICTOR BANAMEX'!$N$2:$N$65,'VICTOR BANAMEX'!$H$2:$H$65,"SALIDA",'VICTOR BANAMEX'!$J$2:$J$65,$B45),0) -> 0 | H45: =IFERROR(SUMIFS('VICTOR BANORTE'!$N$2:$N$9,'VICTOR BANORTE'!$H$2:$H$9,"SALIDA",'VICTOR BANORTE'!$J$2:$J$9,$B45),0) -> 0 | I45: =IFERROR(SUMIFS(RODRIGO!$N$2:$N$2,RODRIGO!$H$2:$H$2,"SALIDA",RODRIGO!$J$2:$J$2,$B45),0) -> 0 | J45: =IFERROR(SUMIFS(MOY!$N$2:$N$12,MOY!$H$2:$H$12,"SALIDA",MOY!$J$2:$J$12,$B45),0) -> 0 | K45: =IFERROR(SUMIFS('NORMA RUTH'!$N$2:$N$12,'NORMA RUTH'!$H$2:$H$12,"SALIDA",'NORMA RUTH'!$J$2:$J$12,$B45),0) -> 0 | L45: =IFERROR(SUMIFS(VALERIA!$N$2:$N$10,VALERIA!$H$2:$H$10,"SALIDA",VALERIA!$J$2:$J$10,$B45),0) -> 0 | M45: =IFERROR(SUMIFS('MANUEL BANAMEX'!$N$2:$N$25,'MANUEL BANAMEX'!$H$2:$H$25,"SALIDA",'MANUEL BANAMEX'!$J$2:$J$25,$B45),0) -> 0 | N45: =IFERROR(SUMIFS(ROBERTO!$N$2:$N$2,ROBERTO!$H$2:$H$2,"SALIDA",ROBERTO!$J$2:$J$2,$B45),0) -> 0 | O45: =IFERROR(SUMIFS(JUAN!$N$2:$N$11,JUAN!$H$2:$H$11,"SALIDA",JUAN!$J$2:$J$11,$B45),0) -> 0 | P45: =IFERROR(SUMIFS('NORMA SANCHEZ'!$N$2:$N$14,'NORMA SANCHEZ'!$H$2:$H$14,"SALIDA",'NORMA SANCHEZ'!$J$2:$J$14,$B45),0) -> 0 | Q45: =IFERROR(SUMIFS('JOSE CARLOS'!$N$2:$N$16,'JOSE CARLOS'!$H$2:$H$16,"SALIDA",'JOSE CARLOS'!$J$2:$J$16,$B45),0) -> 0 | R45: =IFERROR(SUMIFS('LUIS ENRIQUE '!$N$2:$N$21,'LUIS ENRIQUE '!$H$2:$H$21,"SALIDA",'LUIS ENRIQUE '!$J$2:$J$21,$B45),0) -> 0 | S45: =IFERROR(SUMIFS(CESARIA!$N$2:$N$15,CESARIA!$H$2:$H$15,"SALIDA",CESARIA!$J$2:$J$15,$B45),0) -> 0 | T45: =IFERROR(SUMIFS(ALAN!$N$2:$N$14,ALAN!$H$2:$H$14,"SALIDA",ALAN!$J$2:$J$14,$B45),0) -> 0 | U45: =IFERROR(SUMIFS(ELVIA!$N$2:$N$6,ELVIA!$H$2:$H$6,"SALIDA",ELVIA!$J$2:$J$6,$B45),0) -> 0 | V45: =IFERROR(SUMIFS(CAJA!$N$2:$N$586,CAJA!$H$2:$H$586,"SALIDA",CAJA!$J$2:$J$586,$B45),0) -> 2000 | W45: =IFERROR(SUMIFS('CAJA TIGRES'!$N$2:$N$139,'CAJA TIGRES'!$H$2:$H$139,"SALIDA",'CAJA TIGRES'!$J$2:$J$139,$B45),0) -> 4000 | X45: =IFERROR(SUMIFS(RESERVA!$N$2:$N$2,RESERVA!$H$2:$H$2,"SALIDA",RESERVA!$J$2:$J$2,$B45),0) -> 0 | Y45: =SUM(C45:X45) -> 6000 | Z45: =Y45 -> 6000
B46: MTTO INSTALACIONES | C46: =IFERROR(SUMIFS('MGZ121'!$N$2:$N$175,'MGZ121'!H$2:H$175,"SALIDA",'MGZ121'!$J$2:$J$175,$B46),0) -> 0 | D46: =IFERROR(SUMIFS('MGZ BBVA'!$N$2:$N$88,'MGZ BBVA'!$H$2:$H$88,"SALIDA",'MGZ BBVA'!$J$2:$J$88,$B46),0) -> 0 | E46: =IFERROR(SUMIFS('MGZ DOLARES'!$N$2:$N$2,'MGZ DOLARES'!$F$2:$F$2,"SALIDA",'MGZ DOLARES'!$J$2:$J$2,$B46),0) -> 0 | F46: =IFERROR(SUMIFS('MGZ BAJIO'!$N$2:$N$4,'MGZ BAJIO'!$H$2:$H$4,"SALIDA",'MGZ BAJIO'!$J$2:$J$4,$B46),0) -> 0 | G46: =IFERROR(SUMIFS('VICTOR BANAMEX'!$N$2:$N$65,'VICTOR BANAMEX'!$H$2:$H$65,"SALIDA",'VICTOR BANAMEX'!$J$2:$J$65,$B46),0) -> 0 | H46: =IFERROR(SUMIFS('VICTOR BANORTE'!$N$2:$N$9,'VICTOR BANORTE'!$H$2:$H$9,"SALIDA",'VICTOR BANORTE'!$J$2:$J$9,$B46),0) -> 0 | I46: =IFERROR(SUMIFS(RODRIGO!$N$2:$N$2,RODRIGO!$H$2:$H$2,"SALIDA",RODRIGO!$J$2:$J$2,$B46),0) -> 0 | J46: =IFERROR(SUMIFS(MOY!$N$2:$N$12,MOY!$H$2:$H$12,"SALIDA",MOY!$J$2:$J$12,$B46),0) -> 0 | K46: =IFERROR(SUMIFS('NORMA RUTH'!$N$2:$N$12,'NORMA RUTH'!$H$2:$H$12,"SALIDA",'NORMA RUTH'!$J$2:$J$12,$B46),0) -> 0 | L46: =IFERROR(SUMIFS(VALERIA!$N$2:$N$10,VALERIA!$H$2:$H$10,"SALIDA",VALERIA!$J$2:$J$10,$B46),0) -> 0 | M46: =IFERROR(SUMIFS('MANUEL BANAMEX'!$N$2:$N$25,'MANUEL BANAMEX'!$H$2:$H$25,"SALIDA",'MANUEL BANAMEX'!$J$2:$J$25,$B46),0) -> 0 | N46: =IFERROR(SUMIFS(ROBERTO!$N$2:$N$2,ROBERTO!$H$2:$H$2,"SALIDA",ROBERTO!$J$2:$J$2,$B46),0) -> 0 | O46: =IFERROR(SUMIFS(JUAN!$N$2:$N$11,JUAN!$H$2:$H$11,"SALIDA",JUAN!$J$2:$J$11,$B46),0) -> 0 | P46: =IFERROR(SUMIFS('NORMA SANCHEZ'!$N$2:$N$14,'NORMA SANCHEZ'!$H$2:$H$14,"SALIDA",'NORMA SANCHEZ'!$J$2:$J$14,$B46),0) -> 0 | Q46: =IFERROR(SUMIFS('JOSE CARLOS'!$N$2:$N$16,'JOSE CARLOS'!$H$2:$H$16,"SALIDA",'JOSE CARLOS'!$J$2:$J$16,$B46),0) -> 0 | R46: =IFERROR(SUMIFS('LUIS ENRIQUE '!$N$2:$N$21,'LUIS ENRIQUE '!$H$2:$H$21,"SALIDA",'LUIS ENRIQUE '!$J$2:$J$21,$B46),0) -> 0 | S46: =IFERROR(SUMIFS(CESARIA!$N$2:$N$15,CESARIA!$H$2:$H$15,"SALIDA",CESARIA!$J$2:$J$15,$B46),0) -> 0 | T46: =IFERROR(SUMIFS(ALAN!$N$2:$N$14,ALAN!$H$2:$H$14,"SALIDA",ALAN!$J$2:$J$14,$B46),0) -> 0 | U46: =IFERROR(SUMIFS(ELVIA!$N$2:$N$6,ELVIA!$H$2:$H$6,"SALIDA",ELVIA!$J$2:$J$6,$B46),0) -> 0 | V46: =IFERROR(SUMIFS(CAJA!$N$2:$N$586,CAJA!$H$2:$H$586,"SALIDA",CAJA!$J$2:$J$586,$B46),0) -> 0 | W46: =IFERROR(SUMIFS('CAJA TIGRES'!$N$2:$N$139,'CAJA TIGRES'!$H$2:$H$139,"SALIDA",'CAJA TIGRES'!$J$2:$J$139,$B46),0) -> 0 | X46: =IFERROR(SUMIFS(RESERVA!$N$2:$N$2,RESERVA!$H$2:$H$2,"SALIDA",RESERVA!$J$2:$J$2,$B46),0) -> 0 | Y46: =SUM(C46:X46) -> 0 | Z46: =Y46 -> 0
B47: DESCARGA DE PRODUCTOS | C47: =IFERROR(SUMIFS('MGZ121'!$N$2:$N$175,'MGZ121'!H$2:H$175,"SALIDA",'MGZ121'!$J$2:$J$175,$B47),0) -> 0 | D47: =IFERROR(SUMIFS('MGZ BBVA'!$N$2:$N$88,'MGZ BBVA'!$H$2:$H$88,"SALIDA",'MGZ BBVA'!$J$2:$J$88,$B47),0) -> 0 | E47: =IFERROR(SUMIFS('MGZ DOLARES'!$N$2:$N$2,'MGZ DOLARES'!$F$2:$F$2,"SALIDA",'MGZ DOLARES'!$J$2:$J$2,$B47),0) -> 0 | F47: =IFERROR(SUMIFS('MGZ BAJIO'!$N$2:$N$4,'MGZ BAJIO'!$H$2:$H$4,"SALIDA",'MGZ BAJIO'!$J$2:$J$4,$B47),0) -> 0 | G47: =IFERROR(SUMIFS('VICTOR BANAMEX'!$N$2:$N$65,'VICTOR BANAMEX'!$H$2:$H$65,"SALIDA",'VICTOR BANAMEX'!$J$2:$J$65,$B47),0) -> 0 | H47: =IFERROR(SUMIFS('VICTOR BANORTE'!$N$2:$N$9,'VICTOR BANORTE'!$H$2:$H$9,"SALIDA",'VICTOR BANORTE'!$J$2:$J$9,$B47),0) -> 0 | I47: =IFERROR(SUMIFS(RODRIGO!$N$2:$N$2,RODRIGO!$H$2:$H$2,"SALIDA",RODRIGO!$J$2:$J$2,$B47),0) -> 0 | J47: =IFERROR(SUMIFS(MOY!$N$2:$N$12,MOY!$H$2:$H$12,"SALIDA",MOY!$J$2:$J$12,$B47),0) -> 0 | K47: =IFERROR(SUMIFS('NORMA RUTH'!$N$2:$N$12,'NORMA RUTH'!$H$2:$H$12,"SALIDA",'NORMA RUTH'!$J$2:$J$12,$B47),0) -> 0 | L47: =IFERROR(SUMIFS(VALERIA!$N$2:$N$10,VALERIA!$H$2:$H$10,"SALIDA",VALERIA!$J$2:$J$10,$B47),0) -> 0 | M47: =IFERROR(SUMIFS('MANUEL BANAMEX'!$N$2:$N$25,'MANUEL BANAMEX'!$H$2:$H$25,"SALIDA",'MANUEL BANAMEX'!$J$2:$J$25,$B47),0) -> 0 | N47: =IFERROR(SUMIFS(ROBERTO!$N$2:$N$2,ROBERTO!$H$2:$H$2,"SALIDA",ROBERTO!$J$2:$J$2,$B47),0) -> 0 | O47: =IFERROR(SUMIFS(JUAN!$N$2:$N$11,JUAN!$H$2:$H$11,"SALIDA",JUAN!$J$2:$J$11,$B47),0) -> 0 | P47: =IFERROR(SUMIFS('NORMA SANCHEZ'!$N$2:$N$14,'NORMA SANCHEZ'!$H$2:$H$14,"SALIDA",'NORMA SANCHEZ'!$J$2:$J$14,$B47),0) -> 0 | Q47: =IFERROR(SUMIFS('JOSE CARLOS'!$N$2:$N$16,'JOSE CARLOS'!$H$2:$H$16,"SALIDA",'JOSE CARLOS'!$J$2:$J$16,$B47),0) -> 0 | R47: =IFERROR(SUMIFS('LUIS ENRIQUE '!$N$2:$N$21,'LUIS ENRIQUE '!$H$2:$H$21,"SALIDA",'LUIS ENRIQUE '!$J$2:$J$21,$B47),0) -> 0 | S47: =IFERROR(SUMIFS(CESARIA!$N$2:$N$15,CESARIA!$H$2:$H$15,"SALIDA",CESARIA!$J$2:$J$15,$B47),0) -> 0 | T47: =IFERROR(SUMIFS(ALAN!$N$2:$N$14,ALAN!$H$2:$H$14,"SALIDA",ALAN!$J$2:$J$14,$B47),0) -> 0 | U47: =IFERROR(SUMIFS(ELVIA!$N$2:$N$6,ELVIA!$H$2:$H$6,"SALIDA",ELVIA!$J$2:$J$6,$B47),0) -> 0 | V47: =IFERROR(SUMIFS(CAJA!$N$2:$N$586,CAJA!$H$2:$H$586,"SALIDA",CAJA!$J$2:$J$586,$B47),0) -> 27139 | W47: =IFERROR(SUMIFS('CAJA TIGRES'!$N$2:$N$139,'CAJA TIGRES'!$H$2:$H$139,"SALIDA",'CAJA TIGRES'!$J$2:$J$139,$B47),0) -> 0 | X47: =IFERROR(SUMIFS(RESERVA!$N$2:$N$2,RESERVA!$H$2:$H$2,"SALIDA",RESERVA!$J$2:$J$2,$B47),0) -> 0 | Y47: =SUM(C47:X47) -> 27139 | Z47: =Y47 -> 27139
B48: PERDIDA EN VENTA FRUTA | C48: =IFERROR(SUMIFS('MGZ121'!$N$2:$N$175,'MGZ121'!H$2:H$175,"SALIDA",'MGZ121'!$J$2:$J$175,$B48),0) -> 0 | D48: =IFERROR(SUMIFS('MGZ BBVA'!$N$2:$N$88,'MGZ BBVA'!$H$2:$H$88,"SALIDA",'MGZ BBVA'!$J$2:$J$88,$B48),0) -> 0 | E48: =IFERROR(SUMIFS('MGZ DOLARES'!$N$2:$N$2,'MGZ DOLARES'!$F$2:$F$2,"SALIDA",'MGZ DOLARES'!$J$2:$J$2,$B48),0) -> 0 | F48: =IFERROR(SUMIFS('MGZ BAJIO'!$N$2:$N$4,'MGZ BAJIO'!$H$2:$H$4,"SALIDA",'MGZ BAJIO'!$J$2:$J$4,$B48),0) -> 0 | G48: =IFERROR(SUMIFS('VICTOR BANAMEX'!$N$2:$N$65,'VICTOR BANAMEX'!$H$2:$H$65,"SALIDA",'VICTOR BANAMEX'!$J$2:$J$65,$B48),0) -> 0 | H48: =IFERROR(SUMIFS('VICTOR BANORTE'!$N$2:$N$9,'VICTOR BANORTE'!$H$2:$H$9,"SALIDA",'VICTOR BANORTE'!$J$2:$J$9,$B48),0) -> 0 | I48: =IFERROR(SUMIFS(RODRIGO!$N$2:$N$2,RODRIGO!$H$2:$H$2,"SALIDA",RODRIGO!$J$2:$J$2,$B48),0) -> 0 | J48: =IFERROR(SUMIFS(MOY!$N$2:$N$12,MOY!$H$2:$H$12,"SALIDA",MOY!$J$2:$J$12,$B48),0) -> 0 | K48: =IFERROR(SUMIFS('NORMA RUTH'!$N$2:$N$12,'NORMA RUTH'!$H$2:$H$12,"SALIDA",'NORMA RUTH'!$J$2:$J$12,$B48),0) -> 0 | L48: =IFERROR(SUMIFS(VALERIA!$N$2:$N$10,VALERIA!$H$2:$H$10,"SALIDA",VALERIA!$J$2:$J$10,$B48),0) -> 0 | M48: =IFERROR(SUMIFS('MANUEL BANAMEX'!$N$2:$N$25,'MANUEL BANAMEX'!$H$2:$H$25,"SALIDA",'MANUEL BANAMEX'!$J$2:$J$25,$B48),0) -> 0 | N48: =IFERROR(SUMIFS(ROBERTO!$N$2:$N$2,ROBERTO!$H$2:$H$2,"SALIDA",ROBERTO!$J$2:$J$2,$B48),0) -> 0 | O48: =IFERROR(SUMIFS(JUAN!$N$2:$N$11,JUAN!$H$2:$H$11,"SALIDA",JUAN!$J$2:$J$11,$B48),0) -> 0 | P48: =IFERROR(SUMIFS('NORMA SANCHEZ'!$N$2:$N$14,'NORMA SANCHEZ'!$H$2:$H$14,"SALIDA",'NORMA SANCHEZ'!$J$2:$J$14,$B48),0) -> 0 | Q48: =IFERROR(SUMIFS('JOSE CARLOS'!$N$2:$N$16,'JOSE CARLOS'!$H$2:$H$16,"SALIDA",'JOSE CARLOS'!$J$2:$J$16,$B48),0) -> 0 | R48: =IFERROR(SUMIFS('LUIS ENRIQUE '!$N$2:$N$21,'LUIS ENRIQUE '!$H$2:$H$21,"SALIDA",'LUIS ENRIQUE '!$J$2:$J$21,$B48),0) -> 0 | S48: =IFERROR(SUMIFS(CESARIA!$N$2:$N$15,CESARIA!$H$2:$H$15,"SALIDA",CESARIA!$J$2:$J$15,$B48),0) -> 0 | T48: =IFERROR(SUMIFS(ALAN!$N$2:$N$14,ALAN!$H$2:$H$14,"SALIDA",ALAN!$J$2:$J$14,$B48),0) -> 0 | U48: =IFERROR(SUMIFS(ELVIA!$N$2:$N$6,ELVIA!$H$2:$H$6,"SALIDA",ELVIA!$J$2:$J$6,$B48),0) -> 0 | V48: =IFERROR(SUMIFS(CAJA!$N$2:$N$586,CAJA!$H$2:$H$586,"SALIDA",CAJA!$J$2:$J$586,$B48),0) -> 0 | W48: =IFERROR(SUMIFS('CAJA TIGRES'!$N$2:$N$139,'CAJA TIGRES'!$H$2:$H$139,"SALIDA",'CAJA TIGRES'!$J$2:$J$139,$B48),0) -> 0 | X48: =IFERROR(SUMIFS(RESERVA!$N$2:$N$2,RESERVA!$H$2:$H$2,"SALIDA",RESERVA!$J$2:$J$2,$B48),0) -> 0 | Y48: =SUM(C48:X48) -> 0 | Z48: =Y48 -> 0
A49: 6 | B49: ADMINISTRATIVO | C49: =SUM(C50:C59) -> 132325.39 | D49: =SUM(D50:D59) -> 44844 | E49: =SUM(E50:E59) -> 0 | F49: =SUM(F50:F59) -> 0 | G49: =SUM(G50:G59) -> 96653.61 | H49: =SUM(H50:H59) -> 0 | I49: =SUM(I50:I59) -> 0 | J49: =SUM(J50:J59) -> 0 | ... Z49: =SUM(Z50:Z59) -> 334764.97
A50: 6.1 | B50: ASESORIAS | C50: =IFERROR(SUMIFS('MGZ121'!$N$2:$N$175,'MGZ121'!H$2:H$175,"SALIDA",'MGZ121'!$J$2:$J$175,$B50),0) -> 0 | D50: =IFERROR(SUMIFS('MGZ BBVA'!$N$2:$N$88,'MGZ BBVA'!$H$2:$H$88,"SALIDA",'MGZ BBVA'!$J$2:$J$88,$B50),0) -> 0 | E50: =IFERROR(SUMIFS('MGZ DOLARES'!$N$2:$N$2,'MGZ DOLARES'!$F$2:$F$2,"SALIDA",'MGZ DOLARES'!$J$2:$J$2,$B50),0) -> 0 | F50: =IFERROR(SUMIFS('MGZ BAJIO'!$N$2:$N$4,'MGZ BAJIO'!$H$2:$H$4,"SALIDA",'MGZ BAJIO'!$J$2:$J$4,$B50),0) -> 0 | G50: =IFERROR(SUMIFS('VICTOR BANAMEX'!$N$2:$N$65,'VICTOR BANAMEX'!$H$2:$H$65,"SALIDA",'VICTOR BANAMEX'!$J$2:$J$65,$B50),0) -> 58960 | H50: =IFERROR(SUMIFS('VICTOR BANORTE'!$N$2:$N$9,'VICTOR BANORTE'!$H$2:$H$9,"SALIDA",'VICTOR BANORTE'!$J$2:$J$9,$B50),0) -> 0 | I50: =IFERROR(SUMIFS(RODRIGO!$N$2:$N$2,RODRIGO!$H$2:$H$2,"SALIDA",RODRIGO!$J$2:$J$2,$B50),0) -> 0 | J50: =IFERROR(SUMIFS(MOY!$N$2:$N$12,MOY!$H$2:$H$12,"SALIDA",MOY!$J$2:$J$12,$B50),0) -> 0 | K50: =IFERROR(SUMIFS('NORMA RUTH'!$N$2:$N$12,'NORMA RUTH'!$H$2:$H$12,"SALIDA",'NORMA RUTH'!$J$2:$J$12,$B50),0) -> 0 | L50: =IFERROR(SUMIFS(VALERIA!$N$2:$N$10,VALERIA!$H$2:$H$10,"SALIDA",VALERIA!$J$2:$J$10,$B50),0) -> 0 | M50: =IFERROR(SUMIFS('MANUEL BANAMEX'!$N$2:$N$25,'MANUEL BANAMEX'!$H$2:$H$25,"SALIDA",'MANUEL BANAMEX'!$J$2:$J$25,$B50),0) -> 0 | N50: =IFERROR(SUMIFS(ROBERTO!$N$2:$N$2,ROBERTO!$H$2:$H$2,"SALIDA",ROBERTO!$J$2:$J$2,$B50),0) -> 0 | O50: =IFERROR(SUMIFS(JUAN!$N$2:$N$11,JUAN!$H$2:$H$11,"SALIDA",JUAN!$J$2:$J$11,$B50),0) -> 0 | P50: =IFERROR(SUMIFS('NORMA SANCHEZ'!$N$2:$N$14,'NORMA SANCHEZ'!$H$2:$H$14,"SALIDA",'NORMA SANCHEZ'!$J$2:$J$14,$B50),0) -> 0 | Q50: =IFERROR(SUMIFS('JOSE CARLOS'!$N$2:$N$16,'JOSE CARLOS'!$H$2:$H$16,"SALIDA",'JOSE CARLOS'!$J$2:$J$16,$B50),0) -> 0 | R50: =IFERROR(SUMIFS('LUIS ENRIQUE '!$N$2:$N$21,'LUIS ENRIQUE '!$H$2:$H$21,"SALIDA",'LUIS ENRIQUE '!$J$2:$J$21,$B50),0) -> 0 | S50: =IFERROR(SUMIFS(CESARIA!$N$2:$N$15,CESARIA!$H$2:$H$15,"SALIDA",CESARIA!$J$2:$J$15,$B50),0) -> 0 | T50: =IFERROR(SUMIFS(ALAN!$N$2:$N$14,ALAN!$H$2:$H$14,"SALIDA",ALAN!$J$2:$J$14,$B50),0) -> 0 | U50: =IFERROR(SUMIFS(ELVIA!$N$2:$N$6,ELVIA!$H$2:$H$6,"SALIDA",ELVIA!$J$2:$J$6,$B50),0) -> 0 | V50: =IFERROR(SUMIFS(CAJA!$N$2:$N$586,CAJA!$H$2:$H$586,"SALIDA",CAJA!$J$2:$J$586,$B50),0) -> 4500 | W50: =IFERROR(SUMIFS('CAJA TIGRES'!$N$2:$N$139,'CAJA TIGRES'!$H$2:$H$139,"SALIDA",'CAJA TIGRES'!$J$2:$J$139,$B50),0) -> 0 | X50: =IFERROR(SUMIFS(RESERVA!$N$2:$N$2,RESERVA!$H$2:$H$2,"SALIDA",RESERVA!$J$2:$J$2,$B50),0) -> 0 | Y50: =SUM(C50:X50) -> 63460 | Z50: =Y50 -> 63460
A51: 6.2 | B51: SIPARE/IMSS | C51: =IFERROR(SUMIFS('MGZ121'!$N$2:$N$175,'MGZ121'!H$2:H$175,"SALIDA",'MGZ121'!$J$2:$J$175,$B51),0) -> 132325.39 | D51: =IFERROR(SUMIFS('MGZ BBVA'!$N$2:$N$88,'MGZ BBVA'!$H$2:$H$88,"SALIDA",'MGZ BBVA'!$J$2:$J$88,$B51),0) -> 0 | E51: =IFERROR(SUMIFS('MGZ DOLARES'!$N$2:$N$2,'MGZ DOLARES'!$F$2:$F$2,"SALIDA",'MGZ DOLARES'!$J$2:$J$2,$B51),0) -> 0 | F51: =IFERROR(SUMIFS('MGZ BAJIO'!$N$2:$N$4,'MGZ BAJIO'!$H$2:$H$4,"SALIDA",'MGZ BAJIO'!$J$2:$J$4,$B51),0) -> 0 | G51: =IFERROR(SUMIFS('VICTOR BANAMEX'!$N$2:$N$65,'VICTOR BANAMEX'!$H$2:$H$65,"SALIDA",'VICTOR BANAMEX'!$J$2:$J$65,$B51),0) -> 22324.73 | H51: =IFERROR(SUMIFS('VICTOR BANORTE'!$N$2:$N$9,'VICTOR BANORTE'!$H$2:$H$9,"SALIDA",'VICTOR BANORTE'!$J$2:$J$9,$B51),0) -> 0 | I51: =IFERROR(SUMIFS(RODRIGO!$N$2:$N$2,RODRIGO!$H$2:$H$2,"SALIDA",RODRIGO!$J$2:$J$2,$B51),0) -> 0 | J51: =IFERROR(SUMIFS(MOY!$N$2:$N$12,MOY!$H$2:$H$12,"SALIDA",MOY!$J$2:$J$12,$B51),0) -> 0 | K51: =IFERROR(SUMIFS('NORMA RUTH'!$N$2:$N$12,'NORMA RUTH'!$H$2:$H$12,"SALIDA",'NORMA RUTH'!$J$2:$J$12,$B51),0) -> 0 | L51: =IFERROR(SUMIFS(VALERIA!$N$2:$N$10,VALERIA!$H$2:$H$10,"SALIDA",VALERIA!$J$2:$J$10,$B51),0) -> 0 | M51: =IFERROR(SUMIFS('MANUEL BANAMEX'!$N$2:$N$25,'MANUEL BANAMEX'!$H$2:$H$25,"SALIDA",'MANUEL BANAMEX'!$J$2:$J$25,$B51),0) -> 0 | N51: =IFERROR(SUMIFS(ROBERTO!$N$2:$N$2,ROBERTO!$H$2:$H$2,"SALIDA",ROBERTO!$J$2:$J$2,$B51),0) -> 0 | O51: =IFERROR(SUMIFS(JUAN!$N$2:$N$11,JUAN!$H$2:$H$11,"SALIDA",JUAN!$J$2:$J$11,$B51),0) -> 3197.24 | P51: =IFERROR(SUMIFS('NORMA SANCHEZ'!$N$2:$N$14,'NORMA SANCHEZ'!$H$2:$H$14,"SALIDA",'NORMA SANCHEZ'!$J$2:$J$14,$B51),0) -> 0 | Q51: =IFERROR(SUMIFS('JOSE CARLOS'!$N$2:$N$16,'JOSE CARLOS'!$H$2:$H$16,"SALIDA",'JOSE CARLOS'!$J$2:$J$16,$B51),0) -> 0 | R51: =IFERROR(SUMIFS('LUIS ENRIQUE '!$N$2:$N$21,'LUIS ENRIQUE '!$H$2:$H$21,"SALIDA",'LUIS ENRIQUE '!$J$2:$J$21,$B51),0) -> 0 | S51: =IFERROR(SUMIFS(CESARIA!$N$2:$N$15,CESARIA!$H$2:$H$15,"SALIDA",CESARIA!$J$2:$J$15,$B51),0) -> 3197.24 | T51: =IFERROR(SUMIFS(ALAN!$N$2:$N$14,ALAN!$H$2:$H$14,"SALIDA",ALAN!$J$2:$J$14,$B51),0) -> 0 | U51: =IFERROR(SUMIFS(ELVIA!$N$2:$N$6,ELVIA!$H$2:$H$6,"SALIDA",ELVIA!$J$2:$J$6,$B51),0) -> 0 | V51: =IFERROR(SUMIFS(CAJA!$N$2:$N$586,CAJA!$H$2:$H$586,"SALIDA",CAJA!$J$2:$J$586,$B51),0) -> 9562.53 | W51: =IFERROR(SUMIFS('CAJA TIGRES'!$N$2:$N$139,'CAJA TIGRES'!$H$2:$H$139,"SALIDA",'CAJA TIGRES'!$J$2:$J$139,$B51),0) -> 0 | X51: =IFERROR(SUMIFS(RESERVA!$N$2:$N$2,RESERVA!$H$2:$H$2,"SALIDA",RESERVA!$J$2:$J$2,$B51),0) -> 0 | Y51: =SUM(C51:X51) -> 170607.13 | Z51: =Y51 -> 170607.13
B52: IMPUESTO ESTATAL | C52: =IFERROR(SUMIFS('MGZ121'!$N$2:$N$175,'MGZ121'!H$2:H$175,"SALIDA",'MGZ121'!$J$2:$J$175,$B52),0) -> 0 | D52: =IFERROR(SUMIFS('MGZ BBVA'!$N$2:$N$88,'MGZ BBVA'!$H$2:$H$88,"SALIDA",'MGZ BBVA'!$J$2:$J$88,$B52),0) -> 0 | E52: =IFERROR(SUMIFS('MGZ DOLARES'!$N$2:$N$2,'MGZ DOLARES'!$F$2:$F$2,"SALIDA",'MGZ DOLARES'!$J$2:$J$2,$B52),0) -> 0 | F52: =IFERROR(SUMIFS('MGZ BAJIO'!$N$2:$N$4,'MGZ BAJIO'!$H$2:$H$4,"SALIDA",'MGZ BAJIO'!$J$2:$J$4,$B52),0) -> 0 | G52: =IFERROR(SUMIFS('VICTOR BANAMEX'!$N$2:$N$65,'VICTOR BANAMEX'!$H$2:$H$65,"SALIDA",'VICTOR BANAMEX'!$J$2:$J$65,$B52),0) -> 0 | H52: =IFERROR(SUMIFS('VICTOR BANORTE'!$N$2:$N$9,'VICTOR BANORTE'!$H$2:$H$9,"SALIDA",'VICTOR BANORTE'!$J$2:$J$9,$B52),0) -> 0 | I52: =IFERROR(SUMIFS(RODRIGO!$N$2:$N$2,RODRIGO!$H$2:$H$2,"SALIDA",RODRIGO!$J$2:$J$2,$B52),0) -> 0 | J52: =IFERROR(SUMIFS(MOY!$N$2:$N$12,MOY!$H$2:$H$12,"SALIDA",MOY!$J$2:$J$12,$B52),0) -> 0 | K52: =IFERROR(SUMIFS('NORMA RUTH'!$N$2:$N$12,'NORMA RUTH'!$H$2:$H$12,"SALIDA",'NORMA RUTH'!$J$2:$J$12,$B52),0) -> 0 | L52: =IFERROR(SUMIFS(VALERIA!$N$2:$N$10,VALERIA!$H$2:$H$10,"SALIDA",VALERIA!$J$2:$J$10,$B52),0) -> 0 | M52: =IFERROR(SUMIFS('MANUEL BANAMEX'!$N$2:$N$25,'MANUEL BANAMEX'!$H$2:$H$25,"SALIDA",'MANUEL BANAMEX'!$J$2:$J$25,$B52),0) -> 0 | N52: =IFERROR(SUMIFS(ROBERTO!$N$2:$N$2,ROBERTO!$H$2:$H$2,"SALIDA",ROBERTO!$J$2:$J$2,$B52),0) -> 0 | O52: =IFERROR(SUMIFS(JUAN!$N$2:$N$11,JUAN!$H$2:$H$11,"SALIDA",JUAN!$J$2:$J$11,$B52),0) -> 0 | P52: =IFERROR(SUMIFS('NORMA SANCHEZ'!$N$2:$N$14,'NORMA SANCHEZ'!$H$2:$H$14,"SALIDA",'NORMA SANCHEZ'!$J$2:$J$14,$B52),0) -> 0 | Q52: =IFERROR(SUMIFS('JOSE CARLOS'!$N$2:$N$16,'JOSE CARLOS'!$H$2:$H$16,"SALIDA",'JOSE CARLOS'!$J$2:$J$16,$B52),0) -> 0 | R52: =IFERROR(SUMIFS('LUIS ENRIQUE '!$N$2:$N$21,'LUIS ENRIQUE '!$H$2:$H$21,"SALIDA",'LUIS ENRIQUE '!$J$2:$J$21,$B52),0) -> 0 | S52: =IFERROR(SUMIFS(CESARIA!$N$2:$N$15,CESARIA!$H$2:$H$15,"SALIDA",CESARIA!$J$2:$J$15,$B52),0) -> 0 | T52: =IFERROR(SUMIFS(ALAN!$N$2:$N$14,ALAN!$H$2:$H$14,"SALIDA",ALAN!$J$2:$J$14,$B52),0) -> 0 | U52: =IFERROR(SUMIFS(ELVIA!$N$2:$N$6,ELVIA!$H$2:$H$6,"SALIDA",ELVIA!$J$2:$J$6,$B52),0) -> 0 | V52: =IFERROR(SUMIFS(CAJA!$N$2:$N$586,CAJA!$H$2:$H$586,"SALIDA",CAJA!$J$2:$J$586,$B52),0) -> 0 | W52: =IFERROR(SUMIFS('CAJA TIGRES'!$N$2:$N$139,'CAJA TIGRES'!$H$2:$H$139,"SALIDA",'CAJA TIGRES'!$J$2:$J$139,$B52),0) -> 0 | X52: =IFERROR(SUMIFS(RESERVA!$N$2:$N$2,RESERVA!$H$2:$H$2,"SALIDA",RESERVA!$J$2:$J$2,$B52),0) -> 0 | Y52: =SUM(C52:X52) -> 0 | Z52: =Y52 -> 0
A53: 6.3 | B53: TELEFONOS/INTERNET | C53: =IFERROR(SUMIFS('MGZ121'!$N$2:$N$175,'MGZ121'!H$2:H$175,"SALIDA",'MGZ121'!$J$2:$J$175,$B53),0) -> 0 | D53: =IFERROR(SUMIFS('MGZ BBVA'!$N$2:$N$88,'MGZ BBVA'!$H$2:$H$88,"SALIDA",'MGZ BBVA'!$J$2:$J$88,$B53),0) -> 0 | E53: =IFERROR(SUMIFS('MGZ DOLARES'!$N$2:$N$2,'MGZ DOLARES'!$F$2:$F$2,"SALIDA",'MGZ DOLARES'!$J$2:$J$2,$B53),0) -> 0 | F53: =IFERROR(SUMIFS('MGZ BAJIO'!$N$2:$N$4,'MGZ BAJIO'!$H$2:$H$4,"SALIDA",'MGZ BAJIO'!$J$2:$J$4,$B53),0) -> 0 | G53: =IFERROR(SUMIFS('VICTOR BANAMEX'!$N$2:$N$65,'VICTOR BANAMEX'!$H$2:$H$65,"SALIDA",'VICTOR BANAMEX'!$J$2:$J$65,$B53),0) -> 14382.88 | H53: =IFERROR(SUMIFS('VICTOR BANORTE'!$N$2:$N$9,'VICTOR BANORTE'!$H$2:$H$9,"SALIDA",'VICTOR BANORTE'!$J$2:$J$9,$B53),0) -> 0 | I53: =IFERROR(SUMIFS(RODRIGO!$N$2:$N$2,RODRIGO!$H$2:$H$2,"SALIDA",RODRIGO!$J$2:$J$2,$B53),0) -> 0 | J53: =IFERROR(SUMIFS(MOY!$N$2:$N$12,MOY!$H$2:$H$12,"SALIDA",MOY!$J$2:$J$12,$B53),0) -> 0 | K53: =IFERROR(SUMIFS('NORMA RUTH'!$N$2:$N$12,'NORMA RUTH'!$H$2:$H$12,"SALIDA",'NORMA RUTH'!$J$2:$J$12,$B53),0) -> 0 | L53: =IFERROR(SUMIFS(VALERIA!$N$2:$N$10,VALERIA!$H$2:$H$10,"SALIDA",VALERIA!$J$2:$J$10,$B53),0) -> 0 | M53: =IFERROR(SUMIFS('MANUEL BANAMEX'!$N$2:$N$25,'MANUEL BANAMEX'!$H$2:$H$25,"SALIDA",'MANUEL BANAMEX'!$J$2:$J$25,$B53),0) -> 2610 | N53: =IFERROR(SUMIFS(ROBERTO!$N$2:$N$2,ROBERTO!$H$2:$H$2,"SALIDA",ROBERTO!$J$2:$J$2,$B53),0) -> 0 | O53: =IFERROR(SUMIFS(JUAN!$N$2:$N$11,JUAN!$H$2:$H$11,"SALIDA",JUAN!$J$2:$J$11,$B53),0) -> 0 | P53: =IFERROR(SUMIFS('NORMA SANCHEZ'!$N$2:$N$14,'NORMA SANCHEZ'!$H$2:$H$14,"SALIDA",'NORMA SANCHEZ'!$J$2:$J$14,$B53),0) -> 0 | Q53: =IFERROR(SUMIFS('JOSE CARLOS'!$N$2:$N$16,'JOSE CARLOS'!$H$2:$H$16,"SALIDA",'JOSE CARLOS'!$J$2:$J$16,$B53),0) -> 0 | R53: =IFERROR(SUMIFS('LUIS ENRIQUE '!$N$2:$N$21,'LUIS ENRIQUE '!$H$2:$H$21,"SALIDA",'LUIS ENRIQUE '!$J$2:$J$21,$B53),0) -> 0 | S53: =IFERROR(SUMIFS(CESARIA!$N$2:$N$15,CESARIA!$H$2:$H$15,"SALIDA",CESARIA!$J$2:$J$15,$B53),0) -> 0 | T53: =IFERROR(SUMIFS(ALAN!$N$2:$N$14,ALAN!$H$2:$H$14,"SALIDA",ALAN!$J$2:$J$14,$B53),0) -> 0 | U53: =IFERROR(SUMIFS(ELVIA!$N$2:$N$6,ELVIA!$H$2:$H$6,"SALIDA",ELVIA!$J$2:$J$6,$B53),0) -> 0 | V53: =IFERROR(SUMIFS(CAJA!$N$2:$N$586,CAJA!$H$2:$H$586,"SALIDA",CAJA!$J$2:$J$586,$B53),0) -> 0 | W53: =IFERROR(SUMIFS('CAJA TIGRES'!$N$2:$N$139,'CAJA TIGRES'!$H$2:$H$139,"SALIDA",'CAJA TIGRES'!$J$2:$J$139,$B53),0) -> 700 | X53: =IFERROR(SUMIFS(RESERVA!$N$2:$N$2,RESERVA!$H$2:$H$2,"SALIDA",RESERVA!$J$2:$J$2,$B53),0) -> 0 | Y53: =SUM(C53:X53) -> 17692.88 | Z53: =Y53 -> 17692.88
A54: 6.4 | B54: LUZ/AGUA | C54: =IFERROR(SUMIFS('MGZ121'!$N$2:$N$175,'MGZ121'!H$2:H$175,"SALIDA",'MGZ121'!$J$2:$J$175,$B54),0) -> 0 | D54: =IFERROR(SUMIFS('MGZ BBVA'!$N$2:$N$88,'MGZ BBVA'!$H$2:$H$88,"SALIDA",'MGZ BBVA'!$J$2:$J$88,$B54),0) -> 0 | E54: =IFERROR(SUMIFS('MGZ DOLARES'!$N$2:$N$2,'MGZ DOLARES'!$F$2:$F$2,"SALIDA",'MGZ DOLARES'!$J$2:$J$2,$B54),0) -> 0 | F54: =IFERROR(SUMIFS('MGZ BAJIO'!$N$2:$N$4,'MGZ BAJIO'!$H$2:$H$4,"SALIDA",'MGZ BAJIO'!$J$2:$J$4,$B54),0) -> 0 | G54: =IFERROR(SUMIFS('VICTOR BANAMEX'!$N$2:$N$65,'VICTOR BANAMEX'!$H$2:$H$65,"SALIDA",'VICTOR BANAMEX'!$J$2:$J$65,$B54),0) -> 0 | H54: =IFERROR(SUMIFS('VICTOR BANORTE'!$N$2:$N$9,'VICTOR BANORTE'!$H$2:$H$9,"SALIDA",'VICTOR BANORTE'!$J$2:$J$9,$B54),0) -> 0 | I54: =IFERROR(SUMIFS(RODRIGO!$N$2:$N$2,RODRIGO!$H$2:$H$2,"SALIDA",RODRIGO!$J$2:$J$2,$B54),0) -> 0 | J54: =IFERROR(SUMIFS(MOY!$N$2:$N$12,MOY!$H$2:$H$12,"SALIDA",MOY!$J$2:$J$12,$B54),0) -> 0 | K54: =IFERROR(SUMIFS('NORMA RUTH'!$N$2:$N$12,'NORMA RUTH'!$H$2:$H$12,"SALIDA",'NORMA RUTH'!$J$2:$J$12,$B54),0) -> 0 | L54: =IFERROR(SUMIFS(VALERIA!$N$2:$N$10,VALERIA!$H$2:$H$10,"SALIDA",VALERIA!$J$2:$J$10,$B54),0) -> 0 | M54: =IFERROR(SUMIFS('MANUEL BANAMEX'!$N$2:$N$25,'MANUEL BANAMEX'!$H$2:$H$25,"SALIDA",'MANUEL BANAMEX'!$J$2:$J$25,$B54),0) -> 0 | N54: =IFERROR(SUMIFS(ROBERTO!$N$2:$N$2,ROBERTO!$H$2:$H$2,"SALIDA",ROBERTO!$J$2:$J$2,$B54),0) -> 0 | O54: =IFERROR(SUMIFS(JUAN!$N$2:$N$11,JUAN!$H$2:$H$11,"SALIDA",JUAN!$J$2:$J$11,$B54),0) -> 0 | P54: =IFERROR(SUMIFS('NORMA SANCHEZ'!$N$2:$N$14,'NORMA SANCHEZ'!$H$2:$H$14,"SALIDA",'NORMA SANCHEZ'!$J$2:$J$14,$B54),0) -> 0 | Q54: =IFERROR(SUMIFS('JOSE CARLOS'!$N$2:$N$16,'JOSE CARLOS'!$H$2:$H$16,"SALIDA",'JOSE CARLOS'!$J$2:$J$16,$B54),0) -> 0 | R54: =IFERROR(SUMIFS('LUIS ENRIQUE '!$N$2:$N$21,'LUIS ENRIQUE '!$H$2:$H$21,"SALIDA",'LUIS ENRIQUE '!$J$2:$J$21,$B54),0) -> 0 | S54: =IFERROR(SUMIFS(CESARIA!$N$2:$N$15,CESARIA!$H$2:$H$15,"SALIDA",CESARIA!$J$2:$J$15,$B54),0) -> 0 | T54: =IFERROR(SUMIFS(ALAN!$N$2:$N$14,ALAN!$H$2:$H$14,"SALIDA",ALAN!$J$2:$J$14,$B54),0) -> 0 | U54: =IFERROR(SUMIFS(ELVIA!$N$2:$N$6,ELVIA!$H$2:$H$6,"SALIDA",ELVIA!$J$2:$J$6,$B54),0) -> 0 | V54: =IFERROR(SUMIFS(CAJA!$N$2:$N$586,CAJA!$H$2:$H$586,"SALIDA",CAJA!$J$2:$J$586,$B54),0) -> 8117 | W54: =IFERROR(SUMIFS('CAJA TIGRES'!$N$2:$N$139,'CAJA TIGRES'!$H$2:$H$139,"SALIDA",'CAJA TIGRES'!$J$2:$J$139,$B54),0) -> 0 | X54: =IFERROR(SUMIFS(RESERVA!$N$2:$N$2,RESERVA!$H$2:$H$2,"SALIDA",RESERVA!$J$2:$J$2,$B54),0) -> 0 | Y54: =SUM(C54:X54) -> 8117 | Z54: =Y54 -> 8117
A55: 6.5 | B55: VARIOS ADMINISTRACION | C55: =IFERROR(SUMIFS('MGZ121'!$N$2:$N$175,'MGZ121'!H$2:H$175,"SALIDA",'MGZ121'!$J$2:$J$175,$B55),0) -> 0 | D55: =IFERROR(SUMIFS('MGZ BBVA'!$N$2:$N$88,'MGZ BBVA'!$H$2:$H$88,"SALIDA",'MGZ BBVA'!$J$2:$J$88,$B55),0) -> 44844 | E55: =IFERROR(SUMIFS('MGZ DOLARES'!$N$2:$N$2,'MGZ DOLARES'!$F$2:$F$2,"SALIDA",'MGZ DOLARES'!$J$2:$J$2,$B55),0) -> 0 | F55: =IFERROR(SUMIFS('MGZ BAJIO'!$N$2:$N$4,'MGZ BAJIO'!$H$2:$H$4,"SALIDA",'MGZ BAJIO'!$J$2:$J$4,$B55),0) -> 0 | G55: =IFERROR(SUMIFS('VICTOR BANAMEX'!$N$2:$N$65,'VICTOR BANAMEX'!$H$2:$H$65,"SALIDA",'VICTOR BANAMEX'!$J$2:$J$65,$B55),0) -> 986 | H55: =IFERROR(SUMIFS('VICTOR BANORTE'!$N$2:$N$9,'VICTOR BANORTE'!$H$2:$H$9,"SALIDA",'VICTOR BANORTE'!$J$2:$J$9,$B55),0) -> 0 | I55: =IFERROR(SUMIFS(RODRIGO!$N$2:$N$2,RODRIGO!$H$2:$H$2,"SALIDA",RODRIGO!$J$2:$J$2,$B55),0) -> 0 | J55: =IFERROR(SUMIFS(MOY!$N$2:$N$12,MOY!$H$2:$H$12,"SALIDA",MOY!$J$2:$J$12,$B55),0) -> 0 | K55: =IFERROR(SUMIFS('NORMA RUTH'!$N$2:$N$12,'NORMA RUTH'!$H$2:$H$12,"SALIDA",'NORMA RUTH'!$J$2:$J$12,$B55),0) -> 0 | L55: =IFERROR(SUMIFS(VALERIA!$N$2:$N$10,VALERIA!$H$2:$H$10,"SALIDA",VALERIA!$J$2:$J$10,$B55),0) -> 0 | M55: =IFERROR(SUMIFS('MANUEL BANAMEX'!$N$2:$N$25,'MANUEL BANAMEX'!$H$2:$H$25,"SALIDA",'MANUEL BANAMEX'!$J$2:$J$25,$B55),0) -> 0 | N55: =IFERROR(SUMIFS(ROBERTO!$N$2:$N$2,ROBERTO!$H$2:$H$2,"SALIDA",ROBERTO!$J$2:$J$2,$B55),0) -> 0 | O55: =IFERROR(SUMIFS(JUAN!$N$2:$N$11,JUAN!$H$2:$H$11,"SALIDA",JUAN!$J$2:$J$11,$B55),0) -> 0 | P55: =IFERROR(SUMIFS('NORMA SANCHEZ'!$N$2:$N$14,'NORMA SANCHEZ'!$H$2:$H$14,"SALIDA",'NORMA SANCHEZ'!$J$2:$J$14,$B55),0) -> 0 | Q55: =IFERROR(SUMIFS('JOSE CARLOS'!$N$2:$N$16,'JOSE CARLOS'!$H$2:$H$16,"SALIDA",'JOSE CARLOS'!$J$2:$J$16,$B55),0) -> 0 | R55: =IFERROR(SUMIFS('LUIS ENRIQUE '!$N$2:$N$21,'LUIS ENRIQUE '!$H$2:$H$21,"SALIDA",'LUIS ENRIQUE '!$J$2:$J$21,$B55),0) -> 0 | S55: =IFERROR(SUMIFS(CESARIA!$N$2:$N$15,CESARIA!$H$2:$H$15,"SALIDA",CESARIA!$J$2:$J$15,$B55),0) -> 0 | T55: =IFERROR(SUMIFS(ALAN!$N$2:$N$14,ALAN!$H$2:$H$14,"SALIDA",ALAN!$J$2:$J$14,$B55),0) -> 475.94 | U55: =IFERROR(SUMIFS(ELVIA!$N$2:$N$6,ELVIA!$H$2:$H$6,"SALIDA",ELVIA!$J$2:$J$6,$B55),0) -> 0 | V55: =IFERROR(SUMIFS(CAJA!$N$2:$N$586,CAJA!$H$2:$H$586,"SALIDA",CAJA!$J$2:$J$586,$B55),0) -> 18862.02 | W55: =IFERROR(SUMIFS('CAJA TIGRES'!$N$2:$N$139,'CAJA TIGRES'!$H$2:$H$139,"SALIDA",'CAJA TIGRES'!$J$2:$J$139,$B55),0) -> 6220 | X55: =IFERROR(SUMIFS(RESERVA!$N$2:$N$2,RESERVA!$H$2:$H$2,"SALIDA",RESERVA!$J$2:$J$2,$B55),0) -> 0 | Y55: =SUM(C55:X55) -> 71387.96 | Z55: =Y55 -> 71387.96
B56: MTTO EQUIPO DE OFICINA | C56: =IFERROR(SUMIFS('MGZ121'!$N$2:$N$175,'MGZ121'!H$2:H$175,"SALIDA",'MGZ121'!$J$2:$J$175,$B56),0) -> 0 | D56: =IFERROR(SUMIFS('MGZ BBVA'!$N$2:$N$88,'MGZ BBVA'!$H$2:$H$88,"SALIDA",'MGZ BBVA'!$J$2:$J$88,$B56),0) -> 0 | E56: =IFERROR(SUMIFS('MGZ DOLARES'!$N$2:$N$2,'MGZ DOLARES'!$F$2:$F$2,"SALIDA",'MGZ DOLARES'!$J$2:$J$2,$B56),0) -> 0 | F56: =IFERROR(SUMIFS('MGZ BAJIO'!$N$2:$N$4,'MGZ BAJIO'!$H$2:$H$4,"SALIDA",'MGZ BAJIO'!$J$2:$J$4,$B56),0) -> 0 | G56: =IFERROR(SUMIFS('VICTOR BANAMEX'!$N$2:$N$65,'VICTOR BANAMEX'!$H$2:$H$65,"SALIDA",'VICTOR BANAMEX'!$J$2:$J$65,$B56),0) -> 0 | H56: =IFERROR(SUMIFS('VICTOR BANORTE'!$N$2:$N$9,'VICTOR BANORTE'!$H$2:$H$9,"SALIDA",'VICTOR BANORTE'!$J$2:$J$9,$B56),0) -> 0 | I56: =IFERROR(SUMIFS(RODRIGO!$N$2:$N$2,RODRIGO!$H$2:$H$2,"SALIDA",RODRIGO!$J$2:$J$2,$B56),0) -> 0 | J56: =IFERROR(SUMIFS(MOY!$N$2:$N$12,MOY!$H$2:$H$12,"SALIDA",MOY!$J$2:$J$12,$B56),0) -> 0 | K56: =IFERROR(SUMIFS('NORMA RUTH'!$N$2:$N$12,'NORMA RUTH'!$H$2:$H$12,"SALIDA",'NORMA RUTH'!$J$2:$J$12,$B56),0) -> 0 | L56: =IFERROR(SUMIFS(VALERIA!$N$2:$N$10,VALERIA!$H$2:$H$10,"SALIDA",VALERIA!$J$2:$J$10,$B56),0) -> 0 | M56: =IFERROR(SUMIFS('MANUEL BANAMEX'!$N$2:$N$25,'MANUEL BANAMEX'!$H$2:$H$25,"SALIDA",'MANUEL BANAMEX'!$J$2:$J$25,$B56),0) -> 0 | N56: =IFERROR(SUMIFS(ROBERTO!$N$2:$N$2,ROBERTO!$H$2:$H$2,"SALIDA",ROBERTO!$J$2:$J$2,$B56),0) -> 0 | O56: =IFERROR(SUMIFS(JUAN!$N$2:$N$11,JUAN!$H$2:$H$11,"SALIDA",JUAN!$J$2:$J$11,$B56),0) -> 0 | P56: =IFERROR(SUMIFS('NORMA SANCHEZ'!$N$2:$N$14,'NORMA SANCHEZ'!$H$2:$H$14,"SALIDA",'NORMA SANCHEZ'!$J$2:$J$14,$B56),0) -> 0 | Q56: =IFERROR(SUMIFS('JOSE CARLOS'!$N$2:$N$16,'JOSE CARLOS'!$H$2:$H$16,"SALIDA",'JOSE CARLOS'!$J$2:$J$16,$B56),0) -> 0 | R56: =IFERROR(SUMIFS('LUIS ENRIQUE '!$N$2:$N$21,'LUIS ENRIQUE '!$H$2:$H$21,"SALIDA",'LUIS ENRIQUE '!$J$2:$J$21,$B56),0) -> 0 | S56: =IFERROR(SUMIFS(CESARIA!$N$2:$N$15,CESARIA!$H$2:$H$15,"SALIDA",CESARIA!$J$2:$J$15,$B56),0) -> 0 | T56: =IFERROR(SUMIFS(ALAN!$N$2:$N$14,ALAN!$H$2:$H$14,"SALIDA",ALAN!$J$2:$J$14,$B56),0) -> 0 | U56: =IFERROR(SUMIFS(ELVIA!$N$2:$N$6,ELVIA!$H$2:$H$6,"SALIDA",ELVIA!$J$2:$J$6,$B56),0) -> 0 | V56: =IFERROR(SUMIFS(CAJA!$N$2:$N$586,CAJA!$H$2:$H$586,"SALIDA",CAJA!$J$2:$J$586,$B56),0) -> 0 | W56: =IFERROR(SUMIFS('CAJA TIGRES'!$N$2:$N$139,'CAJA TIGRES'!$H$2:$H$139,"SALIDA",'CAJA TIGRES'!$J$2:$J$139,$B56),0) -> 0 | X56: =IFERROR(SUMIFS(RESERVA!$N$2:$N$2,RESERVA!$H$2:$H$2,"SALIDA",RESERVA!$J$2:$J$2,$B56),0) -> 0 | Y56: =SUM(C56:X56) -> 0 | Z56: =Y56 -> 0
B57: ARRENDAMIENTO OFICINA | C57: =IFERROR(SUMIFS('MGZ121'!$N$2:$N$175,'MGZ121'!H$2:H$175,"SALIDA",'MGZ121'!$J$2:$J$175,$B57),0) -> 0 | D57: =IFERROR(SUMIFS('MGZ BBVA'!$N$2:$N$88,'MGZ BBVA'!$H$2:$H$88,"SALIDA",'MGZ BBVA'!$J$2:$J$88,$B57),0) -> 0 | E57: =IFERROR(SUMIFS('MGZ DOLARES'!$N$2:$N$2,'MGZ DOLARES'!$F$2:$F$2,"SALIDA",'MGZ DOLARES'!$J$2:$J$2,$B57),0) -> 0 | F57: =IFERROR(SUMIFS('MGZ BAJIO'!$N$2:$N$4,'MGZ BAJIO'!$H$2:$H$4,"SALIDA",'MGZ BAJIO'!$J$2:$J$4,$B57),0) -> 0 | G57: =IFERROR(SUMIFS('VICTOR BANAMEX'!$N$2:$N$65,'VICTOR BANAMEX'!$H$2:$H$65,"SALIDA",'VICTOR BANAMEX'!$J$2:$J$65,$B57),0) -> 0 | H57: =IFERROR(SUMIFS('VICTOR BANORTE'!$N$2:$N$9,'VICTOR BANORTE'!$H$2:$H$9,"SALIDA",'VICTOR BANORTE'!$J$2:$J$9,$B57),0) -> 0 | I57: =IFERROR(SUMIFS(RODRIGO!$N$2:$N$2,RODRIGO!$H$2:$H$2,"SALIDA",RODRIGO!$J$2:$J$2,$B57),0) -> 0 | J57: =IFERROR(SUMIFS(MOY!$N$2:$N$12,MOY!$H$2:$H$12,"SALIDA",MOY!$J$2:$J$12,$B57),0) -> 0 | K57: =IFERROR(SUMIFS('NORMA RUTH'!$N$2:$N$12,'NORMA RUTH'!$H$2:$H$12,"SALIDA",'NORMA RUTH'!$J$2:$J$12,$B57),0) -> 0 | L57: =IFERROR(SUMIFS(VALERIA!$N$2:$N$10,VALERIA!$H$2:$H$10,"SALIDA",VALERIA!$J$2:$J$10,$B57),0) -> 0 | M57: =IFERROR(SUMIFS('MANUEL BANAMEX'!$N$2:$N$25,'MANUEL BANAMEX'!$H$2:$H$25,"SALIDA",'MANUEL BANAMEX'!$J$2:$J$25,$B57),0) -> 0 | N57: =IFERROR(SUMIFS(ROBERTO!$N$2:$N$2,ROBERTO!$H$2:$H$2,"SALIDA",ROBERTO!$J$2:$J$2,$B57),0) -> 0 | O57: =IFERROR(SUMIFS(JUAN!$N$2:$N$11,JUAN!$H$2:$H$11,"SALIDA",JUAN!$J$2:$J$11,$B57),0) -> 0 | P57: =IFERROR(SUMIFS('NORMA SANCHEZ'!$N$2:$N$14,'NORMA SANCHEZ'!$H$2:$H$14,"SALIDA",'NORMA SANCHEZ'!$J$2:$J$14,$B57),0) -> 0 | Q57: =IFERROR(SUMIFS('JOSE CARLOS'!$N$2:$N$16,'JOSE CARLOS'!$H$2:$H$16,"SALIDA",'JOSE CARLOS'!$J$2:$J$16,$B57),0) -> 0 | R57: =IFERROR(SUMIFS('LUIS ENRIQUE '!$N$2:$N$21,'LUIS ENRIQUE '!$H$2:$H$21,"SALIDA",'LUIS ENRIQUE '!$J$2:$J$21,$B57),0) -> 0 | S57: =IFERROR(SUMIFS(CESARIA!$N$2:$N$15,CESARIA!$H$2:$H$15,"SALIDA",CESARIA!$J$2:$J$15,$B57),0) -> 0 | T57: =IFERROR(SUMIFS(ALAN!$N$2:$N$14,ALAN!$H$2:$H$14,"SALIDA",ALAN!$J$2:$J$14,$B57),0) -> 0 | U57: =IFERROR(SUMIFS(ELVIA!$N$2:$N$6,ELVIA!$H$2:$H$6,"SALIDA",ELVIA!$J$2:$J$6,$B57),0) -> 0 | V57: =IFERROR(SUMIFS(CAJA!$N$2:$N$586,CAJA!$H$2:$H$586,"SALIDA",CAJA!$J$2:$J$586,$B57),0) -> 0 | W57: =IFERROR(SUMIFS('CAJA TIGRES'!$N$2:$N$139,'CAJA TIGRES'!$H$2:$H$139,"SALIDA",'CAJA TIGRES'!$J$2:$J$139,$B57),0) -> 0 | X57: =IFERROR(SUMIFS(RESERVA!$N$2:$N$2,RESERVA!$H$2:$H$2,"SALIDA",RESERVA!$J$2:$J$2,$B57),0) -> 0 | Y57: =SUM(C57:X57) -> 0 | Z57: =Y57 -> 0
B58: VIATICOS | C58: =IFERROR(SUMIFS('MGZ121'!$N$2:$N$175,'MGZ121'!H$2:H$175,"SALIDA",'MGZ121'!$J$2:$J$175,$B58),0) -> 0 | D58: =IFERROR(SUMIFS('MGZ BBVA'!$N$2:$N$88,'MGZ BBVA'!$H$2:$H$88,"SALIDA",'MGZ BBVA'!$J$2:$J$88,$B58),0) -> 0 | E58: =IFERROR(SUMIFS('MGZ DOLARES'!$N$2:$N$2,'MGZ DOLARES'!$F$2:$F$2,"SALIDA",'MGZ DOLARES'!$J$2:$J$2,$B58),0) -> 0 | F58: =IFERROR(SUMIFS('MGZ BAJIO'!$N$2:$N$4,'MGZ BAJIO'!$H$2:$H$4,"SALIDA",'MGZ BAJIO'!$J$2:$J$4,$B58),0) -> 0 | G58: =IFERROR(SUMIFS('VICTOR BANAMEX'!$N$2:$N$65,'VICTOR BANAMEX'!$H$2:$H$65,"SALIDA",'VICTOR BANAMEX'!$J$2:$J$65,$B58),0) -> 0 | H58: =IFERROR(SUMIFS('VICTOR BANORTE'!$N$2:$N$9,'VICTOR BANORTE'!$H$2:$H$9,"SALIDA",'VICTOR BANORTE'!$J$2:$J$9,$B58),0) -> 0 | I58: =IFERROR(SUMIFS(RODRIGO!$N$2:$N$2,RODRIGO!$H$2:$H$2,"SALIDA",RODRIGO!$J$2:$J$2,$B58),0) -> 0 | J58: =IFERROR(SUMIFS(MOY!$N$2:$N$12,MOY!$H$2:$H$12,"SALIDA",MOY!$J$2:$J$12,$B58),0) -> 0 | K58: =IFERROR(SUMIFS('NORMA RUTH'!$N$2:$N$12,'NORMA RUTH'!$H$2:$H$12,"SALIDA",'NORMA RUTH'!$J$2:$J$12,$B58),0) -> 0 | L58: =IFERROR(SUMIFS(VALERIA!$N$2:$N$10,VALERIA!$H$2:$H$10,"SALIDA",VALERIA!$J$2:$J$10,$B58),0) -> 0 | M58: =IFERROR(SUMIFS('MANUEL BANAMEX'!$N$2:$N$25,'MANUEL BANAMEX'!$H$2:$H$25,"SALIDA",'MANUEL BANAMEX'!$J$2:$J$25,$B58),0) -> 0 | N58: =IFERROR(SUMIFS(ROBERTO!$N$2:$N$2,ROBERTO!$H$2:$H$2,"SALIDA",ROBERTO!$J$2:$J$2,$B58),0) -> 0 | O58: =IFERROR(SUMIFS(JUAN!$N$2:$N$11,JUAN!$H$2:$H$11,"SALIDA",JUAN!$J$2:$J$11,$B58),0) -> 0 | P58: =IFERROR(SUMIFS('NORMA SANCHEZ'!$N$2:$N$14,'NORMA SANCHEZ'!$H$2:$H$14,"SALIDA",'NORMA SANCHEZ'!$J$2:$J$14,$B58),0) -> 0 | Q58: =IFERROR(SUMIFS('JOSE CARLOS'!$N$2:$N$16,'JOSE CARLOS'!$H$2:$H$16,"SALIDA",'JOSE CARLOS'!$J$2:$J$16,$B58),0) -> 0 | R58: =IFERROR(SUMIFS('LUIS ENRIQUE '!$N$2:$N$21,'LUIS ENRIQUE '!$H$2:$H$21,"SALIDA",'LUIS ENRIQUE '!$J$2:$J$21,$B58),0) -> 0 | S58: =IFERROR(SUMIFS(CESARIA!$N$2:$N$15,CESARIA!$H$2:$H$15,"SALIDA",CESARIA!$J$2:$J$15,$B58),0) -> 0 | T58: =IFERROR(SUMIFS(ALAN!$N$2:$N$14,ALAN!$H$2:$H$14,"SALIDA",ALAN!$J$2:$J$14,$B58),0) -> 0 | U58: =IFERROR(SUMIFS(ELVIA!$N$2:$N$6,ELVIA!$H$2:$H$6,"SALIDA",ELVIA!$J$2:$J$6,$B58),0) -> 0 | V58: =IFERROR(SUMIFS(CAJA!$N$2:$N$586,CAJA!$H$2:$H$586,"SALIDA",CAJA!$J$2:$J$586,$B58),0) -> 3500 | W58: =IFERROR(SUMIFS('CAJA TIGRES'!$N$2:$N$139,'CAJA TIGRES'!$H$2:$H$139,"SALIDA",'CAJA TIGRES'!$J$2:$J$139,$B58),0) -> 0 | X58: =IFERROR(SUMIFS(RESERVA!$N$2:$N$2,RESERVA!$H$2:$H$2,"SALIDA",RESERVA!$J$2:$J$2,$B58),0) -> 0 | Y58: =SUM(C58:X58) -> 3500 | Z58: =Y58 -> 3500
B59: LAVADO Y ENGRASADO VEHICULOS ADMTVO | C59: =IFERROR(SUMIFS('MGZ121'!$N$2:$N$175,'MGZ121'!H$2:H$175,"SALIDA",'MGZ121'!$J$2:$J$175,$B59),0) -> 0 | D59: =IFERROR(SUMIFS('MGZ BBVA'!$N$2:$N$88,'MGZ BBVA'!$H$2:$H$88,"SALIDA",'MGZ BBVA'!$J$2:$J$88,$B59),0) -> 0 | E59: =IFERROR(SUMIFS('MGZ DOLARES'!$N$2:$N$2,'MGZ DOLARES'!$F$2:$F$2,"SALIDA",'MGZ DOLARES'!$J$2:$J$2,$B59),0) -> 0 | F59: =IFERROR(SUMIFS('MGZ BAJIO'!$N$2:$N$4,'MGZ BAJIO'!$H$2:$H$4,"SALIDA",'MGZ BAJIO'!$J$2:$J$4,$B59),0) -> 0 | G59: =IFERROR(SUMIFS('VICTOR BANAMEX'!$N$2:$N$65,'VICTOR BANAMEX'!$H$2:$H$65,"SALIDA",'VICTOR BANAMEX'!$J$2:$J$65,$B59),0) -> 0 | H59: =IFERROR(SUMIFS('VICTOR BANORTE'!$N$2:$N$9,'VICTOR BANORTE'!$H$2:$H$9,"SALIDA",'VICTOR BANORTE'!$J$2:$J$9,$B59),0) -> 0 | I59: =IFERROR(SUMIFS(RODRIGO!$N$2:$N$2,RODRIGO!$H$2:$H$2,"SALIDA",RODRIGO!$J$2:$J$2,$B59),0) -> 0 | J59: =IFERROR(SUMIFS(MOY!$N$2:$N$12,MOY!$H$2:$H$12,"SALIDA",MOY!$J$2:$J$12,$B59),0) -> 0 | K59: =IFERROR(SUMIFS('NORMA RUTH'!$N$2:$N$12,'NORMA RUTH'!$H$2:$H$12,"SALIDA",'NORMA RUTH'!$J$2:$J$12,$B59),0) -> 0 | L59: =IFERROR(SUMIFS(VALERIA!$N$2:$N$10,VALERIA!$H$2:$H$10,"SALIDA",VALERIA!$J$2:$J$10,$B59),0) -> 0 | M59: =IFERROR(SUMIFS('MANUEL BANAMEX'!$N$2:$N$25,'MANUEL BANAMEX'!$H$2:$H$25,"SALIDA",'MANUEL BANAMEX'!$J$2:$J$25,$B59),0) -> 0 | N59: =IFERROR(SUMIFS(ROBERTO!$N$2:$N$2,ROBERTO!$H$2:$H$2,"SALIDA",ROBERTO!$J$2:$J$2,$B59),0) -> 0 | O59: =IFERROR(SUMIFS(JUAN!$N$2:$N$11,JUAN!$H$2:$H$11,"SALIDA",JUAN!$J$2:$J$11,$B59),0) -> 0 | P59: =IFERROR(SUMIFS('NORMA SANCHEZ'!$N$2:$N$14,'NORMA SANCHEZ'!$H$2:$H$14,"SALIDA",'NORMA SANCHEZ'!$J$2:$J$14,$B59),0) -> 0 | Q59: =IFERROR(SUMIFS('JOSE CARLOS'!$N$2:$N$16,'JOSE CARLOS'!$H$2:$H$16,"SALIDA",'JOSE CARLOS'!$J$2:$J$16,$B59),0) -> 0 | R59: =IFERROR(SUMIFS('LUIS ENRIQUE '!$N$2:$N$21,'LUIS ENRIQUE '!$H$2:$H$21,"SALIDA",'LUIS ENRIQUE '!$J$2:$J$21,$B59),0) -> 0 | S59: =IFERROR(SUMIFS(CESARIA!$N$2:$N$15,CESARIA!$H$2:$H$15,"SALIDA",CESARIA!$J$2:$J$15,$B59),0) -> 0 | T59: =IFERROR(SUMIFS(ALAN!$N$2:$N$14,ALAN!$H$2:$H$14,"SALIDA",ALAN!$J$2:$J$14,$B59),0) -> 0 | U59: =IFERROR(SUMIFS(ELVIA!$N$2:$N$6,ELVIA!$H$2:$H$6,"SALIDA",ELVIA!$J$2:$J$6,$B59),0) -> 0 | V59: =IFERROR(SUMIFS(CAJA!$N$2:$N$586,CAJA!$H$2:$H$586,"SALIDA",CAJA!$J$2:$J$586,$B59),0) -> 0 | W59: =IFERROR(SUMIFS('CAJA TIGRES'!$N$2:$N$139,'CAJA TIGRES'!$H$2:$H$139,"SALIDA",'CAJA TIGRES'!$J$2:$J$139,$B59),0) -> 0 | X59: =IFERROR(SUMIFS(RESERVA!$N$2:$N$2,RESERVA!$H$2:$H$2,"SALIDA",RESERVA!$J$2:$J$2,$B59),0) -> 0 | Y59: =SUM(C59:X59) -> 0 | Z59: =Y59 -> 0
A60: 7 | B60: FINANCIERO | C60: =SUM(C61:C63) -> 451084.35 | D60: =SUM(D61:D63) -> 1037.04 | E60: =SUM(E61:E63) -> 0 | F60: =SUM(F61:F63) -> 580 | G60: =SUM(G61:G63) -> 508.21 | H60: =SUM(H61:H63) -> 511.4 | I60: =SUM(I61:I63) -> 0 | J60: =SUM(J61:J63) -> 455.88 | ... Z60: =SUM(Z61:Z63) -> 779705.39
A61: 7.1 | B61: COMISION BANCARIA | C61: =IFERROR(SUMIFS('MGZ121'!$N$2:$N$175,'MGZ121'!H$2:H$175,"SALIDA",'MGZ121'!$J$2:$J$175,$B61),0) -> 55044.7 | D61: =IFERROR(SUMIFS('MGZ BBVA'!$N$2:$N$88,'MGZ BBVA'!$H$2:$H$88,"SALIDA",'MGZ BBVA'!$J$2:$J$88,$B61),0) -> 1037.04 | E61: =IFERROR(SUMIFS('MGZ DOLARES'!$N$2:$N$2,'MGZ DOLARES'!$F$2:$F$2,"SALIDA",'MGZ DOLARES'!$J$2:$J$2,$B61),0) -> 0 | F61: =IFERROR(SUMIFS('MGZ BAJIO'!$N$2:$N$4,'MGZ BAJIO'!$H$2:$H$4,"SALIDA",'MGZ BAJIO'!$J$2:$J$4,$B61),0) -> 580 | G61: =IFERROR(SUMIFS('VICTOR BANAMEX'!$N$2:$N$65,'VICTOR BANAMEX'!$H$2:$H$65,"SALIDA",'VICTOR BANAMEX'!$J$2:$J$65,$B61),0) -> 508.21 | H61: =IFERROR(SUMIFS('VICTOR BANORTE'!$N$2:$N$9,'VICTOR BANORTE'!$H$2:$H$9,"SALIDA",'VICTOR BANORTE'!$J$2:$J$9,$B61),0) -> 511.4 | I61: =IFERROR(SUMIFS(RODRIGO!$N$2:$N$2,RODRIGO!$H$2:$H$2,"SALIDA",RODRIGO!$J$2:$J$2,$B61),0) -> 0 | J61: =IFERROR(SUMIFS(MOY!$N$2:$N$12,MOY!$H$2:$H$12,"SALIDA",MOY!$J$2:$J$12,$B61),0) -> 455.88 | K61: =IFERROR(SUMIFS('NORMA RUTH'!$N$2:$N$12,'NORMA RUTH'!$H$2:$H$12,"SALIDA",'NORMA RUTH'!$J$2:$J$12,$B61),0) -> 324.8 | L61: =IFERROR(SUMIFS(VALERIA!$N$2:$N$10,VALERIA!$H$2:$H$10,"SALIDA",VALERIA!$J$2:$J$10,$B61),0) -> 585.8 | M61: =IFERROR(SUMIFS('MANUEL BANAMEX'!$N$2:$N$25,'MANUEL BANAMEX'!$H$2:$H$25,"SALIDA",'MANUEL BANAMEX'!$J$2:$J$25,$B61),0) -> 0 | N61: =IFERROR(SUMIFS(ROBERTO!$N$2:$N$2,ROBERTO!$H$2:$H$2,"SALIDA",ROBERTO!$J$2:$J$2,$B61),0) -> 0 | O61: =IFERROR(SUMIFS(JUAN!$N$2:$N$11,JUAN!$H$2:$H$11,"SALIDA",JUAN!$J$2:$J$11,$B61),0) -> 568.4 | P61: =IFERROR(SUMIFS('NORMA SANCHEZ'!$N$2:$N$14,'NORMA SANCHEZ'!$H$2:$H$14,"SALIDA",'NORMA SANCHEZ'!$J$2:$J$14,$B61),0) -> 191.4 | Q61: =IFERROR(SUMIFS('JOSE CARLOS'!$N$2:$N$16,'JOSE CARLOS'!$H$2:$H$16,"SALIDA",'JOSE CARLOS'!$J$2:$J$16,$B61),0) -> 359.6 | R61: =IFERROR(SUMIFS('LUIS ENRIQUE '!$N$2:$N$21,'LUIS ENRIQUE '!$H$2:$H$21,"SALIDA",'LUIS ENRIQUE '!$J$2:$J$21,$B61),0) -> 2476.6 | S61: =IFERROR(SUMIFS(CESARIA!$N$2:$N$15,CESARIA!$H$2:$H$15,"SALIDA",CESARIA!$J$2:$J$15,$B61),0) -> 1136.8 | T61: =IFERROR(SUMIFS(ALAN!$N$2:$N$14,ALAN!$H$2:$H$14,"SALIDA",ALAN!$J$2:$J$14,$B61),0) -> 560.31 | U61: =IFERROR(SUMIFS(ELVIA!$N$2:$N$6,ELVIA!$H$2:$H$6,"SALIDA",ELVIA!$J$2:$J$6,$B61),0) -> 324.8 | V61: =IFERROR(SUMIFS(CAJA!$N$2:$N$586,CAJA!$H$2:$H$586,"SALIDA",CAJA!$J$2:$J$586,$B61),0) -> 0 | W61: =IFERROR(SUMIFS('CAJA TIGRES'!$N$2:$N$139,'CAJA TIGRES'!$H$2:$H$139,"SALIDA",'CAJA TIGRES'!$J$2:$J$139,$B61),0) -> 0 | X61: =IFERROR(SUMIFS(RESERVA!$N$2:$N$2,RESERVA!$H$2:$H$2,"SALIDA",RESERVA!$J$2:$J$2,$B61),0) -> 0 | Y61: =SUM(C61:X61) -> 64665.74 | Z61: =Y61 -> 64665.74
A62: 7.2 | B62: INTERES BANCARIO | C62: =IFERROR(SUMIFS('MGZ121'!$N$2:$N$175,'MGZ121'!H$2:H$175,"SALIDA",'MGZ121'!$J$2:$J$175,$B62),0) -> 396039.65 | D62: =IFERROR(SUMIFS('MGZ BBVA'!$N$2:$N$88,'MGZ BBVA'!$H$2:$H$88,"SALIDA",'MGZ BBVA'!$J$2:$J$88,$B62),0) -> 0 | E62: =IFERROR(SUMIFS('MGZ DOLARES'!$N$2:$N$2,'MGZ DOLARES'!$F$2:$F$2,"SALIDA",'MGZ DOLARES'!$J$2:$J$2,$B62),0) -> 0 | F62: =IFERROR(SUMIFS('MGZ BAJIO'!$N$2:$N$4,'MGZ BAJIO'!$H$2:$H$4,"SALIDA",'MGZ BAJIO'!$J$2:$J$4,$B62),0) -> 0 | G62: =IFERROR(SUMIFS('VICTOR BANAMEX'!$N$2:$N$65,'VICTOR BANAMEX'!$H$2:$H$65,"SALIDA",'VICTOR BANAMEX'!$J$2:$J$65,$B62),0) -> 0 | H62: =IFERROR(SUMIFS('VICTOR BANORTE'!$N$2:$N$9,'VICTOR BANORTE'!$H$2:$H$9,"SALIDA",'VICTOR BANORTE'!$J$2:$J$9,$B62),0) -> 0 | I62: =IFERROR(SUMIFS(RODRIGO!$N$2:$N$2,RODRIGO!$H$2:$H$2,"SALIDA",RODRIGO!$J$2:$J$2,$B62),0) -> 0 | J62: =IFERROR(SUMIFS(MOY!$N$2:$N$12,MOY!$H$2:$H$12,"SALIDA",MOY!$J$2:$J$12,$B62),0) -> 0 | K62: =IFERROR(SUMIFS('NORMA RUTH'!$N$2:$N$12,'NORMA RUTH'!$H$2:$H$12,"SALIDA",'NORMA RUTH'!$J$2:$J$12,$B62),0) -> 0 | L62: =IFERROR(SUMIFS(VALERIA!$N$2:$N$10,VALERIA!$H$2:$H$10,"SALIDA",VALERIA!$J$2:$J$10,$B62),0) -> 0 | M62: =IFERROR(SUMIFS('MANUEL BANAMEX'!$N$2:$N$25,'MANUEL BANAMEX'!$H$2:$H$25,"SALIDA",'MANUEL BANAMEX'!$J$2:$J$25,$B62),0) -> 0 | N62: =IFERROR(SUMIFS(ROBERTO!$N$2:$N$2,ROBERTO!$H$2:$H$2,"SALIDA",ROBERTO!$J$2:$J$2,$B62),0) -> 0 | O62: =IFERROR(SUMIFS(JUAN!$N$2:$N$11,JUAN!$H$2:$H$11,"SALIDA",JUAN!$J$2:$J$11,$B62),0) -> 0 | P62: =IFERROR(SUMIFS('NORMA SANCHEZ'!$N$2:$N$14,'NORMA SANCHEZ'!$H$2:$H$14,"SALIDA",'NORMA SANCHEZ'!$J$2:$J$14,$B62),0) -> 0 | Q62: =IFERROR(SUMIFS('JOSE CARLOS'!$N$2:$N$16,'JOSE CARLOS'!$H$2:$H$16,"SALIDA",'JOSE CARLOS'!$J$2:$J$16,$B62),0) -> 0 | R62: =IFERROR(SUMIFS('LUIS ENRIQUE '!$N$2:$N$21,'LUIS ENRIQUE '!$H$2:$H$21,"SALIDA",'LUIS ENRIQUE '!$J$2:$J$21,$B62),0) -> 0 | S62: =IFERROR(SUMIFS(CESARIA!$N$2:$N$15,CESARIA!$H$2:$H$15,"SALIDA",CESARIA!$J$2:$J$15,$B62),0) -> 0 | T62: =IFERROR(SUMIFS(ALAN!$N$2:$N$14,ALAN!$H$2:$H$14,"SALIDA",ALAN!$J$2:$J$14,$B62),0) -> 0 | U62: =IFERROR(SUMIFS(ELVIA!$N$2:$N$6,ELVIA!$H$2:$H$6,"SALIDA",ELVIA!$J$2:$J$6,$B62),0) -> 0 | V62: =IFERROR(SUMIFS(CAJA!$N$2:$N$586,CAJA!$H$2:$H$586,"SALIDA",CAJA!$J$2:$J$586,$B62),0) -> 0 | W62: =IFERROR(SUMIFS('CAJA TIGRES'!$N$2:$N$139,'CAJA TIGRES'!$H$2:$H$139,"SALIDA",'CAJA TIGRES'!$J$2:$J$139,$B62),0) -> 0 | X62: =IFERROR(SUMIFS(RESERVA!$N$2:$N$2,RESERVA!$H$2:$H$2,"SALIDA",RESERVA!$J$2:$J$2,$B62),0) -> 0 | Y62: =SUM(C62:X62) -> 396039.65 | Z62: =Y62 -> 396039.65
A63: 7.3 | B63: INTERES EXTERNO | C63: =IFERROR(SUMIFS('MGZ121'!$N$2:$N$175,'MGZ121'!H$2:H$175,"SALIDA",'MGZ121'!$J$2:$J$175,$B63),0) -> 0 | D63: =IFERROR(SUMIFS('MGZ BBVA'!$N$2:$N$88,'MGZ BBVA'!$H$2:$H$88,"SALIDA",'MGZ BBVA'!$J$2:$J$88,$B63),0) -> 0 | E63: =IFERROR(SUMIFS('MGZ DOLARES'!$N$2:$N$2,'MGZ DOLARES'!$F$2:$F$2,"SALIDA",'MGZ DOLARES'!$J$2:$J$2,$B63),0) -> 0 | F63: =IFERROR(SUMIFS('MGZ BAJIO'!$N$2:$N$4,'MGZ BAJIO'!$H$2:$H$4,"SALIDA",'MGZ BAJIO'!$J$2:$J$4,$B63),0) -> 0 | G63: =IFERROR(SUMIFS('VICTOR BANAMEX'!$N$2:$N$65,'VICTOR BANAMEX'!$H$2:$H$65,"SALIDA",'VICTOR BANAMEX'!$J$2:$J$65,$B63),0) -> 0 | H63: =IFERROR(SUMIFS('VICTOR BANORTE'!$N$2:$N$9,'VICTOR BANORTE'!$H$2:$H$9,"SALIDA",'VICTOR BANORTE'!$J$2:$J$9,$B63),0) -> 0 | I63: =IFERROR(SUMIFS(RODRIGO!$N$2:$N$2,RODRIGO!$H$2:$H$2,"SALIDA",RODRIGO!$J$2:$J$2,$B63),0) -> 0 | J63: =IFERROR(SUMIFS(MOY!$N$2:$N$12,MOY!$H$2:$H$12,"SALIDA",MOY!$J$2:$J$12,$B63),0) -> 0 | K63: =IFERROR(SUMIFS('NORMA RUTH'!$N$2:$N$12,'NORMA RUTH'!$H$2:$H$12,"SALIDA",'NORMA RUTH'!$J$2:$J$12,$B63),0) -> 0 | L63: =IFERROR(SUMIFS(VALERIA!$N$2:$N$10,VALERIA!$H$2:$H$10,"SALIDA",VALERIA!$J$2:$J$10,$B63),0) -> 0 | M63: =IFERROR(SUMIFS('MANUEL BANAMEX'!$N$2:$N$25,'MANUEL BANAMEX'!$H$2:$H$25,"SALIDA",'MANUEL BANAMEX'!$J$2:$J$25,$B63),0) -> 0 | N63: =IFERROR(SUMIFS(ROBERTO!$N$2:$N$2,ROBERTO!$H$2:$H$2,"SALIDA",ROBERTO!$J$2:$J$2,$B63),0) -> 0 | O63: =IFERROR(SUMIFS(JUAN!$N$2:$N$11,JUAN!$H$2:$H$11,"SALIDA",JUAN!$J$2:$J$11,$B63),0) -> 0 | P63: =IFERROR(SUMIFS('NORMA SANCHEZ'!$N$2:$N$14,'NORMA SANCHEZ'!$H$2:$H$14,"SALIDA",'NORMA SANCHEZ'!$J$2:$J$14,$B63),0) -> 0 | Q63: =IFERROR(SUMIFS('JOSE CARLOS'!$N$2:$N$16,'JOSE CARLOS'!$H$2:$H$16,"SALIDA",'JOSE CARLOS'!$J$2:$J$16,$B63),0) -> 0 | R63: =IFERROR(SUMIFS('LUIS ENRIQUE '!$N$2:$N$21,'LUIS ENRIQUE '!$H$2:$H$21,"SALIDA",'LUIS ENRIQUE '!$J$2:$J$21,$B63),0) -> 0 | S63: =IFERROR(SUMIFS(CESARIA!$N$2:$N$15,CESARIA!$H$2:$H$15,"SALIDA",CESARIA!$J$2:$J$15,$B63),0) -> 0 | T63: =IFERROR(SUMIFS(ALAN!$N$2:$N$14,ALAN!$H$2:$H$14,"SALIDA",ALAN!$J$2:$J$14,$B63),0) -> 0 | U63: =IFERROR(SUMIFS(ELVIA!$N$2:$N$6,ELVIA!$H$2:$H$6,"SALIDA",ELVIA!$J$2:$J$6,$B63),0) -> 0 | V63: =IFERROR(SUMIFS(CAJA!$N$2:$N$586,CAJA!$H$2:$H$586,"SALIDA",CAJA!$J$2:$J$586,$B63),0) -> 319000 | W63: =IFERROR(SUMIFS('CAJA TIGRES'!$N$2:$N$139,'CAJA TIGRES'!$H$2:$H$139,"SALIDA",'CAJA TIGRES'!$J$2:$J$139,$B63),0) -> 0 | X63: =IFERROR(SUMIFS(RESERVA!$N$2:$N$2,RESERVA!$H$2:$H$2,"SALIDA",RESERVA!$J$2:$J$2,$B63),0) -> 0 | Y63: =SUM(C63:X63) -> 319000 | Z63: =Y63 -> 319000
A64: 9 | B64: ACTIVOS | C64: =SUM(C65:C68) -> 79922.05 | D64: =SUM(D65:D68) -> 59357.11 | E64: =SUM(E65:E68) -> 0 | F64: =SUM(F65:F68) -> 0 | G64: =SUM(G65:G68) -> 0 | H64: =SUM(H65:H68) -> 0 | I64: =SUM(I65:I68) -> 0 | J64: =SUM(J65:J68) -> 0 | ... Z64: =SUM(Z65:Z68) -> 139279.16
A65: 9.1 | B65: VEHICULOS TRABAJO | C65: =IFERROR(SUMIFS('MGZ121'!$N$2:$N$175,'MGZ121'!H$2:H$175,"SALIDA",'MGZ121'!$J$2:$J$175,$B65),0) -> 79922.05 | D65: =IFERROR(SUMIFS('MGZ BBVA'!$N$2:$N$88,'MGZ BBVA'!$H$2:$H$88,"SALIDA",'MGZ BBVA'!$J$2:$J$88,$B65),0) -> 59357.11 | E65: =IFERROR(SUMIFS('MGZ DOLARES'!$N$2:$N$2,'MGZ DOLARES'!$F$2:$F$2,"SALIDA",'MGZ DOLARES'!$J$2:$J$2,$B65),0) -> 0 | F65: =IFERROR(SUMIFS('MGZ BAJIO'!$N$2:$N$4,'MGZ BAJIO'!$H$2:$H$4,"SALIDA",'MGZ BAJIO'!$J$2:$J$4,$B65),0) -> 0 | G65: =IFERROR(SUMIFS('VICTOR BANAMEX'!$N$2:$N$65,'VICTOR BANAMEX'!$H$2:$H$65,"SALIDA",'VICTOR BANAMEX'!$J$2:$J$65,$B65),0) -> 0 | H65: =IFERROR(SUMIFS('VICTOR BANORTE'!$N$2:$N$9,'VICTOR BANORTE'!$H$2:$H$9,"SALIDA",'VICTOR BANORTE'!$J$2:$J$9,$B65),0) -> 0 | I65: =IFERROR(SUMIFS(RODRIGO!$N$2:$N$2,RODRIGO!$H$2:$H$2,"SALIDA",RODRIGO!$J$2:$J$2,$B65),0) -> 0 | J65: =IFERROR(SUMIFS(MOY!$N$2:$N$12,MOY!$H$2:$H$12,"SALIDA",MOY!$J$2:$J$12,$B65),0) -> 0 | K65: =IFERROR(SUMIFS('NORMA RUTH'!$N$2:$N$12,'NORMA RUTH'!$H$2:$H$12,"SALIDA",'NORMA RUTH'!$J$2:$J$12,$B65),0) -> 0 | L65: =IFERROR(SUMIFS(VALERIA!$N$2:$N$10,VALERIA!$H$2:$H$10,"SALIDA",VALERIA!$J$2:$J$10,$B65),0) -> 0 | M65: =IFERROR(SUMIFS('MANUEL BANAMEX'!$N$2:$N$25,'MANUEL BANAMEX'!$H$2:$H$25,"SALIDA",'MANUEL BANAMEX'!$J$2:$J$25,$B65),0) -> 0 | N65: =IFERROR(SUMIFS(ROBERTO!$N$2:$N$2,ROBERTO!$H$2:$H$2,"SALIDA",ROBERTO!$J$2:$J$2,$B65),0) -> 0 | O65: =IFERROR(SUMIFS(JUAN!$N$2:$N$11,JUAN!$H$2:$H$11,"SALIDA",JUAN!$J$2:$J$11,$B65),0) -> 0 | P65: =IFERROR(SUMIFS('NORMA SANCHEZ'!$N$2:$N$14,'NORMA SANCHEZ'!$H$2:$H$14,"SALIDA",'NORMA SANCHEZ'!$J$2:$J$14,$B65),0) -> 0 | Q65: =IFERROR(SUMIFS('JOSE CARLOS'!$N$2:$N$16,'JOSE CARLOS'!$H$2:$H$16,"SALIDA",'JOSE CARLOS'!$J$2:$J$16,$B65),0) -> 0 | R65: =IFERROR(SUMIFS('LUIS ENRIQUE '!$N$2:$N$21,'LUIS ENRIQUE '!$H$2:$H$21,"SALIDA",'LUIS ENRIQUE '!$J$2:$J$21,$B65),0) -> 0 | S65: =IFERROR(SUMIFS(CESARIA!$N$2:$N$15,CESARIA!$H$2:$H$15,"SALIDA",CESARIA!$J$2:$J$15,$B65),0) -> 0 | T65: =IFERROR(SUMIFS(ALAN!$N$2:$N$14,ALAN!$H$2:$H$14,"SALIDA",ALAN!$J$2:$J$14,$B65),0) -> 0 | U65: =IFERROR(SUMIFS(ELVIA!$N$2:$N$6,ELVIA!$H$2:$H$6,"SALIDA",ELVIA!$J$2:$J$6,$B65),0) -> 0 | V65: =IFERROR(SUMIFS(CAJA!$N$2:$N$586,CAJA!$H$2:$H$586,"SALIDA",CAJA!$J$2:$J$586,$B65),0) -> 0 | W65: =IFERROR(SUMIFS('CAJA TIGRES'!$N$2:$N$139,'CAJA TIGRES'!$H$2:$H$139,"SALIDA",'CAJA TIGRES'!$J$2:$J$139,$B65),0) -> 0 | X65: =IFERROR(SUMIFS(RESERVA!$N$2:$N$2,RESERVA!$H$2:$H$2,"SALIDA",RESERVA!$J$2:$J$2,$B65),0) -> 0 | Y65: =SUM(C65:X65) -> 139279.16 | Z65: =Y65 -> 139279.16
A66: 9.2 | B66: TERRENOS | C66: =IFERROR(SUMIFS('MGZ121'!$N$2:$N$175,'MGZ121'!H$2:H$175,"SALIDA",'MGZ121'!$J$2:$J$175,$B66),0) -> 0 | D66: =IFERROR(SUMIFS('MGZ BBVA'!$N$2:$N$88,'MGZ BBVA'!$H$2:$H$88,"SALIDA",'MGZ BBVA'!$J$2:$J$88,$B66),0) -> 0 | E66: =IFERROR(SUMIFS('MGZ DOLARES'!$N$2:$N$2,'MGZ DOLARES'!$F$2:$F$2,"SALIDA",'MGZ DOLARES'!$J$2:$J$2,$B66),0) -> 0 | F66: =IFERROR(SUMIFS('MGZ BAJIO'!$N$2:$N$4,'MGZ BAJIO'!$H$2:$H$4,"SALIDA",'MGZ BAJIO'!$J$2:$J$4,$B66),0) -> 0 | G66: =IFERROR(SUMIFS('VICTOR BANAMEX'!$N$2:$N$65,'VICTOR BANAMEX'!$H$2:$H$65,"SALIDA",'VICTOR BANAMEX'!$J$2:$J$65,$B66),0) -> 0 | H66: =IFERROR(SUMIFS('VICTOR BANORTE'!$N$2:$N$9,'VICTOR BANORTE'!$H$2:$H$9,"SALIDA",'VICTOR BANORTE'!$J$2:$J$9,$B66),0) -> 0 | I66: =IFERROR(SUMIFS(RODRIGO!$N$2:$N$2,RODRIGO!$H$2:$H$2,"SALIDA",RODRIGO!$J$2:$J$2,$B66),0) -> 0 | J66: =IFERROR(SUMIFS(MOY!$N$2:$N$12,MOY!$H$2:$H$12,"SALIDA",MOY!$J$2:$J$12,$B66),0) -> 0 | K66: =IFERROR(SUMIFS('NORMA RUTH'!$N$2:$N$12,'NORMA RUTH'!$H$2:$H$12,"SALIDA",'NORMA RUTH'!$J$2:$J$12,$B66),0) -> 0 | L66: =IFERROR(SUMIFS(VALERIA!$N$2:$N$10,VALERIA!$H$2:$H$10,"SALIDA",VALERIA!$J$2:$J$10,$B66),0) -> 0 | M66: =IFERROR(SUMIFS('MANUEL BANAMEX'!$N$2:$N$25,'MANUEL BANAMEX'!$H$2:$H$25,"SALIDA",'MANUEL BANAMEX'!$J$2:$J$25,$B66),0) -> 0 | N66: =IFERROR(SUMIFS(ROBERTO!$N$2:$N$2,ROBERTO!$H$2:$H$2,"SALIDA",ROBERTO!$J$2:$J$2,$B66),0) -> 0 | O66: =IFERROR(SUMIFS(JUAN!$N$2:$N$11,JUAN!$H$2:$H$11,"SALIDA",JUAN!$J$2:$J$11,$B66),0) -> 0 | P66: =IFERROR(SUMIFS('NORMA SANCHEZ'!$N$2:$N$14,'NORMA SANCHEZ'!$H$2:$H$14,"SALIDA",'NORMA SANCHEZ'!$J$2:$J$14,$B66),0) -> 0 | Q66: =IFERROR(SUMIFS('JOSE CARLOS'!$N$2:$N$16,'JOSE CARLOS'!$H$2:$H$16,"SALIDA",'JOSE CARLOS'!$J$2:$J$16,$B66),0) -> 0 | R66: =IFERROR(SUMIFS('LUIS ENRIQUE '!$N$2:$N$21,'LUIS ENRIQUE '!$H$2:$H$21,"SALIDA",'LUIS ENRIQUE '!$J$2:$J$21,$B66),0) -> 0 | S66: =IFERROR(SUMIFS(CESARIA!$N$2:$N$15,CESARIA!$H$2:$H$15,"SALIDA",CESARIA!$J$2:$J$15,$B66),0) -> 0 | T66: =IFERROR(SUMIFS(ALAN!$N$2:$N$14,ALAN!$H$2:$H$14,"SALIDA",ALAN!$J$2:$J$14,$B66),0) -> 0 | U66: =IFERROR(SUMIFS(ELVIA!$N$2:$N$6,ELVIA!$H$2:$H$6,"SALIDA",ELVIA!$J$2:$J$6,$B66),0) -> 0 | V66: =IFERROR(SUMIFS(CAJA!$N$2:$N$586,CAJA!$H$2:$H$586,"SALIDA",CAJA!$J$2:$J$586,$B66),0) -> 0 | W66: =IFERROR(SUMIFS('CAJA TIGRES'!$N$2:$N$139,'CAJA TIGRES'!$H$2:$H$139,"SALIDA",'CAJA TIGRES'!$J$2:$J$139,$B66),0) -> 0 | X66: =IFERROR(SUMIFS(RESERVA!$N$2:$N$2,RESERVA!$H$2:$H$2,"SALIDA",RESERVA!$J$2:$J$2,$B66),0) -> 0 | Y66: =SUM(C66:X66) -> 0 | Z66: =Y66 -> 0
B67: AIRE ACONDICIONADO | C67: =IFERROR(SUMIFS('MGZ121'!$N$2:$N$175,'MGZ121'!H$2:H$175,"SALIDA",'MGZ121'!$J$2:$J$175,$B67),0) -> 0 | D67: =IFERROR(SUMIFS('MGZ BBVA'!$N$2:$N$88,'MGZ BBVA'!$H$2:$H$88,"SALIDA",'MGZ BBVA'!$J$2:$J$88,$B67),0) -> 0 | E67: =IFERROR(SUMIFS('MGZ DOLARES'!$N$2:$N$2,'MGZ DOLARES'!$F$2:$F$2,"SALIDA",'MGZ DOLARES'!$J$2:$J$2,$B67),0) -> 0 | F67: =IFERROR(SUMIFS('MGZ BAJIO'!$N$2:$N$4,'MGZ BAJIO'!$H$2:$H$4,"SALIDA",'MGZ BAJIO'!$J$2:$J$4,$B67),0) -> 0 | G67: =IFERROR(SUMIFS('VICTOR BANAMEX'!$N$2:$N$65,'VICTOR BANAMEX'!$H$2:$H$65,"SALIDA",'VICTOR BANAMEX'!$J$2:$J$65,$B67),0) -> 0 | H67: =IFERROR(SUMIFS('VICTOR BANORTE'!$N$2:$N$9,'VICTOR BANORTE'!$H$2:$H$9,"SALIDA",'VICTOR BANORTE'!$J$2:$J$9,$B67),0) -> 0 | I67: =IFERROR(SUMIFS(RODRIGO!$N$2:$N$2,RODRIGO!$H$2:$H$2,"SALIDA",RODRIGO!$J$2:$J$2,$B67),0) -> 0 | J67: =IFERROR(SUMIFS(MOY!$N$2:$N$12,MOY!$H$2:$H$12,"SALIDA",MOY!$J$2:$J$12,$B67),0) -> 0 | K67: =IFERROR(SUMIFS('NORMA RUTH'!$N$2:$N$12,'NORMA RUTH'!$H$2:$H$12,"SALIDA",'NORMA RUTH'!$J$2:$J$12,$B67),0) -> 0 | L67: =IFERROR(SUMIFS(VALERIA!$N$2:$N$10,VALERIA!$H$2:$H$10,"SALIDA",VALERIA!$J$2:$J$10,$B67),0) -> 0 | M67: =IFERROR(SUMIFS('MANUEL BANAMEX'!$N$2:$N$25,'MANUEL BANAMEX'!$H$2:$H$25,"SALIDA",'MANUEL BANAMEX'!$J$2:$J$25,$B67),0) -> 0 | N67: =IFERROR(SUMIFS(ROBERTO!$N$2:$N$2,ROBERTO!$H$2:$H$2,"SALIDA",ROBERTO!$J$2:$J$2,$B67),0) -> 0 | O67: =IFERROR(SUMIFS(JUAN!$N$2:$N$11,JUAN!$H$2:$H$11,"SALIDA",JUAN!$J$2:$J$11,$B67),0) -> 0 | P67: =IFERROR(SUMIFS('NORMA SANCHEZ'!$N$2:$N$14,'NORMA SANCHEZ'!$H$2:$H$14,"SALIDA",'NORMA SANCHEZ'!$J$2:$J$14,$B67),0) -> 0 | Q67: =IFERROR(SUMIFS('JOSE CARLOS'!$N$2:$N$16,'JOSE CARLOS'!$H$2:$H$16,"SALIDA",'JOSE CARLOS'!$J$2:$J$16,$B67),0) -> 0 | R67: =IFERROR(SUMIFS('LUIS ENRIQUE '!$N$2:$N$21,'LUIS ENRIQUE '!$H$2:$H$21,"SALIDA",'LUIS ENRIQUE '!$J$2:$J$21,$B67),0) -> 0 | S67: =IFERROR(SUMIFS(CESARIA!$N$2:$N$15,CESARIA!$H$2:$H$15,"SALIDA",CESARIA!$J$2:$J$15,$B67),0) -> 0 | T67: =IFERROR(SUMIFS(ALAN!$N$2:$N$14,ALAN!$H$2:$H$14,"SALIDA",ALAN!$J$2:$J$14,$B67),0) -> 0 | U67: =IFERROR(SUMIFS(ELVIA!$N$2:$N$6,ELVIA!$H$2:$H$6,"SALIDA",ELVIA!$J$2:$J$6,$B67),0) -> 0 | V67: =IFERROR(SUMIFS(CAJA!$N$2:$N$586,CAJA!$H$2:$H$586,"SALIDA",CAJA!$J$2:$J$586,$B67),0) -> 0 | W67: =IFERROR(SUMIFS('CAJA TIGRES'!$N$2:$N$139,'CAJA TIGRES'!$H$2:$H$139,"SALIDA",'CAJA TIGRES'!$J$2:$J$139,$B67),0) -> 0 | X67: =IFERROR(SUMIFS(RESERVA!$N$2:$N$2,RESERVA!$H$2:$H$2,"SALIDA",RESERVA!$J$2:$J$2,$B67),0) -> 0 | Y67: =SUM(C67:X67) -> 0 | Z67: =Y67 -> 0
B68: EQUIPOS DIVERSOS | C68: =IFERROR(SUMIFS('MGZ121'!$N$2:$N$175,'MGZ121'!H$2:H$175,"SALIDA",'MGZ121'!$J$2:$J$175,$B68),0) -> 0 | D68: =IFERROR(SUMIFS('MGZ BBVA'!$N$2:$N$88,'MGZ BBVA'!$H$2:$H$88,"SALIDA",'MGZ BBVA'!$J$2:$J$88,$B68),0) -> 0 | E68: =IFERROR(SUMIFS('MGZ DOLARES'!$N$2:$N$2,'MGZ DOLARES'!$F$2:$F$2,"SALIDA",'MGZ DOLARES'!$J$2:$J$2,$B68),0) -> 0 | F68: =IFERROR(SUMIFS('MGZ BAJIO'!$N$2:$N$4,'MGZ BAJIO'!$H$2:$H$4,"SALIDA",'MGZ BAJIO'!$J$2:$J$4,$B68),0) -> 0 | G68: =IFERROR(SUMIFS('VICTOR BANAMEX'!$N$2:$N$65,'VICTOR BANAMEX'!$H$2:$H$65,"SALIDA",'VICTOR BANAMEX'!$J$2:$J$65,$B68),0) -> 0 | H68: =IFERROR(SUMIFS('VICTOR BANORTE'!$N$2:$N$9,'VICTOR BANORTE'!$H$2:$H$9,"SALIDA",'VICTOR BANORTE'!$J$2:$J$9,$B68),0) -> 0 | I68: =IFERROR(SUMIFS(RODRIGO!$N$2:$N$2,RODRIGO!$H$2:$H$2,"SALIDA",RODRIGO!$J$2:$J$2,$B68),0) -> 0 | J68: =IFERROR(SUMIFS(MOY!$N$2:$N$12,MOY!$H$2:$H$12,"SALIDA",MOY!$J$2:$J$12,$B68),0) -> 0 | K68: =IFERROR(SUMIFS('NORMA RUTH'!$N$2:$N$12,'NORMA RUTH'!$H$2:$H$12,"SALIDA",'NORMA RUTH'!$J$2:$J$12,$B68),0) -> 0 | L68: =IFERROR(SUMIFS(VALERIA!$N$2:$N$10,VALERIA!$H$2:$H$10,"SALIDA",VALERIA!$J$2:$J$10,$B68),0) -> 0 | M68: =IFERROR(SUMIFS('MANUEL BANAMEX'!$N$2:$N$25,'MANUEL BANAMEX'!$H$2:$H$25,"SALIDA",'MANUEL BANAMEX'!$J$2:$J$25,$B68),0) -> 0 | N68: =IFERROR(SUMIFS(ROBERTO!$N$2:$N$2,ROBERTO!$H$2:$H$2,"SALIDA",ROBERTO!$J$2:$J$2,$B68),0) -> 0 | O68: =IFERROR(SUMIFS(JUAN!$N$2:$N$11,JUAN!$H$2:$H$11,"SALIDA",JUAN!$J$2:$J$11,$B68),0) -> 0 | P68: =IFERROR(SUMIFS('NORMA SANCHEZ'!$N$2:$N$14,'NORMA SANCHEZ'!$H$2:$H$14,"SALIDA",'NORMA SANCHEZ'!$J$2:$J$14,$B68),0) -> 0 | Q68: =IFERROR(SUMIFS('JOSE CARLOS'!$N$2:$N$16,'JOSE CARLOS'!$H$2:$H$16,"SALIDA",'JOSE CARLOS'!$J$2:$J$16,$B68),0) -> 0 | R68: =IFERROR(SUMIFS('LUIS ENRIQUE '!$N$2:$N$21,'LUIS ENRIQUE '!$H$2:$H$21,"SALIDA",'LUIS ENRIQUE '!$J$2:$J$21,$B68),0) -> 0 | S68: =IFERROR(SUMIFS(CESARIA!$N$2:$N$15,CESARIA!$H$2:$H$15,"SALIDA",CESARIA!$J$2:$J$15,$B68),0) -> 0 | T68: =IFERROR(SUMIFS(ALAN!$N$2:$N$14,ALAN!$H$2:$H$14,"SALIDA",ALAN!$J$2:$J$14,$B68),0) -> 0 | U68: =IFERROR(SUMIFS(ELVIA!$N$2:$N$6,ELVIA!$H$2:$H$6,"SALIDA",ELVIA!$J$2:$J$6,$B68),0) -> 0 | V68: =IFERROR(SUMIFS(CAJA!$N$2:$N$586,CAJA!$H$2:$H$586,"SALIDA",CAJA!$J$2:$J$586,$B68),0) -> 0 | W68: =IFERROR(SUMIFS('CAJA TIGRES'!$N$2:$N$139,'CAJA TIGRES'!$H$2:$H$139,"SALIDA",'CAJA TIGRES'!$J$2:$J$139,$B68),0) -> 0 | X68: =IFERROR(SUMIFS(RESERVA!$N$2:$N$2,RESERVA!$H$2:$H$2,"SALIDA",RESERVA!$J$2:$J$2,$B68),0) -> 0 | Y68: =SUM(C68:X68) -> 0 | Z68: =Y68 -> 0
A69: 10 | B69: IMPUESTOS | C69: =C70 -> 414368 | D69: =D70 -> 14367 | E69: =E70 -> 0 | F69: =F70 -> 0 | G69: =G70 -> 35244 | H69: =H70 -> 0 | I69: =I70 -> 0 | J69: =J70 -> 0 | ... Z69: =Z70 -> 576379.4
A70: 10.1 | B70: IMPUESTOS | C70: =IFERROR(SUMIFS('MGZ121'!$N$2:$N$175,'MGZ121'!H$2:H$175,"SALIDA",'MGZ121'!$J$2:$J$175,$B70),0) -> 414368 | D70: =IFERROR(SUMIFS('MGZ BBVA'!$N$2:$N$88,'MGZ BBVA'!$H$2:$H$88,"SALIDA",'MGZ BBVA'!$J$2:$J$88,$B70),0) -> 14367 | E70: =IFERROR(SUMIFS('MGZ DOLARES'!$N$2:$N$2,'MGZ DOLARES'!$F$2:$F$2,"SALIDA",'MGZ DOLARES'!$J$2:$J$2,$B70),0) -> 0 | F70: =IFERROR(SUMIFS('MGZ BAJIO'!$N$2:$N$4,'MGZ BAJIO'!$H$2:$H$4,"SALIDA",'MGZ BAJIO'!$J$2:$J$4,$B70),0) -> 0 | G70: =IFERROR(SUMIFS('VICTOR BANAMEX'!$N$2:$N$65,'VICTOR BANAMEX'!$H$2:$H$65,"SALIDA",'VICTOR BANAMEX'!$J$2:$J$65,$B70),0) -> 35244 | H70: =IFERROR(SUMIFS('VICTOR BANORTE'!$N$2:$N$9,'VICTOR BANORTE'!$H$2:$H$9,"SALIDA",'VICTOR BANORTE'!$J$2:$J$9,$B70),0) -> 0 | I70: =IFERROR(SUMIFS(RODRIGO!$N$2:$N$2,RODRIGO!$H$2:$H$2,"SALIDA",RODRIGO!$J$2:$J$2,$B70),0) -> 0 | J70: =IFERROR(SUMIFS(MOY!$N$2:$N$12,MOY!$H$2:$H$12,"SALIDA",MOY!$J$2:$J$12,$B70),0) -> 0 | K70: =IFERROR(SUMIFS('NORMA RUTH'!$N$2:$N$12,'NORMA RUTH'!$H$2:$H$12,"SALIDA",'NORMA RUTH'!$J$2:$J$12,$B70),0) -> 22704 | L70: =IFERROR(SUMIFS(VALERIA!$N$2:$N$10,VALERIA!$H$2:$H$10,"SALIDA",VALERIA!$J$2:$J$10,$B70),0) -> 29481 | M70: =IFERROR(SUMIFS('MANUEL BANAMEX'!$N$2:$N$25,'MANUEL BANAMEX'!$H$2:$H$25,"SALIDA",'MANUEL BANAMEX'!$J$2:$J$25,$B70),0) -> 14235 | N70: =IFERROR(SUMIFS(ROBERTO!$N$2:$N$2,ROBERTO!$H$2:$H$2,"SALIDA",ROBERTO!$J$2:$J$2,$B70),0) -> 0 | O70: =IFERROR(SUMIFS(JUAN!$N$2:$N$11,JUAN!$H$2:$H$11,"SALIDA",JUAN!$J$2:$J$11,$B70),0) -> 1531 | P70: =IFERROR(SUMIFS('NORMA SANCHEZ'!$N$2:$N$14,'NORMA SANCHEZ'!$H$2:$H$14,"SALIDA",'NORMA SANCHEZ'!$J$2:$J$14,$B70),0) -> 4858 | Q70: =IFERROR(SUMIFS('JOSE CARLOS'!$N$2:$N$16,'JOSE CARLOS'!$H$2:$H$16,"SALIDA",'JOSE CARLOS'!$J$2:$J$16,$B70),0) -> 2750 | R70: =IFERROR(SUMIFS('LUIS ENRIQUE '!$N$2:$N$21,'LUIS ENRIQUE '!$H$2:$H$21,"SALIDA",'LUIS ENRIQUE '!$J$2:$J$21,$B70),0) -> 19120 | S70: =IFERROR(SUMIFS(CESARIA!$N$2:$N$15,CESARIA!$H$2:$H$15,"SALIDA",CESARIA!$J$2:$J$15,$B70),0) -> 5705 | T70: =IFERROR(SUMIFS(ALAN!$N$2:$N$14,ALAN!$H$2:$H$14,"SALIDA",ALAN!$J$2:$J$14,$B70),0) -> 0 | U70: =IFERROR(SUMIFS(ELVIA!$N$2:$N$6,ELVIA!$H$2:$H$6,"SALIDA",ELVIA!$J$2:$J$6,$B70),0) -> 10711 | V70: =IFERROR(SUMIFS(CAJA!$N$2:$N$586,CAJA!$H$2:$H$586,"SALIDA",CAJA!$J$2:$J$586,$B70),0) -> 1305.4 | W70: =IFERROR(SUMIFS('CAJA TIGRES'!$N$2:$N$139,'CAJA TIGRES'!$H$2:$H$139,"SALIDA",'CAJA TIGRES'!$J$2:$J$139,$B70),0) -> 0 | X70: =IFERROR(SUMIFS(RESERVA!$N$2:$N$2,RESERVA!$H$2:$H$2,"SALIDA",RESERVA!$J$2:$J$2,$B70),0) -> 0 | Y70: =SUM(C70:X70) -> 576379.4 | Z70: =Y70 -> 576379.4
A71: 13 | B71: EXTERNA | C71: =C72 -> 0 | D71: =D72 -> 0 | E71: =E72 -> 0 | F71: =F72 -> 0 | G71: =G72 -> 0 | H71: =H72 -> 0 | I71: =I72 -> 0 | J71: =J72 -> 0 | ... Z71: =Z72 -> 15766.85
A72: 13.1 | B72: DEV. VENTA EXTERNA | C72: =IFERROR(SUMIFS('MGZ121'!$N$2:$N$175,'MGZ121'!H$2:H$175,"SALIDA",'MGZ121'!$J$2:$J$175,$B72),0) -> 0 | D72: =IFERROR(SUMIFS('MGZ BBVA'!$N$2:$N$88,'MGZ BBVA'!$H$2:$H$88,"SALIDA",'MGZ BBVA'!$J$2:$J$88,$B72),0) -> 0 | E72: =IFERROR(SUMIFS('MGZ DOLARES'!$N$2:$N$2,'MGZ DOLARES'!$F$2:$F$2,"SALIDA",'MGZ DOLARES'!$J$2:$J$2,$B72),0) -> 0 | F72: =IFERROR(SUMIFS('MGZ BAJIO'!$N$2:$N$4,'MGZ BAJIO'!$H$2:$H$4,"SALIDA",'MGZ BAJIO'!$J$2:$J$4,$B72),0) -> 0 | G72: =IFERROR(SUMIFS('VICTOR BANAMEX'!$N$2:$N$65,'VICTOR BANAMEX'!$H$2:$H$65,"SALIDA",'VICTOR BANAMEX'!$J$2:$J$65,$B72),0) -> 0 | H72: =IFERROR(SUMIFS('VICTOR BANORTE'!$N$2:$N$9,'VICTOR BANORTE'!$H$2:$H$9,"SALIDA",'VICTOR BANORTE'!$J$2:$J$9,$B72),0) -> 0 | I72: =IFERROR(SUMIFS(RODRIGO!$N$2:$N$2,RODRIGO!$H$2:$H$2,"SALIDA",RODRIGO!$J$2:$J$2,$B72),0) -> 0 | J72: =IFERROR(SUMIFS(MOY!$N$2:$N$12,MOY!$H$2:$H$12,"SALIDA",MOY!$J$2:$J$12,$B72),0) -> 0 | K72: =IFERROR(SUMIFS('NORMA RUTH'!$N$2:$N$12,'NORMA RUTH'!$H$2:$H$12,"SALIDA",'NORMA RUTH'!$J$2:$J$12,$B72),0) -> 0 | L72: =IFERROR(SUMIFS(VALERIA!$N$2:$N$10,VALERIA!$H$2:$H$10,"SALIDA",VALERIA!$J$2:$J$10,$B72),0) -> 0 | M72: =IFERROR(SUMIFS('MANUEL BANAMEX'!$N$2:$N$25,'MANUEL BANAMEX'!$H$2:$H$25,"SALIDA",'MANUEL BANAMEX'!$J$2:$J$25,$B72),0) -> 8180.42 | N72: =IFERROR(SUMIFS(ROBERTO!$N$2:$N$2,ROBERTO!$H$2:$H$2,"SALIDA",ROBERTO!$J$2:$J$2,$B72),0) -> 0 | O72: =IFERROR(SUMIFS(JUAN!$N$2:$N$11,JUAN!$H$2:$H$11,"SALIDA",JUAN!$J$2:$J$11,$B72),0) -> 0 | P72: =IFERROR(SUMIFS('NORMA SANCHEZ'!$N$2:$N$14,'NORMA SANCHEZ'!$H$2:$H$14,"SALIDA",'NORMA SANCHEZ'!$J$2:$J$14,$B72),0) -> 7586.43 | Q72: =IFERROR(SUMIFS('JOSE CARLOS'!$N$2:$N$16,'JOSE CARLOS'!$H$2:$H$16,"SALIDA",'JOSE CARLOS'!$J$2:$J$16,$B72),0) -> 0 | R72: =IFERROR(SUMIFS('LUIS ENRIQUE '!$N$2:$N$21,'LUIS ENRIQUE '!$H$2:$H$21,"SALIDA",'LUIS ENRIQUE '!$J$2:$J$21,$B72),0) -> 0 | S72: =IFERROR(SUMIFS(CESARIA!$N$2:$N$15,CESARIA!$H$2:$H$15,"SALIDA",CESARIA!$J$2:$J$15,$B72),0) -> 0 | T72: =IFERROR(SUMIFS(ALAN!$N$2:$N$14,ALAN!$H$2:$H$14,"SALIDA",ALAN!$J$2:$J$14,$B72),0) -> 0 | U72: =IFERROR(SUMIFS(ELVIA!$N$2:$N$6,ELVIA!$H$2:$H$6,"SALIDA",ELVIA!$J$2:$J$6,$B72),0) -> 0 | V72: =IFERROR(SUMIFS(CAJA!$N$2:$N$586,CAJA!$H$2:$H$586,"SALIDA",CAJA!$J$2:$J$586,$B72),0) -> 0 | W72: =IFERROR(SUMIFS('CAJA TIGRES'!$N$2:$N$139,'CAJA TIGRES'!$H$2:$H$139,"SALIDA",'CAJA TIGRES'!$J$2:$J$139,$B72),0) -> 0 | X72: =IFERROR(SUMIFS(RESERVA!$N$2:$N$2,RESERVA!$H$2:$H$2,"SALIDA",RESERVA!$J$2:$J$2,$B72),0) -> 0 | Y72: =SUM(C72:X72) -> 15766.85 | Z72: =Y72 -> 15766.85
B73: Total de Egresos Propios | C73: =C17+C21+C29+C49+C60+C64+C69+C71 -> 3024090.8 | D73: =D17+D21+D29+D49+D60+D64+D69+D71 -> 1106014.7 | E73: =E17+E21+E29+E49+E60+E64+E69+E71 -> 0 | F73: =F17+F21+F29+F49+F60+F64+F69+F71 -> 580 | G73: =G17+G21+G29+G49+G60+G64+G69+G71 -> 280880.11 | H73: =H17+H21+H29+H49+H60+H64+H69+H71 -> 511.4 | I73: =I17+I21+I29+I49+I60+I64+I69+I71 -> 0 | J73: =J17+J21+J29+J49+J60+J64+J69+J71 -> 455.88 | ... Z73: =Z17+Z21+Z29+Z49+Z60+Z64+Z69+Z71 -> 8630146.3
B74: Flujo de Operación | C74: =C14-C73 -> 3863449.2 | D74: =D14-D73 -> 912646.3 | E74: =E14-E73 -> 0 | F74: =F14-F73 -> -580 | G74: =G14-G73 -> -280880.11 | H74: =H14-H73 -> -511.4 | I74: =I14-I73 -> 0 | J74: =J14-J73 -> -455.88 | ... Z74: =Z14-Z73 -> 1737711.7
B76: ENTRADAS
A77: 8 | B77: PRESTAMOS
A78: 8.1 | B78: BANCARIOS | C78: =IFERROR(SUMIFS('MGZ121'!$M$2:'MGZ121'!$M$175,'MGZ121'!$H$2:$H$175,"ENTRADA",'MGZ121'!$J$2:$J$175,B78),0) -> 0 | D78: =IFERROR(SUMIFS('MGZ BBVA'!$M$2:$M$88,'MGZ BBVA'!$H$2:$H$88,"ENTRADA",'MGZ BBVA'!$J$2:$J$88,$B78),0) -> 0 | E78: =IFERROR(SUMIFS('MGZ DOLARES'!$M$2:$M$2,'MGZ DOLARES'!$F$2:$F$2,"ENTRADA",'MGZ DOLARES'!$J$2:$J$2,$B78),0) -> 0 | F78: =IFERROR(SUMIFS('MGZ BAJIO'!$M$2:$M$4,'MGZ BAJIO'!$H$2:$H$4,"ENTRADA",'MGZ BAJIO'!$J$2:$J$4,$B78),0) -> 0 | G78: =IFERROR(SUMIFS('VICTOR BANAMEX'!$M$2:$M$65,'VICTOR BANAMEX'!$H$2:$H$65,"ENTRADA",'VICTOR BANAMEX'!$J$2:$J$65,$B78),0) -> 0 | H78: =IFERROR(SUMIFS('VICTOR BANORTE'!$M$2:$M$9,'VICTOR BANORTE'!$H$2:$H$9,"ENTRADA",'VICTOR BANORTE'!$J$2:$J$9,$B78),0) -> 0 | I78: =IFERROR(SUMIFS(RODRIGO!$M$2:$M$2,RODRIGO!$H$2:$H$2,"ENTRADA",RODRIGO!$J$2:$J$2,$B78),0) -> 0 | J78: =IFERROR(SUMIFS(MOY!$M$2:$M$12,MOY!$H$2:$H$12,"ENTRADA",MOY!$J$2:$J$12,$B78),0) -> 0 | K78: =IFERROR(SUMIFS('NORMA RUTH'!$M$2:$M$12,'NORMA RUTH'!$H$2:$H$12,"ENTRADA",'NORMA RUTH'!$J$2:$J$12,$B78),0) -> 0 | L78: =IFERROR(SUMIFS(VALERIA!$M$2:$M$10,VALERIA!$H$2:$H$10,"ENTRADA",VALERIA!$J$2:$J$10,$B78),0) -> 0 | M78: =IFERROR(SUMIFS('MANUEL BANAMEX'!$M$2:$M$25,'MANUEL BANAMEX'!$H$2:$H$25,"ENTRADA",'MANUEL BANAMEX'!$J$2:$J$25,$B78),0) -> 0 | N78: =IFERROR(SUMIFS(ROBERTO!$M$2:$M$2,ROBERTO!$H$2:$H$2,"ENTRADA",ROBERTO!$J$2:$J$2,$B78),0) -> 0 | O78: =IFERROR(SUMIFS(JUAN!$M$2:$M$11,JUAN!$H$2:$H$11,"ENTRADA",JUAN!$J$2:$J$11,$B78),0) -> 0 | P78: =IFERROR(SUMIFS('NORMA SANCHEZ'!$M$2:$M$14,'NORMA SANCHEZ'!$H$2:$H$14,"ENTRADA",'NORMA SANCHEZ'!$J$2:$J$14,$B78),0) -> 0 | Q78: =IFERROR(SUMIFS('JOSE CARLOS'!$M$2:$M$16,'JOSE CARLOS'!$H$2:$H$16,"ENTRADA",'JOSE CARLOS'!$J$2:$J$16,$B78),0) -> 0 | R78: =IFERROR(SUMIFS('LUIS ENRIQUE '!$M$2:$M$21,'LUIS ENRIQUE '!$H$2:$H$21,"ENTRADA",'LUIS ENRIQUE '!$J$2:$J$21,$B78),0) -> 0 | S78: =IFERROR(SUMIFS(CESARIA!$M$2:$M$15,CESARIA!$H$2:$H$15,"ENTRADA",CESARIA!$J$2:$J$15,$B78),0) -> 0 | T78: =IFERROR(SUMIFS(ALAN!$M$2:$M$14,ALAN!$H$2:$H$14,"ENTRADA",ALAN!$J$2:$J$14,$B78),0) -> 0 | U78: =IFERROR(SUMIFS(ELVIA!$M$2:$M$6,ELVIA!$H$2:$H$6,"ENTRADA",ELVIA!$J$2:$J$6,$B78),0) -> 0 | V78: =IFERROR(SUMIFS(CAJA!$M$2:$M$586,CAJA!$H$2:$H$586,"ENTRADA",CAJA!$J$2:$J$586,$B78),0) -> 0 | W78: =IFERROR(SUMIFS('CAJA TIGRES'!$M$2:$M$139,'CAJA TIGRES'!$H$2:$H$139,"ENTRADA",'CAJA TIGRES'!$J$2:$J$139,$B78),0) -> 0 | X78: =IFERROR(SUMIFS(RESERVA!$M$2:$M$2,RESERVA!$H$2:$H$2,"ENTRADA",RESERVA!$J$2:$J$2,$B78),0) -> 0 | Y78: =SUM(C78:X78) -> 0 | Z78: =Y78 -> 0
A79: 8.2 | B79: EXTERNOS | C79: =IFERROR(SUMIFS('MGZ121'!$M$2:'MGZ121'!$M$175,'MGZ121'!$H$2:$H$175,"ENTRADA",'MGZ121'!$J$2:$J$175,B79),0) -> 314585 | D79: =IFERROR(SUMIFS('MGZ BBVA'!$M$2:$M$88,'MGZ BBVA'!$H$2:$H$88,"ENTRADA",'MGZ BBVA'!$J$2:$J$88,$B79),0) -> 0 | E79: =IFERROR(SUMIFS('MGZ DOLARES'!$M$2:$M$2,'MGZ DOLARES'!$F$2:$F$2,"ENTRADA",'MGZ DOLARES'!$J$2:$J$2,$B79),0) -> 0 | F79: =IFERROR(SUMIFS('MGZ BAJIO'!$M$2:$M$4,'MGZ BAJIO'!$H$2:$H$4,"ENTRADA",'MGZ BAJIO'!$J$2:$J$4,$B79),0) -> 0 | G79: =IFERROR(SUMIFS('VICTOR BANAMEX'!$M$2:$M$65,'VICTOR BANAMEX'!$H$2:$H$65,"ENTRADA",'VICTOR BANAMEX'!$J$2:$J$65,$B79),0) -> 0 | H79: =IFERROR(SUMIFS('VICTOR BANORTE'!$M$2:$M$9,'VICTOR BANORTE'!$H$2:$H$9,"ENTRADA",'VICTOR BANORTE'!$J$2:$J$9,$B79),0) -> 0 | I79: =IFERROR(SUMIFS(RODRIGO!$M$2:$M$2,RODRIGO!$H$2:$H$2,"ENTRADA",RODRIGO!$J$2:$J$2,$B79),0) -> 0 | J79: =IFERROR(SUMIFS(MOY!$M$2:$M$12,MOY!$H$2:$H$12,"ENTRADA",MOY!$J$2:$J$12,$B79),0) -> 0 | K79: =IFERROR(SUMIFS('NORMA RUTH'!$M$2:$M$12,'NORMA RUTH'!$H$2:$H$12,"ENTRADA",'NORMA RUTH'!$J$2:$J$12,$B79),0) -> 0 | L79: =IFERROR(SUMIFS(VALERIA!$M$2:$M$10,VALERIA!$H$2:$H$10,"ENTRADA",VALERIA!$J$2:$J$10,$B79),0) -> 0 | M79: =IFERROR(SUMIFS('MANUEL BANAMEX'!$M$2:$M$25,'MANUEL BANAMEX'!$H$2:$H$25,"ENTRADA",'MANUEL BANAMEX'!$J$2:$J$25,$B79),0) -> 0 | N79: =IFERROR(SUMIFS(ROBERTO!$M$2:$M$2,ROBERTO!$H$2:$H$2,"ENTRADA",ROBERTO!$J$2:$J$2,$B79),0) -> 0 | O79: =IFERROR(SUMIFS(JUAN!$M$2:$M$11,JUAN!$H$2:$H$11,"ENTRADA",JUAN!$J$2:$J$11,$B79),0) -> 0 | P79: =IFERROR(SUMIFS('NORMA SANCHEZ'!$M$2:$M$14,'NORMA SANCHEZ'!$H$2:$H$14,"ENTRADA",'NORMA SANCHEZ'!$J$2:$J$14,$B79),0) -> 0 | Q79: =IFERROR(SUMIFS('JOSE CARLOS'!$M$2:$M$16,'JOSE CARLOS'!$H$2:$H$16,"ENTRADA",'JOSE CARLOS'!$J$2:$J$16,$B79),0) -> 0 | R79: =IFERROR(SUMIFS('LUIS ENRIQUE '!$M$2:$M$21,'LUIS ENRIQUE '!$H$2:$H$21,"ENTRADA",'LUIS ENRIQUE '!$J$2:$J$21,$B79),0) -> 0 | S79: =IFERROR(SUMIFS(CESARIA!$M$2:$M$15,CESARIA!$H$2:$H$15,"ENTRADA",CESARIA!$J$2:$J$15,$B79),0) -> 0 | T79: =IFERROR(SUMIFS(ALAN!$M$2:$M$14,ALAN!$H$2:$H$14,"ENTRADA",ALAN!$J$2:$J$14,$B79),0) -> 0 | U79: =IFERROR(SUMIFS(ELVIA!$M$2:$M$6,ELVIA!$H$2:$H$6,"ENTRADA",ELVIA!$J$2:$J$6,$B79),0) -> 0 | V79: =IFERROR(SUMIFS(CAJA!$M$2:$M$586,CAJA!$H$2:$H$586,"ENTRADA",CAJA!$J$2:$J$586,$B79),0) -> 89910 | W79: =IFERROR(SUMIFS('CAJA TIGRES'!$M$2:$M$139,'CAJA TIGRES'!$H$2:$H$139,"ENTRADA",'CAJA TIGRES'!$J$2:$J$139,$B79),0) -> 0 | X79: =IFERROR(SUMIFS(RESERVA!$M$2:$M$2,RESERVA!$H$2:$H$2,"ENTRADA",RESERVA!$J$2:$J$2,$B79),0) -> 0 | Y79: =SUM(C79:X79) -> 404495 | Z79: =Y79 -> 404495
B80: TRABAJADORES | C80: =IFERROR(SUMIFS('MGZ121'!$M$2:'MGZ121'!$M$175,'MGZ121'!$H$2:$H$175,"ENTRADA",'MGZ121'!$J$2:$J$175,B80),0) -> 0 | D80: =IFERROR(SUMIFS('MGZ BBVA'!$M$2:$M$88,'MGZ BBVA'!$H$2:$H$88,"ENTRADA",'MGZ BBVA'!$J$2:$J$88,$B80),0) -> 0 | E80: =IFERROR(SUMIFS('MGZ DOLARES'!$M$2:$M$2,'MGZ DOLARES'!$F$2:$F$2,"ENTRADA",'MGZ DOLARES'!$J$2:$J$2,$B80),0) -> 0 | F80: =IFERROR(SUMIFS('MGZ BAJIO'!$M$2:$M$4,'MGZ BAJIO'!$H$2:$H$4,"ENTRADA",'MGZ BAJIO'!$J$2:$J$4,$B80),0) -> 0 | G80: =IFERROR(SUMIFS('VICTOR BANAMEX'!$M$2:$M$65,'VICTOR BANAMEX'!$H$2:$H$65,"ENTRADA",'VICTOR BANAMEX'!$J$2:$J$65,$B80),0) -> 0 | H80: =IFERROR(SUMIFS('VICTOR BANORTE'!$M$2:$M$9,'VICTOR BANORTE'!$H$2:$H$9,"ENTRADA",'VICTOR BANORTE'!$J$2:$J$9,$B80),0) -> 0 | I80: =IFERROR(SUMIFS(RODRIGO!$M$2:$M$2,RODRIGO!$H$2:$H$2,"ENTRADA",RODRIGO!$J$2:$J$2,$B80),0) -> 0 | J80: =IFERROR(SUMIFS(MOY!$M$2:$M$12,MOY!$H$2:$H$12,"ENTRADA",MOY!$J$2:$J$12,$B80),0) -> 0 | K80: =IFERROR(SUMIFS('NORMA RUTH'!$M$2:$M$12,'NORMA RUTH'!$H$2:$H$12,"ENTRADA",'NORMA RUTH'!$J$2:$J$12,$B80),0) -> 0 | L80: =IFERROR(SUMIFS(VALERIA!$M$2:$M$10,VALERIA!$H$2:$H$10,"ENTRADA",VALERIA!$J$2:$J$10,$B80),0) -> 0 | M80: =IFERROR(SUMIFS('MANUEL BANAMEX'!$M$2:$M$25,'MANUEL BANAMEX'!$H$2:$H$25,"ENTRADA",'MANUEL BANAMEX'!$J$2:$J$25,$B80),0) -> 0 | N80: =IFERROR(SUMIFS(ROBERTO!$M$2:$M$2,ROBERTO!$H$2:$H$2,"ENTRADA",ROBERTO!$J$2:$J$2,$B80),0) -> 0 | O80: =IFERROR(SUMIFS(JUAN!$M$2:$M$11,JUAN!$H$2:$H$11,"ENTRADA",JUAN!$J$2:$J$11,$B80),0) -> 0 | P80: =IFERROR(SUMIFS('NORMA SANCHEZ'!$M$2:$M$14,'NORMA SANCHEZ'!$H$2:$H$14,"ENTRADA",'NORMA SANCHEZ'!$J$2:$J$14,$B80),0) -> 0 | Q80: =IFERROR(SUMIFS('JOSE CARLOS'!$M$2:$M$16,'JOSE CARLOS'!$H$2:$H$16,"ENTRADA",'JOSE CARLOS'!$J$2:$J$16,$B80),0) -> 0 | R80: =IFERROR(SUMIFS('LUIS ENRIQUE '!$M$2:$M$21,'LUIS ENRIQUE '!$H$2:$H$21,"ENTRADA",'LUIS ENRIQUE '!$J$2:$J$21,$B80),0) -> 0 | S80: =IFERROR(SUMIFS(CESARIA!$M$2:$M$15,CESARIA!$H$2:$H$15,"ENTRADA",CESARIA!$J$2:$J$15,$B80),0) -> 0 | T80: =IFERROR(SUMIFS(ALAN!$M$2:$M$14,ALAN!$H$2:$H$14,"ENTRADA",ALAN!$J$2:$J$14,$B80),0) -> 0 | U80: =IFERROR(SUMIFS(ELVIA!$M$2:$M$6,ELVIA!$H$2:$H$6,"ENTRADA",ELVIA!$J$2:$J$6,$B80),0) -> 0 | V80: =IFERROR(SUMIFS(CAJA!$M$2:$M$586,CAJA!$H$2:$H$586,"ENTRADA",CAJA!$J$2:$J$586,$B80),0) -> 1000 | W80: =IFERROR(SUMIFS('CAJA TIGRES'!$M$2:$M$139,'CAJA TIGRES'!$H$2:$H$139,"ENTRADA",'CAJA TIGRES'!$J$2:$J$139,$B80),0) -> 150 | X80: =IFERROR(SUMIFS(RESERVA!$M$2:$M$2,RESERVA!$H$2:$H$2,"ENTRADA",RESERVA!$J$2:$J$2,$B80),0) -> 0 | Y80: =SUM(C80:X80) -> 1150 | Z80: =Y80 -> 1150
B81: SOCIOS | C81: =IFERROR(SUMIFS('MGZ121'!$M$2:'MGZ121'!$M$175,'MGZ121'!$H$2:$H$175,"ENTRADA",'MGZ121'!$J$2:$J$175,B81),0) -> 0 | D81: =IFERROR(SUMIFS('MGZ BBVA'!$M$2:$M$88,'MGZ BBVA'!$H$2:$H$88,"ENTRADA",'MGZ BBVA'!$J$2:$J$88,$B81),0) -> 43000 | E81: =IFERROR(SUMIFS('MGZ DOLARES'!$M$2:$M$2,'MGZ DOLARES'!$F$2:$F$2,"ENTRADA",'MGZ DOLARES'!$J$2:$J$2,$B81),0) -> 0 | F81: =IFERROR(SUMIFS('MGZ BAJIO'!$M$2:$M$4,'MGZ BAJIO'!$H$2:$H$4,"ENTRADA",'MGZ BAJIO'!$J$2:$J$4,$B81),0) -> 0 | G81: =IFERROR(SUMIFS('VICTOR BANAMEX'!$M$2:$M$65,'VICTOR BANAMEX'!$H$2:$H$65,"ENTRADA",'VICTOR BANAMEX'!$J$2:$J$65,$B81),0) -> 0 | H81: =IFERROR(SUMIFS('VICTOR BANORTE'!$M$2:$M$9,'VICTOR BANORTE'!$H$2:$H$9,"ENTRADA",'VICTOR BANORTE'!$J$2:$J$9,$B81),0) -> 0 | I81: =IFERROR(SUMIFS(RODRIGO!$M$2:$M$2,RODRIGO!$H$2:$H$2,"ENTRADA",RODRIGO!$J$2:$J$2,$B81),0) -> 0 | J81: =IFERROR(SUMIFS(MOY!$M$2:$M$12,MOY!$H$2:$H$12,"ENTRADA",MOY!$J$2:$J$12,$B81),0) -> 0 | K81: =IFERROR(SUMIFS('NORMA RUTH'!$M$2:$M$12,'NORMA RUTH'!$H$2:$H$12,"ENTRADA",'NORMA RUTH'!$J$2:$J$12,$B81),0) -> 0 | L81: =IFERROR(SUMIFS(VALERIA!$M$2:$M$10,VALERIA!$H$2:$H$10,"ENTRADA",VALERIA!$J$2:$J$10,$B81),0) -> 0 | M81: =IFERROR(SUMIFS('MANUEL BANAMEX'!$M$2:$M$25,'MANUEL BANAMEX'!$H$2:$H$25,"ENTRADA",'MANUEL BANAMEX'!$J$2:$J$25,$B81),0) -> 0 | N81: =IFERROR(SUMIFS(ROBERTO!$M$2:$M$2,ROBERTO!$H$2:$H$2,"ENTRADA",ROBERTO!$J$2:$J$2,$B81),0) -> 0 | O81: =IFERROR(SUMIFS(JUAN!$M$2:$M$11,JUAN!$H$2:$H$11,"ENTRADA",JUAN!$J$2:$J$11,$B81),0) -> 0 | P81: =IFERROR(SUMIFS('NORMA SANCHEZ'!$M$2:$M$14,'NORMA SANCHEZ'!$H$2:$H$14,"ENTRADA",'NORMA SANCHEZ'!$J$2:$J$14,$B81),0) -> 0 | Q81: =IFERROR(SUMIFS('JOSE CARLOS'!$M$2:$M$16,'JOSE CARLOS'!$H$2:$H$16,"ENTRADA",'JOSE CARLOS'!$J$2:$J$16,$B81),0) -> 0 | R81: =IFERROR(SUMIFS('LUIS ENRIQUE '!$M$2:$M$21,'LUIS ENRIQUE '!$H$2:$H$21,"ENTRADA",'LUIS ENRIQUE '!$J$2:$J$21,$B81),0) -> 0 | S81: =IFERROR(SUMIFS(CESARIA!$M$2:$M$15,CESARIA!$H$2:$H$15,"ENTRADA",CESARIA!$J$2:$J$15,$B81),0) -> 0 | T81: =IFERROR(SUMIFS(ALAN!$M$2:$M$14,ALAN!$H$2:$H$14,"ENTRADA",ALAN!$J$2:$J$14,$B81),0) -> 0 | U81: =IFERROR(SUMIFS(ELVIA!$M$2:$M$6,ELVIA!$H$2:$H$6,"ENTRADA",ELVIA!$J$2:$J$6,$B81),0) -> 0 | V81: =IFERROR(SUMIFS(CAJA!$M$2:$M$586,CAJA!$H$2:$H$586,"ENTRADA",CAJA!$J$2:$J$586,$B81),0) -> 62000 | W81: =IFERROR(SUMIFS('CAJA TIGRES'!$M$2:$M$139,'CAJA TIGRES'!$H$2:$H$139,"ENTRADA",'CAJA TIGRES'!$J$2:$J$139,$B81),0) -> 0 | X81: =IFERROR(SUMIFS(RESERVA!$M$2:$M$2,RESERVA!$H$2:$H$2,"ENTRADA",RESERVA!$J$2:$J$2,$B81),0) -> 0 | Y81: =SUM(C81:X81) -> 105000 | Z81: =Y81 -> 105000
B82: TOTAL ENTRADA PRESTAMO | C82: =SUM(C78:C81) -> 314585 | D82: =SUM(D78:D81) -> 43000 | E82: =SUM(E78:E81) -> 0 | F82: =SUM(F78:F81) -> 0 | G82: =SUM(G78:G81) -> 0 | H82: =SUM(H78:H81) -> 0 | I82: =SUM(I78:I81) -> 0 | J82: =SUM(J78:J81) -> 0 | ... Z82: =SUM(Z78:Z81) -> 510645
B84: SALIDAS
A85: 8 | B85: PRESTAMOS
A86: 8.1 | B86: BANCARIOS | C86: =IFERROR(SUMIFS('MGZ121'!$N$2:'MGZ121'!$N$175,'MGZ121'!$H$2:$H$175,"SALIDA",'MGZ121'!$J$2:$J$175,B86),0) -> 0 | D86: =IFERROR(SUMIFS('MGZ BBVA'!$N$2:$N$88,'MGZ BBVA'!$H$2:$H$88,"SALIDA",'MGZ BBVA'!$J$2:$J$88,$B86),0) -> 0 | E86: =IFERROR(SUMIFS('MGZ DOLARES'!$N$2:$N$2,'MGZ DOLARES'!$F$2:$F$2,"SALIDA",'MGZ DOLARES'!$J$2:$J$2,$B86),0) -> 0 | F86: =IFERROR(SUMIFS('MGZ BAJIO'!$N$2:$N$4,'MGZ BAJIO'!$H$4,"SALIDA",'MGZ BAJIO'!$J$4,$B86),0) -> 0 | G86: =IFERROR(SUMIFS('VICTOR BANAMEX'!$N$2:$N$65,'VICTOR BANAMEX'!$H$2:$H$65,"SALIDA",'VICTOR BANAMEX'!$J$2:$J$65,$B86),0) -> 0 | H86: =IFERROR(SUMIFS('VICTOR BANORTE'!$N$2:$N$9,'VICTOR BANORTE'!$H$2:$H$9,"SALIDA",'VICTOR BANORTE'!$J$2:$J$9,$B86),0) -> 0 | I86: =IFERROR(SUMIFS(RODRIGO!$N$2:$N$2,RODRIGO!$H$2:$H$2,"SALIDA",RODRIGO!$J$2:$J$2,$B86),0) -> 0 | J86: =IFERROR(SUMIFS(MOY!$N$2:$N$12,MOY!$H$2:$H$12,"SALIDA",MOY!$J$2:$J$12,$B86),0) -> 0 | K86: =IFERROR(SUMIFS('NORMA RUTH'!$N$2:$N$12,'NORMA RUTH'!$H$2:$H$12,"SALIDA",'NORMA RUTH'!$J$2:$J$12,$B86),0) -> 0 | L86: =IFERROR(SUMIFS(VALERIA!$N$2:$N$10,VALERIA!$H$2:$H$10,"SALIDA",VALERIA!$J$2:$J$10,$B86),0) -> 0 | M86: =IFERROR(SUMIFS('MANUEL BANAMEX'!$N$2:$N$25,'MANUEL BANAMEX'!$H$2:$H$25,"SALIDA",'MANUEL BANAMEX'!$J$2:$J$25,$B86),0) -> 0 | N86: =IFERROR(SUMIFS(ROBERTO!$N$2:$N$2,ROBERTO!$H$2:$H$2,"SALIDA",ROBERTO!$J$2:$J$2,$B86),0) -> 0 | O86: =IFERROR(SUMIFS(JUAN!$N$2:$N$11,JUAN!$H$2:$H$11,"SALIDA",JUAN!$J$2:$J$11,$B86),0) -> 0 | P86: =IFERROR(SUMIFS('NORMA SANCHEZ'!$N$2:$N$14,'NORMA SANCHEZ'!$H$2:$H$14,"SALIDA",'NORMA SANCHEZ'!$J$2:$J$14,$B86),0) -> 0 | Q86: =IFERROR(SUMIFS('JOSE CARLOS'!$N$2:$N$16,'JOSE CARLOS'!$H$2:$H$16,"SALIDA",'JOSE CARLOS'!$J$2:$J$16,$B86),0) -> 0 | R86: =IFERROR(SUMIFS('LUIS ENRIQUE '!$N$2:$N$21,'LUIS ENRIQUE '!$H$2:$H$21,"SALIDA",'LUIS ENRIQUE '!$J$2:$J$21,$B86),0) -> 0 | S86: =IFERROR(SUMIFS(CESARIA!$N$2:$N$15,CESARIA!$H$2:$H$15,"SALIDA",CESARIA!$J$2:$J$15,$B86),0) -> 0 | T86: =IFERROR(SUMIFS(ALAN!$N$2:$N$14,ALAN!$H$2:$H$14,"SALIDA",ALAN!$J$2:$J$14,$B86),0) -> 0 | U86: =IFERROR(SUMIFS(ELVIA!$N$2:$N$6,ELVIA!$H$2:$H$6,"SALIDA",ELVIA!$J$2:$J$6,$B86),0) -> 0 | V86: =IFERROR(SUMIFS(CAJA!$N$2:$N$586,CAJA!$H$2:$H$586,"SALIDA",CAJA!$J$2:$J$586,$B86),0) -> 0 | W86: =IFERROR(SUMIFS('CAJA TIGRES'!$N$2:$N$139,'CAJA TIGRES'!$H$2:$H$139,"SALIDA",'CAJA TIGRES'!$J$2:$J$139,$B86),0) -> 0 | X86: =IFERROR(SUMIFS(RESERVA!$N$2:$N$2,RESERVA!$H$2:$H$2,"SALIDA",RESERVA!$J$2:$J$2,$B86),0) -> 0 | Y86: =SUM(C86:X86) -> 0 | Z86: =Y86 -> 0
A87: 8.2 | B87: EXTERNOS | C87: =IFERROR(SUMIFS('MGZ121'!$N$2:'MGZ121'!$N$175,'MGZ121'!$H$2:$H$175,"SALIDA",'MGZ121'!$J$2:$J$175,B87),0) -> 0 | D87: =IFERROR(SUMIFS('MGZ BBVA'!$N$2:$N$88,'MGZ BBVA'!$H$2:$H$88,"SALIDA",'MGZ BBVA'!$J$2:$J$88,$B87),0) -> 0 | E87: =IFERROR(SUMIFS('MGZ DOLARES'!$N$2:$N$2,'MGZ DOLARES'!$F$2:$F$2,"SALIDA",'MGZ DOLARES'!$J$2:$J$2,$B87),0) -> 0 | F87: =IFERROR(SUMIFS('MGZ BAJIO'!$N$2:$N$4,'MGZ BAJIO'!$H$4,"SALIDA",'MGZ BAJIO'!$J$4,$B87),0) -> 0 | G87: =IFERROR(SUMIFS('VICTOR BANAMEX'!$N$2:$N$65,'VICTOR BANAMEX'!$H$2:$H$65,"SALIDA",'VICTOR BANAMEX'!$J$2:$J$65,$B87),0) -> 0 | H87: =IFERROR(SUMIFS('VICTOR BANORTE'!$N$2:$N$9,'VICTOR BANORTE'!$H$2:$H$9,"SALIDA",'VICTOR BANORTE'!$J$2:$J$9,$B87),0) -> 0 | I87: =IFERROR(SUMIFS(RODRIGO!$N$2:$N$2,RODRIGO!$H$2:$H$2,"SALIDA",RODRIGO!$J$2:$J$2,$B87),0) -> 0 | J87: =IFERROR(SUMIFS(MOY!$N$2:$N$12,MOY!$H$2:$H$12,"SALIDA",MOY!$J$2:$J$12,$B87),0) -> 0 | K87: =IFERROR(SUMIFS('NORMA RUTH'!$N$2:$N$12,'NORMA RUTH'!$H$2:$H$12,"SALIDA",'NORMA RUTH'!$J$2:$J$12,$B87),0) -> 0 | L87: =IFERROR(SUMIFS(VALERIA!$N$2:$N$10,VALERIA!$H$2:$H$10,"SALIDA",VALERIA!$J$2:$J$10,$B87),0) -> 0 | M87: =IFERROR(SUMIFS('MANUEL BANAMEX'!$N$2:$N$25,'MANUEL BANAMEX'!$H$2:$H$25,"SALIDA",'MANUEL BANAMEX'!$J$2:$J$25,$B87),0) -> 0 | N87: =IFERROR(SUMIFS(ROBERTO!$N$2:$N$2,ROBERTO!$H$2:$H$2,"SALIDA",ROBERTO!$J$2:$J$2,$B87),0) -> 0 | O87: =IFERROR(SUMIFS(JUAN!$N$2:$N$11,JUAN!$H$2:$H$11,"SALIDA",JUAN!$J$2:$J$11,$B87),0) -> 0 | P87: =IFERROR(SUMIFS('NORMA SANCHEZ'!$N$2:$N$14,'NORMA SANCHEZ'!$H$2:$H$14,"SALIDA",'NORMA SANCHEZ'!$J$2:$J$14,$B87),0) -> 0 | Q87: =IFERROR(SUMIFS('JOSE CARLOS'!$N$2:$N$16,'JOSE CARLOS'!$H$2:$H$16,"SALIDA",'JOSE CARLOS'!$J$2:$J$16,$B87),0) -> 0 | R87: =IFERROR(SUMIFS('LUIS ENRIQUE '!$N$2:$N$21,'LUIS ENRIQUE '!$H$2:$H$21,"SALIDA",'LUIS ENRIQUE '!$J$2:$J$21,$B87),0) -> 0 | S87: =IFERROR(SUMIFS(CESARIA!$N$2:$N$15,CESARIA!$H$2:$H$15,"SALIDA",CESARIA!$J$2:$J$15,$B87),0) -> 0 | T87: =IFERROR(SUMIFS(ALAN!$N$2:$N$14,ALAN!$H$2:$H$14,"SALIDA",ALAN!$J$2:$J$14,$B87),0) -> 0 | U87: =IFERROR(SUMIFS(ELVIA!$N$2:$N$6,ELVIA!$H$2:$H$6,"SALIDA",ELVIA!$J$2:$J$6,$B87),0) -> 0 | V87: =IFERROR(SUMIFS(CAJA!$N$2:$N$586,CAJA!$H$2:$H$586,"SALIDA",CAJA!$J$2:$J$586,$B87),0) -> 0 | W87: =IFERROR(SUMIFS('CAJA TIGRES'!$N$2:$N$139,'CAJA TIGRES'!$H$2:$H$139,"SALIDA",'CAJA TIGRES'!$J$2:$J$139,$B87),0) -> 0 | X87: =IFERROR(SUMIFS(RESERVA!$N$2:$N$2,RESERVA!$H$2:$H$2,"SALIDA",RESERVA!$J$2:$J$2,$B87),0) -> 0 | Y87: =SUM(C87:X87) -> 0 | Z87: =Y87 -> 0
B88: TRABAJADORES | C88: =IFERROR(SUMIFS('MGZ121'!$N$2:'MGZ121'!$N$175,'MGZ121'!$H$2:$H$175,"SALIDA",'MGZ121'!$J$2:$J$175,B88),0) -> 0 | D88: =IFERROR(SUMIFS('MGZ BBVA'!$N$2:$N$88,'MGZ BBVA'!$H$2:$H$88,"SALIDA",'MGZ BBVA'!$J$2:$J$88,$B88),0) -> 0 | E88: =IFERROR(SUMIFS('MGZ DOLARES'!$N$2:$N$2,'MGZ DOLARES'!$F$2:$F$2,"SALIDA",'MGZ DOLARES'!$J$2:$J$2,$B88),0) -> 0 | F88: =IFERROR(SUMIFS('MGZ BAJIO'!$N$2:$N$4,'MGZ BAJIO'!$H$4,"SALIDA",'MGZ BAJIO'!$J$4,$B88),0) -> 0 | G88: =IFERROR(SUMIFS('VICTOR BANAMEX'!$N$2:$N$65,'VICTOR BANAMEX'!$H$2:$H$65,"SALIDA",'VICTOR BANAMEX'!$J$2:$J$65,$B88),0) -> 0 | H88: =IFERROR(SUMIFS('VICTOR BANORTE'!$N$2:$N$9,'VICTOR BANORTE'!$H$2:$H$9,"SALIDA",'VICTOR BANORTE'!$J$2:$J$9,$B88),0) -> 0 | I88: =IFERROR(SUMIFS(RODRIGO!$N$2:$N$2,RODRIGO!$H$2:$H$2,"SALIDA",RODRIGO!$J$2:$J$2,$B88),0) -> 0 | J88: =IFERROR(SUMIFS(MOY!$N$2:$N$12,MOY!$H$2:$H$12,"SALIDA",MOY!$J$2:$J$12,$B88),0) -> 0 | K88: =IFERROR(SUMIFS('NORMA RUTH'!$N$2:$N$12,'NORMA RUTH'!$H$2:$H$12,"SALIDA",'NORMA RUTH'!$J$2:$J$12,$B88),0) -> 0 | L88: =IFERROR(SUMIFS(VALERIA!$N$2:$N$10,VALERIA!$H$2:$H$10,"SALIDA",VALERIA!$J$2:$J$10,$B88),0) -> 0 | M88: =IFERROR(SUMIFS('MANUEL BANAMEX'!$N$2:$N$25,'MANUEL BANAMEX'!$H$2:$H$25,"SALIDA",'MANUEL BANAMEX'!$J$2:$J$25,$B88),0) -> 0 | N88: =IFERROR(SUMIFS(ROBERTO!$N$2:$N$2,ROBERTO!$H$2:$H$2,"SALIDA",ROBERTO!$J$2:$J$2,$B88),0) -> 0 | O88: =IFERROR(SUMIFS(JUAN!$N$2:$N$11,JUAN!$H$2:$H$11,"SALIDA",JUAN!$J$2:$J$11,$B88),0) -> 0 | P88: =IFERROR(SUMIFS('NORMA SANCHEZ'!$N$2:$N$14,'NORMA SANCHEZ'!$H$2:$H$14,"SALIDA",'NORMA SANCHEZ'!$J$2:$J$14,$B88),0) -> 0 | Q88: =IFERROR(SUMIFS('JOSE CARLOS'!$N$2:$N$16,'JOSE CARLOS'!$H$2:$H$16,"SALIDA",'JOSE CARLOS'!$J$2:$J$16,$B88),0) -> 0 | R88: =IFERROR(SUMIFS('LUIS ENRIQUE '!$N$2:$N$21,'LUIS ENRIQUE '!$H$2:$H$21,"SALIDA",'LUIS ENRIQUE '!$J$2:$J$21,$B88),0) -> 0 | S88: =IFERROR(SUMIFS(CESARIA!$N$2:$N$15,CESARIA!$H$2:$H$15,"SALIDA",CESARIA!$J$2:$J$15,$B88),0) -> 0 | T88: =IFERROR(SUMIFS(ALAN!$N$2:$N$14,ALAN!$H$2:$H$14,"SALIDA",ALAN!$J$2:$J$14,$B88),0) -> 0 | U88: =IFERROR(SUMIFS(ELVIA!$N$2:$N$6,ELVIA!$H$2:$H$6,"SALIDA",ELVIA!$J$2:$J$6,$B88),0) -> 0 | V88: =IFERROR(SUMIFS(CAJA!$N$2:$N$586,CAJA!$H$2:$H$586,"SALIDA",CAJA!$J$2:$J$586,$B88),0) -> 40000 | W88: =IFERROR(SUMIFS('CAJA TIGRES'!$N$2:$N$139,'CAJA TIGRES'!$H$2:$H$139,"SALIDA",'CAJA TIGRES'!$J$2:$J$139,$B88),0) -> 0 | X88: =IFERROR(SUMIFS(RESERVA!$N$2:$N$2,RESERVA!$H$2:$H$2,"SALIDA",RESERVA!$J$2:$J$2,$B88),0) -> 0 | Y88: =SUM(C88:X88) -> 40000 | Z88: =Y88 -> 40000
B89: SOCIOS | C89: =IFERROR(SUMIFS('MGZ121'!$N$2:'MGZ121'!$N$175,'MGZ121'!$H$2:$H$175,"SALIDA",'MGZ121'!$J$2:$J$175,B89),0) -> 0 | D89: =IFERROR(SUMIFS('MGZ BBVA'!$N$2:$N$88,'MGZ BBVA'!$H$2:$H$88,"SALIDA",'MGZ BBVA'!$J$2:$J$88,$B89),0) -> 0 | E89: =IFERROR(SUMIFS('MGZ DOLARES'!$N$2:$N$2,'MGZ DOLARES'!$F$2:$F$2,"SALIDA",'MGZ DOLARES'!$J$2:$J$2,$B89),0) -> 0 | F89: =IFERROR(SUMIFS('MGZ BAJIO'!$N$2:$N$4,'MGZ BAJIO'!$H$4,"SALIDA",'MGZ BAJIO'!$J$4,$B89),0) -> 0 | G89: =IFERROR(SUMIFS('VICTOR BANAMEX'!$N$2:$N$65,'VICTOR BANAMEX'!$H$2:$H$65,"SALIDA",'VICTOR BANAMEX'!$J$2:$J$65,$B89),0) -> 0 | H89: =IFERROR(SUMIFS('VICTOR BANORTE'!$N$2:$N$9,'VICTOR BANORTE'!$H$2:$H$9,"SALIDA",'VICTOR BANORTE'!$J$2:$J$9,$B89),0) -> 0 | I89: =IFERROR(SUMIFS(RODRIGO!$N$2:$N$2,RODRIGO!$H$2:$H$2,"SALIDA",RODRIGO!$J$2:$J$2,$B89),0) -> 0 | J89: =IFERROR(SUMIFS(MOY!$N$2:$N$12,MOY!$H$2:$H$12,"SALIDA",MOY!$J$2:$J$12,$B89),0) -> 0 | K89: =IFERROR(SUMIFS('NORMA RUTH'!$N$2:$N$12,'NORMA RUTH'!$H$2:$H$12,"SALIDA",'NORMA RUTH'!$J$2:$J$12,$B89),0) -> 0 | L89: =IFERROR(SUMIFS(VALERIA!$N$2:$N$10,VALERIA!$H$2:$H$10,"SALIDA",VALERIA!$J$2:$J$10,$B89),0) -> 0 | M89: =IFERROR(SUMIFS('MANUEL BANAMEX'!$N$2:$N$25,'MANUEL BANAMEX'!$H$2:$H$25,"SALIDA",'MANUEL BANAMEX'!$J$2:$J$25,$B89),0) -> 0 | N89: =IFERROR(SUMIFS(ROBERTO!$N$2:$N$2,ROBERTO!$H$2:$H$2,"SALIDA",ROBERTO!$J$2:$J$2,$B89),0) -> 0 | O89: =IFERROR(SUMIFS(JUAN!$N$2:$N$11,JUAN!$H$2:$H$11,"SALIDA",JUAN!$J$2:$J$11,$B89),0) -> 0 | P89: =IFERROR(SUMIFS('NORMA SANCHEZ'!$N$2:$N$14,'NORMA SANCHEZ'!$H$2:$H$14,"SALIDA",'NORMA SANCHEZ'!$J$2:$J$14,$B89),0) -> 0 | Q89: =IFERROR(SUMIFS('JOSE CARLOS'!$N$2:$N$16,'JOSE CARLOS'!$H$2:$H$16,"SALIDA",'JOSE CARLOS'!$J$2:$J$16,$B89),0) -> 0 | R89: =IFERROR(SUMIFS('LUIS ENRIQUE '!$N$2:$N$21,'LUIS ENRIQUE '!$H$2:$H$21,"SALIDA",'LUIS ENRIQUE '!$J$2:$J$21,$B89),0) -> 0 | S89: =IFERROR(SUMIFS(CESARIA!$N$2:$N$15,CESARIA!$H$2:$H$15,"SALIDA",CESARIA!$J$2:$J$15,$B89),0) -> 0 | T89: =IFERROR(SUMIFS(ALAN!$N$2:$N$14,ALAN!$H$2:$H$14,"SALIDA",ALAN!$J$2:$J$14,$B89),0) -> 0 | U89: =IFERROR(SUMIFS(ELVIA!$N$2:$N$6,ELVIA!$H$2:$H$6,"SALIDA",ELVIA!$J$2:$J$6,$B89),0) -> 0 | V89: =IFERROR(SUMIFS(CAJA!$N$2:$N$586,CAJA!$H$2:$H$586,"SALIDA",CAJA!$J$2:$J$586,$B89),0) -> 92000 | W89: =IFERROR(SUMIFS('CAJA TIGRES'!$N$2:$N$139,'CAJA TIGRES'!$H$2:$H$139,"SALIDA",'CAJA TIGRES'!$J$2:$J$139,$B89),0) -> 0 | X89: =IFERROR(SUMIFS(RESERVA!$N$2:$N$2,RESERVA!$H$2:$H$2,"SALIDA",RESERVA!$J$2:$J$2,$B89),0) -> 0 | Y89: =SUM(C89:X89) -> 92000 | Z89: =Y89 -> 92000
B90: TOTAL SALIDA DE PRESTAMO | C90: =SUM(C86:C89) -> 0 | D90: =SUM(D86:D89) -> 0 | E90: =SUM(E86:E89) -> 0 | F90: =SUM(F86:F89) -> 0 | G90: =SUM(G86:G89) -> 0 | H90: =SUM(H86:H89) -> 0 | I90: =SUM(I86:I89) -> 0 | J90: =SUM(J86:J89) -> 0 | ... Z90: =SUM(Z86:Z89) -> 132000
B91: Flujo en Prestamos | C91: =C82-C90 -> 314585 | D91: =D82-D90 -> 43000 | E91: =E82-E90 -> 0 | F91: =F82-F90 -> 0 | G91: =G82-G90 -> 0 | H91: =H82-H90 -> 0 | I91: =I82-I90 -> 0 | J91: =J82-J90 -> 0 | ... Z91: =Z82-Z90 -> 378645
B93: ENTRADAS
A94: 12 | B94: TRASPASO
B95: TRASPASO MGZ121 | C95: =IFERROR(SUMIFS('MGZ121'!$M$2:'MGZ121'!$M$175,'MGZ121'!$H$2:$H$175,"ENTRADA",'MGZ121'!$J$2:$J$175,$B95),0) -> 0 | D95: =IFERROR(SUMIFS('MGZ BBVA'!$M$2:$M$88,'MGZ BBVA'!$H$2:$H$88,"ENTRADA",'MGZ BBVA'!$J$2:$J$88,$B95),0) -> 1031150 | E95: =IFERROR(SUMIFS('MGZ DOLARES'!$M$2:$M$2,'MGZ DOLARES'!$F$2:$F$2,"ENTRADA",'MGZ DOLARES'!$J$2:$J$2,$B95),0) -> 0 | F95: =IFERROR(SUMIFS('MGZ BAJIO'!$M$2:$M$4,'MGZ BAJIO'!$H$2:$H$4,"ENTRADA",'MGZ BAJIO'!$J$2:$J$4,$B95),0) -> 0 | G95: =IFERROR(SUMIFS('VICTOR BANAMEX'!$M$2:$M$65,'VICTOR BANAMEX'!$H$2:$H$65,"ENTRADA",'VICTOR BANAMEX'!$J$2:$J$65,$B95),0) -> 272870.39 | H95: =IFERROR(SUMIFS('VICTOR BANORTE'!$M$2:$M$9,'VICTOR BANORTE'!$H$2:$H$9,"ENTRADA",'VICTOR BANORTE'!$J$2:$J$9,$B95),0) -> 0 | I95: =IFERROR(SUMIFS(RODRIGO!$M$2:$M$2,RODRIGO!$H$2:$H$2,"ENTRADA",RODRIGO!$J$2:$J$2,$B95),0) -> 0 | J95: =IFERROR(SUMIFS(MOY!$M$2:$M$12,MOY!$H$2:$H$12,"ENTRADA",MOY!$J$2:$J$12,$B95),0) -> 237000 | K95: =IFERROR(SUMIFS('NORMA RUTH'!$M$2:$M$12,'NORMA RUTH'!$H$2:$H$12,"ENTRADA",'NORMA RUTH'!$J$2:$J$12,$B95),0) -> 21261.46 | L95: =IFERROR(SUMIFS(VALERIA!$M$2:$M$10,VALERIA!$H$2:$H$10,"ENTRADA",VALERIA!$J$2:$J$10,$B95),0) -> 40000 | M95: =IFERROR(SUMIFS('MANUEL BANAMEX'!$M$2:$M$25,'MANUEL BANAMEX'!$H$2:$H$25,"ENTRADA",'MANUEL BANAMEX'!$J$2:$J$25,$B95),0) -> 80895 | N95: =IFERROR(SUMIFS(ROBERTO!$M$2:$M$2,ROBERTO!$H$2:$H$2,"ENTRADA",ROBERTO!$J$2:$J$2,$B95),0) -> 0 | O95: =IFERROR(SUMIFS(JUAN!$M$2:$M$11,JUAN!$H$2:$H$11,"ENTRADA",JUAN!$J$2:$J$11,$B95),0) -> 366165 | P95: =IFERROR(SUMIFS('NORMA SANCHEZ'!$M$2:$M$14,'NORMA SANCHEZ'!$H$2:$H$14,"ENTRADA",'NORMA SANCHEZ'!$J$2:$J$14,$B95),0) -> 705766.25 | Q95: =IFERROR(SUMIFS('JOSE CARLOS'!$M$2:$M$16,'JOSE CARLOS'!$H$2:$H$16,"ENTRADA",'JOSE CARLOS'!$J$2:$J$16,$B95),0) -> 570775 | R95: =IFERROR(SUMIFS('LUIS ENRIQUE '!$M$2:$M$21,'LUIS ENRIQUE '!$H$2:$H$21,"ENTRADA",'LUIS ENRIQUE '!$J$2:$J$21,$B95),0) -> 0 | S95: =IFERROR(SUMIFS(CESARIA!$M$2:$M$15,CESARIA!$H$2:$H$15,"ENTRADA",CESARIA!$J$2:$J$15,$B95),0) -> 610571.25 | T95: =IFERROR(SUMIFS(ALAN!$M$2:$M$14,ALAN!$H$2:$H$14,"ENTRADA",ALAN!$J$2:$J$14,$B95),0) -> 350957.5 | U95: =IFERROR(SUMIFS(ELVIA!$M$2:$M$6,ELVIA!$H$2:$H$6,"ENTRADA",ELVIA!$J$2:$J$6,$B95),0) -> 10862.5 | V95: =IFERROR(SUMIFS(CAJA!$M$2:$M$586,CAJA!$H$2:$H$586,"ENTRADA",CAJA!$J$2:$J$586,$B95),0) -> 281246.84 | W95: =IFERROR(SUMIFS('CAJA TIGRES'!$M$2:$M$139,'CAJA TIGRES'!$H$2:$H$139,"ENTRADA",'CAJA TIGRES'!$J$2:$J$139,$B95),0) -> 0 | X95: =IFERROR(SUMIFS(RESERVA!$M$2:$M$2,RESERVA!$H$2:$H$2,"ENTRADA",RESERVA!$J$2:$J$2,$B95),0) -> 0 | Y95: =SUM(C95:X95) -> 4579521.2 | Z95: =Y95 -> 4579521.2
B96: TRASPASO MGZBBVA | C96: =IFERROR(SUMIFS('MGZ121'!$M$2:'MGZ121'!$M$175,'MGZ121'!$H$2:$H$175,"ENTRADA",'MGZ121'!$J$2:$J$175,$B96),0) -> 150000 | D96: =IFERROR(SUMIFS('MGZ BBVA'!$M$2:$M$88,'MGZ BBVA'!$H$2:$H$88,"ENTRADA",'MGZ BBVA'!$J$2:$J$88,$B96),0) -> 0 | E96: =IFERROR(SUMIFS('MGZ DOLARES'!$M$2:$M$2,'MGZ DOLARES'!$F$2:$F$2,"ENTRADA",'MGZ DOLARES'!$J$2:$J$2,$B96),0) -> 0 | F96: =IFERROR(SUMIFS('MGZ BAJIO'!$M$2:$M$4,'MGZ BAJIO'!$H$2:$H$4,"ENTRADA",'MGZ BAJIO'!$J$2:$J$4,$B96),0) -> 0 | G96: =IFERROR(SUMIFS('VICTOR BANAMEX'!$M$2:$M$65,'VICTOR BANAMEX'!$H$2:$H$65,"ENTRADA",'VICTOR BANAMEX'!$J$2:$J$65,$B96),0) -> 64900 | H96: =IFERROR(SUMIFS('VICTOR BANORTE'!$M$2:$M$9,'VICTOR BANORTE'!$H$2:$H$9,"ENTRADA",'VICTOR BANORTE'!$J$2:$J$9,$B96),0) -> 0 | I96: =IFERROR(SUMIFS(RODRIGO!$M$2:$M$2,RODRIGO!$H$2:$H$2,"ENTRADA",RODRIGO!$J$2:$J$2,$B96),0) -> 0 | J96: =IFERROR(SUMIFS(MOY!$M$2:$M$12,MOY!$H$2:$H$12,"ENTRADA",MOY!$J$2:$J$12,$B96),0) -> 0 | K96: =IFERROR(SUMIFS('NORMA RUTH'!$M$2:$M$12,'NORMA RUTH'!$H$2:$H$12,"ENTRADA",'NORMA RUTH'!$J$2:$J$12,$B96),0) -> 0 | L96: =IFERROR(SUMIFS(VALERIA!$M$2:$M$10,VALERIA!$H$2:$H$10,"ENTRADA",VALERIA!$J$2:$J$10,$B96),0) -> 0 | M96: =IFERROR(SUMIFS('MANUEL BANAMEX'!$M$2:$M$25,'MANUEL BANAMEX'!$H$2:$H$25,"ENTRADA",'MANUEL BANAMEX'!$J$2:$J$25,$B96),0) -> 0 | N96: =IFERROR(SUMIFS(ROBERTO!$M$2:$M$2,ROBERTO!$H$2:$H$2,"ENTRADA",ROBERTO!$J$2:$J$2,$B96),0) -> 0 | O96: =IFERROR(SUMIFS(JUAN!$M$2:$M$11,JUAN!$H$2:$H$11,"ENTRADA",JUAN!$J$2:$J$11,$B96),0) -> 0 | P96: =IFERROR(SUMIFS('NORMA SANCHEZ'!$M$2:$M$14,'NORMA SANCHEZ'!$H$2:$H$14,"ENTRADA",'NORMA SANCHEZ'!$J$2:$J$14,$B96),0) -> 0 | Q96: =IFERROR(SUMIFS('JOSE CARLOS'!$M$2:$M$16,'JOSE CARLOS'!$H$2:$H$16,"ENTRADA",'JOSE CARLOS'!$J$2:$J$16,$B96),0) -> 2865 | R96: =IFERROR(SUMIFS('LUIS ENRIQUE '!$M$2:$M$21,'LUIS ENRIQUE '!$H$2:$H$21,"ENTRADA",'LUIS ENRIQUE '!$J$2:$J$21,$B96),0) -> 1319833.2 | S96: =IFERROR(SUMIFS(CESARIA!$M$2:$M$15,CESARIA!$H$2:$H$15,"ENTRADA",CESARIA!$J$2:$J$15,$B96),0) -> 0 | T96: =IFERROR(SUMIFS(ALAN!$M$2:$M$14,ALAN!$H$2:$H$14,"ENTRADA",ALAN!$J$2:$J$14,$B96),0) -> 365078.75 | U96: =IFERROR(SUMIFS(ELVIA!$M$2:$M$6,ELVIA!$H$2:$H$6,"ENTRADA",ELVIA!$J$2:$J$6,$B96),0) -> 0 | V96: =IFERROR(SUMIFS(CAJA!$M$2:$M$586,CAJA!$H$2:$H$586,"ENTRADA",CAJA!$J$2:$J$586,$B96),0) -> 35000 | W96: =IFERROR(SUMIFS('CAJA TIGRES'!$M$2:$M$139,'CAJA TIGRES'!$H$2:$H$139,"ENTRADA",'CAJA TIGRES'!$J$2:$J$139,$B96),0) -> 0 | X96: =IFERROR(SUMIFS(RESERVA!$M$2:$M$2,RESERVA!$H$2:$H$2,"ENTRADA",RESERVA!$J$2:$J$2,$B96),0) -> 0 | Y96: =SUM(C96:X96) -> 1937677 | Z96: =Y96 -> 1937677
B97: TRASPASO MGZ DOLARES | C97: =IFERROR(SUMIFS('MGZ121'!$M$2:'MGZ121'!$M$175,'MGZ121'!$H$2:$H$175,"ENTRADA",'MGZ121'!$J$2:$J$175,$B97),0) -> 0 | D97: =IFERROR(SUMIFS('MGZ BBVA'!$M$2:$M$88,'MGZ BBVA'!$H$2:$H$88,"ENTRADA",'MGZ BBVA'!$J$2:$J$88,$B97),0) -> 0 | E97: =IFERROR(SUMIFS('MGZ DOLARES'!$M$2:$M$2,'MGZ DOLARES'!$F$2:$F$2,"ENTRADA",'MGZ DOLARES'!$J$2:$J$2,$B97),0) -> 0 | F97: =IFERROR(SUMIFS('MGZ BAJIO'!$M$2:$M$4,'MGZ BAJIO'!$H$2:$H$4,"ENTRADA",'MGZ BAJIO'!$J$2:$J$4,$B97),0) -> 0 | G97: =IFERROR(SUMIFS('VICTOR BANAMEX'!$M$2:$M$65,'VICTOR BANAMEX'!$H$2:$H$65,"ENTRADA",'VICTOR BANAMEX'!$J$2:$J$65,$B97),0) -> 0 | H97: =IFERROR(SUMIFS('VICTOR BANORTE'!$M$2:$M$9,'VICTOR BANORTE'!$H$2:$H$9,"ENTRADA",'VICTOR BANORTE'!$J$2:$J$9,$B97),0) -> 0 | I97: =IFERROR(SUMIFS(RODRIGO!$M$2:$M$2,RODRIGO!$H$2:$H$2,"ENTRADA",RODRIGO!$J$2:$J$2,$B97),0) -> 0 | J97: =IFERROR(SUMIFS(MOY!$M$2:$M$12,MOY!$H$2:$H$12,"ENTRADA",MOY!$J$2:$J$12,$B97),0) -> 0 | K97: =IFERROR(SUMIFS('NORMA RUTH'!$M$2:$M$12,'NORMA RUTH'!$H$2:$H$12,"ENTRADA",'NORMA RUTH'!$J$2:$J$12,$B97),0) -> 0 | L97: =IFERROR(SUMIFS(VALERIA!$M$2:$M$10,VALERIA!$H$2:$H$10,"ENTRADA",VALERIA!$J$2:$J$10,$B97),0) -> 0 | M97: =IFERROR(SUMIFS('MANUEL BANAMEX'!$M$2:$M$25,'MANUEL BANAMEX'!$H$2:$H$25,"ENTRADA",'MANUEL BANAMEX'!$J$2:$J$25,$B97),0) -> 0 | N97: =IFERROR(SUMIFS(ROBERTO!$M$2:$M$2,ROBERTO!$H$2:$H$2,"ENTRADA",ROBERTO!$J$2:$J$2,$B97),0) -> 0 | O97: =IFERROR(SUMIFS(JUAN!$M$2:$M$11,JUAN!$H$2:$H$11,"ENTRADA",JUAN!$J$2:$J$11,$B97),0) -> 0 | P97: =IFERROR(SUMIFS('NORMA SANCHEZ'!$M$2:$M$14,'NORMA SANCHEZ'!$H$2:$H$14,"ENTRADA",'NORMA SANCHEZ'!$J$2:$J$14,$B97),0) -> 0 | Q97: =IFERROR(SUMIFS('JOSE CARLOS'!$M$2:$M$16,'JOSE CARLOS'!$H$2:$H$16,"ENTRADA",'JOSE CARLOS'!$J$2:$J$16,$B97),0) -> 0 | R97: =IFERROR(SUMIFS('LUIS ENRIQUE '!$M$2:$M$21,'LUIS ENRIQUE '!$H$2:$H$21,"ENTRADA",'LUIS ENRIQUE '!$J$2:$J$21,$B97),0) -> 0 | S97: =IFERROR(SUMIFS(CESARIA!$M$2:$M$15,CESARIA!$H$2:$H$15,"ENTRADA",CESARIA!$J$2:$J$15,$B97),0) -> 0 | T97: =IFERROR(SUMIFS(ALAN!$M$2:$M$14,ALAN!$H$2:$H$14,"ENTRADA",ALAN!$J$2:$J$14,$B97),0) -> 0 | U97: =IFERROR(SUMIFS(ELVIA!$M$2:$M$6,ELVIA!$H$2:$H$6,"ENTRADA",ELVIA!$J$2:$J$6,$B97),0) -> 0 | V97: =IFERROR(SUMIFS(CAJA!$M$2:$M$586,CAJA!$H$2:$H$586,"ENTRADA",CAJA!$J$2:$J$586,$B97),0) -> 0 | W97: =IFERROR(SUMIFS('CAJA TIGRES'!$M$2:$M$139,'CAJA TIGRES'!$H$2:$H$139,"ENTRADA",'CAJA TIGRES'!$J$2:$J$139,$B97),0) -> 0 | X97: =IFERROR(SUMIFS(RESERVA!$M$2:$M$2,RESERVA!$H$2:$H$2,"ENTRADA",RESERVA!$J$2:$J$2,$B97),0) -> 0 | Y97: =SUM(C97:X97) -> 0 | Z97: =Y97 -> 0
B98: TRASPASO MGZ BAJIO | C98: =IFERROR(SUMIFS('MGZ121'!$M$2:'MGZ121'!$M$175,'MGZ121'!$H$2:$H$175,"ENTRADA",'MGZ121'!$J$2:$J$175,$B98),0) -> 0 | D98: =IFERROR(SUMIFS('MGZ BBVA'!$M$2:$M$88,'MGZ BBVA'!$H$2:$H$88,"ENTRADA",'MGZ BBVA'!$J$2:$J$88,$B98),0) -> 0 | E98: =IFERROR(SUMIFS('MGZ DOLARES'!$M$2:$M$2,'MGZ DOLARES'!$F$2:$F$2,"ENTRADA",'MGZ DOLARES'!$J$2:$J$2,$B98),0) -> 0 | F98: =IFERROR(SUMIFS('MGZ BAJIO'!$M$2:$M$4,'MGZ BAJIO'!$H$2:$H$4,"ENTRADA",'MGZ BAJIO'!$J$2:$J$4,$B98),0) -> 0 | G98: =IFERROR(SUMIFS('VICTOR BANAMEX'!$M$2:$M$65,'VICTOR BANAMEX'!$H$2:$H$65,"ENTRADA",'VICTOR BANAMEX'!$J$2:$J$65,$B98),0) -> 0 | H98: =IFERROR(SUMIFS('VICTOR BANORTE'!$M$2:$M$9,'VICTOR BANORTE'!$H$2:$H$9,"ENTRADA",'VICTOR BANORTE'!$J$2:$J$9,$B98),0) -> 0 | I98: =IFERROR(SUMIFS(RODRIGO!$M$2:$M$2,RODRIGO!$H$2:$H$2,"ENTRADA",RODRIGO!$J$2:$J$2,$B98),0) -> 0 | J98: =IFERROR(SUMIFS(MOY!$M$2:$M$12,MOY!$H$2:$H$12,"ENTRADA",MOY!$J$2:$J$12,$B98),0) -> 0 | K98: =IFERROR(SUMIFS('NORMA RUTH'!$M$2:$M$12,'NORMA RUTH'!$H$2:$H$12,"ENTRADA",'NORMA RUTH'!$J$2:$J$12,$B98),0) -> 0 | L98: =IFERROR(SUMIFS(VALERIA!$M$2:$M$10,VALERIA!$H$2:$H$10,"ENTRADA",VALERIA!$J$2:$J$10,$B98),0) -> 0 | M98: =IFERROR(SUMIFS('MANUEL BANAMEX'!$M$2:$M$25,'MANUEL BANAMEX'!$H$2:$H$25,"ENTRADA",'MANUEL BANAMEX'!$J$2:$J$25,$B98),0) -> 0 | N98: =IFERROR(SUMIFS(ROBERTO!$M$2:$M$2,ROBERTO!$H$2:$H$2,"ENTRADA",ROBERTO!$J$2:$J$2,$B98),0) -> 0 | O98: =IFERROR(SUMIFS(JUAN!$M$2:$M$11,JUAN!$H$2:$H$11,"ENTRADA",JUAN!$J$2:$J$11,$B98),0) -> 0 | P98: =IFERROR(SUMIFS('NORMA SANCHEZ'!$M$2:$M$14,'NORMA SANCHEZ'!$H$2:$H$14,"ENTRADA",'NORMA SANCHEZ'!$J$2:$J$14,$B98),0) -> 0 | Q98: =IFERROR(SUMIFS('JOSE CARLOS'!$M$2:$M$16,'JOSE CARLOS'!$H$2:$H$16,"ENTRADA",'JOSE CARLOS'!$J$2:$J$16,$B98),0) -> 0 | R98: =IFERROR(SUMIFS('LUIS ENRIQUE '!$M$2:$M$21,'LUIS ENRIQUE '!$H$2:$H$21,"ENTRADA",'LUIS ENRIQUE '!$J$2:$J$21,$B98),0) -> 0 | S98: =IFERROR(SUMIFS(CESARIA!$M$2:$M$15,CESARIA!$H$2:$H$15,"ENTRADA",CESARIA!$J$2:$J$15,$B98),0) -> 0 | T98: =IFERROR(SUMIFS(ALAN!$M$2:$M$14,ALAN!$H$2:$H$14,"ENTRADA",ALAN!$J$2:$J$14,$B98),0) -> 0 | U98: =IFERROR(SUMIFS(ELVIA!$M$2:$M$6,ELVIA!$H$2:$H$6,"ENTRADA",ELVIA!$J$2:$J$6,$B98),0) -> 0 | V98: =IFERROR(SUMIFS(CAJA!$M$2:$M$586,CAJA!$H$2:$H$586,"ENTRADA",CAJA!$J$2:$J$586,$B98),0) -> 0 | W98: =IFERROR(SUMIFS('CAJA TIGRES'!$M$2:$M$139,'CAJA TIGRES'!$H$2:$H$139,"ENTRADA",'CAJA TIGRES'!$J$2:$J$139,$B98),0) -> 0 | X98: =IFERROR(SUMIFS(RESERVA!$M$2:$M$2,RESERVA!$H$2:$H$2,"ENTRADA",RESERVA!$J$2:$J$2,$B98),0) -> 0 | Y98: =SUM(C98:X98) -> 0 | Z98: =Y98 -> 0
B99: TRASPASO VICTOR BANAMEX | C99: =IFERROR(SUMIFS('MGZ121'!$M$2:'MGZ121'!$M$175,'MGZ121'!$H$2:$H$175,"ENTRADA",'MGZ121'!$J$2:$J$175,$B99),0) -> 0 | D99: =IFERROR(SUMIFS('MGZ BBVA'!$M$2:$M$88,'MGZ BBVA'!$H$2:$H$88,"ENTRADA",'MGZ BBVA'!$J$2:$J$88,$B99),0) -> 0 | E99: =IFERROR(SUMIFS('MGZ DOLARES'!$M$2:$M$2,'MGZ DOLARES'!$F$2:$F$2,"ENTRADA",'MGZ DOLARES'!$J$2:$J$2,$B99),0) -> 0 | F99: =IFERROR(SUMIFS('MGZ BAJIO'!$M$2:$M$4,'MGZ BAJIO'!$H$2:$H$4,"ENTRADA",'MGZ BAJIO'!$J$2:$J$4,$B99),0) -> 0 | G99: =IFERROR(SUMIFS('VICTOR BANAMEX'!$M$2:$M$65,'VICTOR BANAMEX'!$H$2:$H$65,"ENTRADA",'VICTOR BANAMEX'!$J$2:$J$65,$B99),0) -> 0 | H99: =IFERROR(SUMIFS('VICTOR BANORTE'!$M$2:$M$9,'VICTOR BANORTE'!$H$2:$H$9,"ENTRADA",'VICTOR BANORTE'!$J$2:$J$9,$B99),0) -> 62260 | I99: =IFERROR(SUMIFS(RODRIGO!$M$2:$M$2,RODRIGO!$H$2:$H$2,"ENTRADA",RODRIGO!$J$2:$J$2,$B99),0) -> 0 | J99: =IFERROR(SUMIFS(MOY!$M$2:$M$12,MOY!$H$2:$H$12,"ENTRADA",MOY!$J$2:$J$12,$B99),0) -> 0 | K99: =IFERROR(SUMIFS('NORMA RUTH'!$M$2:$M$12,'NORMA RUTH'!$H$2:$H$12,"ENTRADA",'NORMA RUTH'!$J$2:$J$12,$B99),0) -> 0 | L99: =IFERROR(SUMIFS(VALERIA!$M$2:$M$10,VALERIA!$H$2:$H$10,"ENTRADA",VALERIA!$J$2:$J$10,$B99),0) -> 0 | M99: =IFERROR(SUMIFS('MANUEL BANAMEX'!$M$2:$M$25,'MANUEL BANAMEX'!$H$2:$H$25,"ENTRADA",'MANUEL BANAMEX'!$J$2:$J$25,$B99),0) -> 0 | N99: =IFERROR(SUMIFS(ROBERTO!$M$2:$M$2,ROBERTO!$H$2:$H$2,"ENTRADA",ROBERTO!$J$2:$J$2,$B99),0) -> 0 | O99: =IFERROR(SUMIFS(JUAN!$M$2:$M$11,JUAN!$H$2:$H$11,"ENTRADA",JUAN!$J$2:$J$11,$B99),0) -> 0 | P99: =IFERROR(SUMIFS('NORMA SANCHEZ'!$M$2:$M$14,'NORMA SANCHEZ'!$H$2:$H$14,"ENTRADA",'NORMA SANCHEZ'!$J$2:$J$14,$B99),0) -> 0 | Q99: =IFERROR(SUMIFS('JOSE CARLOS'!$M$2:$M$16,'JOSE CARLOS'!$H$2:$H$16,"ENTRADA",'JOSE CARLOS'!$J$2:$J$16,$B99),0) -> 0 | R99: =IFERROR(SUMIFS('LUIS ENRIQUE '!$M$2:$M$21,'LUIS ENRIQUE '!$H$2:$H$21,"ENTRADA",'LUIS ENRIQUE '!$J$2:$J$21,$B99),0) -> 0 | S99: =IFERROR(SUMIFS(CESARIA!$M$2:$M$15,CESARIA!$H$2:$H$15,"ENTRADA",CESARIA!$J$2:$J$15,$B99),0) -> 0 | T99: =IFERROR(SUMIFS(ALAN!$M$2:$M$14,ALAN!$H$2:$H$14,"ENTRADA",ALAN!$J$2:$J$14,$B99),0) -> 0 | U99: =IFERROR(SUMIFS(ELVIA!$M$2:$M$6,ELVIA!$H$2:$H$6,"ENTRADA",ELVIA!$J$2:$J$6,$B99),0) -> 0 | V99: =IFERROR(SUMIFS(CAJA!$M$2:$M$586,CAJA!$H$2:$H$586,"ENTRADA",CAJA!$J$2:$J$586,$B99),0) -> 0 | W99: =IFERROR(SUMIFS('CAJA TIGRES'!$M$2:$M$139,'CAJA TIGRES'!$H$2:$H$139,"ENTRADA",'CAJA TIGRES'!$J$2:$J$139,$B99),0) -> 0 | X99: =IFERROR(SUMIFS(RESERVA!$M$2:$M$2,RESERVA!$H$2:$H$2,"ENTRADA",RESERVA!$J$2:$J$2,$B99),0) -> 0 | Y99: =SUM(C99:X99) -> 62260 | Z99: =Y99 -> 62260
B100: TRASPASO VICTOR BANORTE | C100: =IFERROR(SUMIFS('MGZ121'!$M$2:'MGZ121'!$M$175,'MGZ121'!$H$2:$H$175,"ENTRADA",'MGZ121'!$J$2:$J$175,$B100),0) -> 0 | D100: =IFERROR(SUMIFS('MGZ BBVA'!$M$2:$M$88,'MGZ BBVA'!$H$2:$H$88,"ENTRADA",'MGZ BBVA'!$J$2:$J$88,$B100),0) -> 0 | E100: =IFERROR(SUMIFS('MGZ DOLARES'!$M$2:$M$2,'MGZ DOLARES'!$F$2:$F$2,"ENTRADA",'MGZ DOLARES'!$J$2:$J$2,$B100),0) -> 0 | F100: =IFERROR(SUMIFS('MGZ BAJIO'!$M$2:$M$4,'MGZ BAJIO'!$H$2:$H$4,"ENTRADA",'MGZ BAJIO'!$J$2:$J$4,$B100),0) -> 0 | G100: =IFERROR(SUMIFS('VICTOR BANAMEX'!$M$2:$M$65,'VICTOR BANAMEX'!$H$2:$H$65,"ENTRADA",'VICTOR BANAMEX'!$J$2:$J$65,$B100),0) -> 0 | H100: =IFERROR(SUMIFS('VICTOR BANORTE'!$M$2:$M$9,'VICTOR BANORTE'!$H$2:$H$9,"ENTRADA",'VICTOR BANORTE'!$J$2:$J$9,$B100),0) -> 0 | I100: =IFERROR(SUMIFS(RODRIGO!$M$2:$M$2,RODRIGO!$H$2:$H$2,"ENTRADA",RODRIGO!$J$2:$J$2,$B100),0) -> 0 | J100: =IFERROR(SUMIFS(MOY!$M$2:$M$12,MOY!$H$2:$H$12,"ENTRADA",MOY!$J$2:$J$12,$B100),0) -> 0 | K100: =IFERROR(SUMIFS('NORMA RUTH'!$M$2:$M$12,'NORMA RUTH'!$H$2:$H$12,"ENTRADA",'NORMA RUTH'!$J$2:$J$12,$B100),0) -> 0 | L100: =IFERROR(SUMIFS(VALERIA!$M$2:$M$10,VALERIA!$H$2:$H$10,"ENTRADA",VALERIA!$J$2:$J$10,$B100),0) -> 0 | M100: =IFERROR(SUMIFS('MANUEL BANAMEX'!$M$2:$M$25,'MANUEL BANAMEX'!$H$2:$H$25,"ENTRADA",'MANUEL BANAMEX'!$J$2:$J$25,$B100),0) -> 0 | N100: =IFERROR(SUMIFS(ROBERTO!$M$2:$M$2,ROBERTO!$H$2:$H$2,"ENTRADA",ROBERTO!$J$2:$J$2,$B100),0) -> 0 | O100: =IFERROR(SUMIFS(JUAN!$M$2:$M$11,JUAN!$H$2:$H$11,"ENTRADA",JUAN!$J$2:$J$11,$B100),0) -> 0 | P100: =IFERROR(SUMIFS('NORMA SANCHEZ'!$M$2:$M$14,'NORMA SANCHEZ'!$H$2:$H$14,"ENTRADA",'NORMA SANCHEZ'!$J$2:$J$14,$B100),0) -> 0 | Q100: =IFERROR(SUMIFS('JOSE CARLOS'!$M$2:$M$16,'JOSE CARLOS'!$H$2:$H$16,"ENTRADA",'JOSE CARLOS'!$J$2:$J$16,$B100),0) -> 0 | R100: =IFERROR(SUMIFS('LUIS ENRIQUE '!$M$2:$M$21,'LUIS ENRIQUE '!$H$2:$H$21,"ENTRADA",'LUIS ENRIQUE '!$J$2:$J$21,$B100),0) -> 0 | S100: =IFERROR(SUMIFS(CESARIA!$M$2:$M$15,CESARIA!$H$2:$H$15,"ENTRADA",CESARIA!$J$2:$J$15,$B100),0) -> 0 | T100: =IFERROR(SUMIFS(ALAN!$M$2:$M$14,ALAN!$H$2:$H$14,"ENTRADA",ALAN!$J$2:$J$14,$B100),0) -> 0 | U100: =IFERROR(SUMIFS(ELVIA!$M$2:$M$6,ELVIA!$H$2:$H$6,"ENTRADA",ELVIA!$J$2:$J$6,$B100),0) -> 0 | V100: =IFERROR(SUMIFS(CAJA!$M$2:$M$586,CAJA!$H$2:$H$586,"ENTRADA",CAJA!$J$2:$J$586,$B100),0) -> 0 | W100: =IFERROR(SUMIFS('CAJA TIGRES'!$M$2:$M$139,'CAJA TIGRES'!$H$2:$H$139,"ENTRADA",'CAJA TIGRES'!$J$2:$J$139,$B100),0) -> 0 | X100: =IFERROR(SUMIFS(RESERVA!$M$2:$M$2,RESERVA!$H$2:$H$2,"ENTRADA",RESERVA!$J$2:$J$2,$B100),0) -> 0 | Y100: =SUM(C100:X100) -> 0 | Z100: =Y100 -> 0
B101: TRASPASO VICTOR BANCOMER | C101: =IFERROR(SUMIFS('MGZ121'!$M$2:'MGZ121'!$M$175,'MGZ121'!$H$2:$H$175,"ENTRADA",'MGZ121'!$J$2:$J$175,$B101),0) -> 0 | D101: =IFERROR(SUMIFS('MGZ BBVA'!$M$2:$M$88,'MGZ BBVA'!$H$2:$H$88,"ENTRADA",'MGZ BBVA'!$J$2:$J$88,$B101),0) -> 0 | E101: =IFERROR(SUMIFS('MGZ DOLARES'!$M$2:$M$2,'MGZ DOLARES'!$F$2:$F$2,"ENTRADA",'MGZ DOLARES'!$J$2:$J$2,$B101),0) -> 0 | F101: =IFERROR(SUMIFS('MGZ BAJIO'!$M$2:$M$4,'MGZ BAJIO'!$H$2:$H$4,"ENTRADA",'MGZ BAJIO'!$J$2:$J$4,$B101),0) -> 0 | G101: =IFERROR(SUMIFS('VICTOR BANAMEX'!$M$2:$M$65,'VICTOR BANAMEX'!$H$2:$H$65,"ENTRADA",'VICTOR BANAMEX'!$J$2:$J$65,$B101),0) -> 0 | H101: =IFERROR(SUMIFS('VICTOR BANORTE'!$M$2:$M$9,'VICTOR BANORTE'!$H$2:$H$9,"ENTRADA",'VICTOR BANORTE'!$J$2:$J$9,$B101),0) -> 0 | I101: =IFERROR(SUMIFS(RODRIGO!$M$2:$M$2,RODRIGO!$H$2:$H$2,"ENTRADA",RODRIGO!$J$2:$J$2,$B101),0) -> 0 | J101: =IFERROR(SUMIFS(MOY!$M$2:$M$12,MOY!$H$2:$H$12,"ENTRADA",MOY!$J$2:$J$12,$B101),0) -> 0 | K101: =IFERROR(SUMIFS('NORMA RUTH'!$M$2:$M$12,'NORMA RUTH'!$H$2:$H$12,"ENTRADA",'NORMA RUTH'!$J$2:$J$12,$B101),0) -> 0 | L101: =IFERROR(SUMIFS(VALERIA!$M$2:$M$10,VALERIA!$H$2:$H$10,"ENTRADA",VALERIA!$J$2:$J$10,$B101),0) -> 0 | M101: =IFERROR(SUMIFS('MANUEL BANAMEX'!$M$2:$M$25,'MANUEL BANAMEX'!$H$2:$H$25,"ENTRADA",'MANUEL BANAMEX'!$J$2:$J$25,$B101),0) -> 0 | N101: =IFERROR(SUMIFS(ROBERTO!$M$2:$M$2,ROBERTO!$H$2:$H$2,"ENTRADA",ROBERTO!$J$2:$J$2,$B101),0) -> 0 | O101: =IFERROR(SUMIFS(JUAN!$M$2:$M$11,JUAN!$H$2:$H$11,"ENTRADA",JUAN!$J$2:$J$11,$B101),0) -> 0 | P101: =IFERROR(SUMIFS('NORMA SANCHEZ'!$M$2:$M$14,'NORMA SANCHEZ'!$H$2:$H$14,"ENTRADA",'NORMA SANCHEZ'!$J$2:$J$14,$B101),0) -> 0 | Q101: =IFERROR(SUMIFS('JOSE CARLOS'!$M$2:$M$16,'JOSE CARLOS'!$H$2:$H$16,"ENTRADA",'JOSE CARLOS'!$J$2:$J$16,$B101),0) -> 0 | R101: =IFERROR(SUMIFS('LUIS ENRIQUE '!$M$2:$M$21,'LUIS ENRIQUE '!$H$2:$H$21,"ENTRADA",'LUIS ENRIQUE '!$J$2:$J$21,$B101),0) -> 0 | S101: =IFERROR(SUMIFS(CESARIA!$M$2:$M$15,CESARIA!$H$2:$H$15,"ENTRADA",CESARIA!$J$2:$J$15,$B101),0) -> 0 | T101: =IFERROR(SUMIFS(ALAN!$M$2:$M$14,ALAN!$H$2:$H$14,"ENTRADA",ALAN!$J$2:$J$14,$B101),0) -> 0 | U101: =IFERROR(SUMIFS(ELVIA!$M$2:$M$6,ELVIA!$H$2:$H$6,"ENTRADA",ELVIA!$J$2:$J$6,$B101),0) -> 0 | V101: =IFERROR(SUMIFS(CAJA!$M$2:$M$586,CAJA!$H$2:$H$586,"ENTRADA",CAJA!$J$2:$J$586,$B101),0) -> 0 | W101: =IFERROR(SUMIFS('CAJA TIGRES'!$M$2:$M$139,'CAJA TIGRES'!$H$2:$H$139,"ENTRADA",'CAJA TIGRES'!$J$2:$J$139,$B101),0) -> 0 | X101: =IFERROR(SUMIFS(RESERVA!$M$2:$M$2,RESERVA!$H$2:$H$2,"ENTRADA",RESERVA!$J$2:$J$2,$B101),0) -> 0 | Y101: =SUM(C101:X101) -> 0 | Z101: =Y101 -> 0
B102: TRASPASO RODRIGO | C102: =IFERROR(SUMIFS('MGZ121'!$M$2:'MGZ121'!$M$175,'MGZ121'!$H$2:$H$175,"ENTRADA",'MGZ121'!$J$2:$J$175,$B102),0) -> 0 | D102: =IFERROR(SUMIFS('MGZ BBVA'!$M$2:$M$88,'MGZ BBVA'!$H$2:$H$88,"ENTRADA",'MGZ BBVA'!$J$2:$J$88,$B102),0) -> 0 | E102: =IFERROR(SUMIFS('MGZ DOLARES'!$M$2:$M$2,'MGZ DOLARES'!$F$2:$F$2,"ENTRADA",'MGZ DOLARES'!$J$2:$J$2,$B102),0) -> 0 | F102: =IFERROR(SUMIFS('MGZ BAJIO'!$M$2:$M$4,'MGZ BAJIO'!$H$2:$H$4,"ENTRADA",'MGZ BAJIO'!$J$2:$J$4,$B102),0) -> 0 | G102: =IFERROR(SUMIFS('VICTOR BANAMEX'!$M$2:$M$65,'VICTOR BANAMEX'!$H$2:$H$65,"ENTRADA",'VICTOR BANAMEX'!$J$2:$J$65,$B102),0) -> 0 | H102: =IFERROR(SUMIFS('VICTOR BANORTE'!$M$2:$M$9,'VICTOR BANORTE'!$H$2:$H$9,"ENTRADA",'VICTOR BANORTE'!$J$2:$J$9,$B102),0) -> 0 | I102: =IFERROR(SUMIFS(RODRIGO!$M$2:$M$2,RODRIGO!$H$2:$H$2,"ENTRADA",RODRIGO!$J$2:$J$2,$B102),0) -> 0 | J102: =IFERROR(SUMIFS(MOY!$M$2:$M$12,MOY!$H$2:$H$12,"ENTRADA",MOY!$J$2:$J$12,$B102),0) -> 0 | K102: =IFERROR(SUMIFS('NORMA RUTH'!$M$2:$M$12,'NORMA RUTH'!$H$2:$H$12,"ENTRADA",'NORMA RUTH'!$J$2:$J$12,$B102),0) -> 0 | L102: =IFERROR(SUMIFS(VALERIA!$M$2:$M$10,VALERIA!$H$2:$H$10,"ENTRADA",VALERIA!$J$2:$J$10,$B102),0) -> 0 | M102: =IFERROR(SUMIFS('MANUEL BANAMEX'!$M$2:$M$25,'MANUEL BANAMEX'!$H$2:$H$25,"ENTRADA",'MANUEL BANAMEX'!$J$2:$J$25,$B102),0) -> 0 | N102: =IFERROR(SUMIFS(ROBERTO!$M$2:$M$2,ROBERTO!$H$2:$H$2,"ENTRADA",ROBERTO!$J$2:$J$2,$B102),0) -> 0 | O102: =IFERROR(SUMIFS(JUAN!$M$2:$M$11,JUAN!$H$2:$H$11,"ENTRADA",JUAN!$J$2:$J$11,$B102),0) -> 0 | P102: =IFERROR(SUMIFS('NORMA SANCHEZ'!$M$2:$M$14,'NORMA SANCHEZ'!$H$2:$H$14,"ENTRADA",'NORMA SANCHEZ'!$J$2:$J$14,$B102),0) -> 0 | Q102: =IFERROR(SUMIFS('JOSE CARLOS'!$M$2:$M$16,'JOSE CARLOS'!$H$2:$H$16,"ENTRADA",'JOSE CARLOS'!$J$2:$J$16,$B102),0) -> 0 | R102: =IFERROR(SUMIFS('LUIS ENRIQUE '!$M$2:$M$21,'LUIS ENRIQUE '!$H$2:$H$21,"ENTRADA",'LUIS ENRIQUE '!$J$2:$J$21,$B102),0) -> 0 | S102: =IFERROR(SUMIFS(CESARIA!$M$2:$M$15,CESARIA!$H$2:$H$15,"ENTRADA",CESARIA!$J$2:$J$15,$B102),0) -> 0 | T102: =IFERROR(SUMIFS(ALAN!$M$2:$M$14,ALAN!$H$2:$H$14,"ENTRADA",ALAN!$J$2:$J$14,$B102),0) -> 0 | U102: =IFERROR(SUMIFS(ELVIA!$M$2:$M$6,ELVIA!$H$2:$H$6,"ENTRADA",ELVIA!$J$2:$J$6,$B102),0) -> 0 | V102: =IFERROR(SUMIFS(CAJA!$M$2:$M$586,CAJA!$H$2:$H$586,"ENTRADA",CAJA!$J$2:$J$586,$B102),0) -> 0 | W102: =IFERROR(SUMIFS('CAJA TIGRES'!$M$2:$M$139,'CAJA TIGRES'!$H$2:$H$139,"ENTRADA",'CAJA TIGRES'!$J$2:$J$139,$B102),0) -> 0 | X102: =IFERROR(SUMIFS(RESERVA!$M$2:$M$2,RESERVA!$H$2:$H$2,"ENTRADA",RESERVA!$J$2:$J$2,$B102),0) -> 0 | Y102: =SUM(C102:X102) -> 0 | Z102: =Y102 -> 0
B103: TRASPASO MOY | C103: =IFERROR(SUMIFS('MGZ121'!$M$2:'MGZ121'!$M$175,'MGZ121'!$H$2:$H$175,"ENTRADA",'MGZ121'!$J$2:$J$175,$B103),0) -> 0 | D103: =IFERROR(SUMIFS('MGZ BBVA'!$M$2:$M$88,'MGZ BBVA'!$H$2:$H$88,"ENTRADA",'MGZ BBVA'!$J$2:$J$88,$B103),0) -> 0 | E103: =IFERROR(SUMIFS('MGZ DOLARES'!$M$2:$M$2,'MGZ DOLARES'!$F$2:$F$2,"ENTRADA",'MGZ DOLARES'!$J$2:$J$2,$B103),0) -> 0 | F103: =IFERROR(SUMIFS('MGZ BAJIO'!$M$2:$M$4,'MGZ BAJIO'!$H$2:$H$4,"ENTRADA",'MGZ BAJIO'!$J$2:$J$4,$B103),0) -> 0 | G103: =IFERROR(SUMIFS('VICTOR BANAMEX'!$M$2:$M$65,'VICTOR BANAMEX'!$H$2:$H$65,"ENTRADA",'VICTOR BANAMEX'!$J$2:$J$65,$B103),0) -> 0 | H103: =IFERROR(SUMIFS('VICTOR BANORTE'!$M$2:$M$9,'VICTOR BANORTE'!$H$2:$H$9,"ENTRADA",'VICTOR BANORTE'!$J$2:$J$9,$B103),0) -> 0 | I103: =IFERROR(SUMIFS(RODRIGO!$M$2:$M$2,RODRIGO!$H$2:$H$2,"ENTRADA",RODRIGO!$J$2:$J$2,$B103),0) -> 0 | J103: =IFERROR(SUMIFS(MOY!$M$2:$M$12,MOY!$H$2:$H$12,"ENTRADA",MOY!$J$2:$J$12,$B103),0) -> 0 | K103: =IFERROR(SUMIFS('NORMA RUTH'!$M$2:$M$12,'NORMA RUTH'!$H$2:$H$12,"ENTRADA",'NORMA RUTH'!$J$2:$J$12,$B103),0) -> 0 | L103: =IFERROR(SUMIFS(VALERIA!$M$2:$M$10,VALERIA!$H$2:$H$10,"ENTRADA",VALERIA!$J$2:$J$10,$B103),0) -> 0 | M103: =IFERROR(SUMIFS('MANUEL BANAMEX'!$M$2:$M$25,'MANUEL BANAMEX'!$H$2:$H$25,"ENTRADA",'MANUEL BANAMEX'!$J$2:$J$25,$B103),0) -> 0 | N103: =IFERROR(SUMIFS(ROBERTO!$M$2:$M$2,ROBERTO!$H$2:$H$2,"ENTRADA",ROBERTO!$J$2:$J$2,$B103),0) -> 0 | O103: =IFERROR(SUMIFS(JUAN!$M$2:$M$11,JUAN!$H$2:$H$11,"ENTRADA",JUAN!$J$2:$J$11,$B103),0) -> 0 | P103: =IFERROR(SUMIFS('NORMA SANCHEZ'!$M$2:$M$14,'NORMA SANCHEZ'!$H$2:$H$14,"ENTRADA",'NORMA SANCHEZ'!$J$2:$J$14,$B103),0) -> 0 | Q103: =IFERROR(SUMIFS('JOSE CARLOS'!$M$2:$M$16,'JOSE CARLOS'!$H$2:$H$16,"ENTRADA",'JOSE CARLOS'!$J$2:$J$16,$B103),0) -> 0 | R103: =IFERROR(SUMIFS('LUIS ENRIQUE '!$M$2:$M$21,'LUIS ENRIQUE '!$H$2:$H$21,"ENTRADA",'LUIS ENRIQUE '!$J$2:$J$21,$B103),0) -> 0 | S103: =IFERROR(SUMIFS(CESARIA!$M$2:$M$15,CESARIA!$H$2:$H$15,"ENTRADA",CESARIA!$J$2:$J$15,$B103),0) -> 0 | T103: =IFERROR(SUMIFS(ALAN!$M$2:$M$14,ALAN!$H$2:$H$14,"ENTRADA",ALAN!$J$2:$J$14,$B103),0) -> 0 | U103: =IFERROR(SUMIFS(ELVIA!$M$2:$M$6,ELVIA!$H$2:$H$6,"ENTRADA",ELVIA!$J$2:$J$6,$B103),0) -> 0 | V103: =IFERROR(SUMIFS(CAJA!$M$2:$M$586,CAJA!$H$2:$H$586,"ENTRADA",CAJA!$J$2:$J$586,$B103),0) -> 0 | W103: =IFERROR(SUMIFS('CAJA TIGRES'!$M$2:$M$139,'CAJA TIGRES'!$H$2:$H$139,"ENTRADA",'CAJA TIGRES'!$J$2:$J$139,$B103),0) -> 0 | X103: =IFERROR(SUMIFS(RESERVA!$M$2:$M$2,RESERVA!$H$2:$H$2,"ENTRADA",RESERVA!$J$2:$J$2,$B103),0) -> 0 | Y103: =SUM(C103:X103) -> 0 | Z103: =Y103 -> 0
B104: TRASPASO NORMA RUTH | C104: =IFERROR(SUMIFS('MGZ121'!$M$2:'MGZ121'!$M$175,'MGZ121'!$H$2:$H$175,"ENTRADA",'MGZ121'!$J$2:$J$175,$B104),0) -> 0 | D104: =IFERROR(SUMIFS('MGZ BBVA'!$M$2:$M$88,'MGZ BBVA'!$H$2:$H$88,"ENTRADA",'MGZ BBVA'!$J$2:$J$88,$B104),0) -> 0 | E104: =IFERROR(SUMIFS('MGZ DOLARES'!$M$2:$M$2,'MGZ DOLARES'!$F$2:$F$2,"ENTRADA",'MGZ DOLARES'!$J$2:$J$2,$B104),0) -> 0 | F104: =IFERROR(SUMIFS('MGZ BAJIO'!$M$2:$M$4,'MGZ BAJIO'!$H$2:$H$4,"ENTRADA",'MGZ BAJIO'!$J$2:$J$4,$B104),0) -> 0 | G104: =IFERROR(SUMIFS('VICTOR BANAMEX'!$M$2:$M$65,'VICTOR BANAMEX'!$H$2:$H$65,"ENTRADA",'VICTOR BANAMEX'!$J$2:$J$65,$B104),0) -> 0 | H104: =IFERROR(SUMIFS('VICTOR BANORTE'!$M$2:$M$9,'VICTOR BANORTE'!$H$2:$H$9,"ENTRADA",'VICTOR BANORTE'!$J$2:$J$9,$B104),0) -> 0 | I104: =IFERROR(SUMIFS(RODRIGO!$M$2:$M$2,RODRIGO!$H$2:$H$2,"ENTRADA",RODRIGO!$J$2:$J$2,$B104),0) -> 0 | J104: =IFERROR(SUMIFS(MOY!$M$2:$M$12,MOY!$H$2:$H$12,"ENTRADA",MOY!$J$2:$J$12,$B104),0) -> 0 | K104: =IFERROR(SUMIFS('NORMA RUTH'!$M$2:$M$12,'NORMA RUTH'!$H$2:$H$12,"ENTRADA",'NORMA RUTH'!$J$2:$J$12,$B104),0) -> 0 | L104: =IFERROR(SUMIFS(VALERIA!$M$2:$M$10,VALERIA!$H$2:$H$10,"ENTRADA",VALERIA!$J$2:$J$10,$B104),0) -> 0 | M104: =IFERROR(SUMIFS('MANUEL BANAMEX'!$M$2:$M$25,'MANUEL BANAMEX'!$H$2:$H$25,"ENTRADA",'MANUEL BANAMEX'!$J$2:$J$25,$B104),0) -> 0 | N104: =IFERROR(SUMIFS(ROBERTO!$M$2:$M$2,ROBERTO!$H$2:$H$2,"ENTRADA",ROBERTO!$J$2:$J$2,$B104),0) -> 0 | O104: =IFERROR(SUMIFS(JUAN!$M$2:$M$11,JUAN!$H$2:$H$11,"ENTRADA",JUAN!$J$2:$J$11,$B104),0) -> 0 | P104: =IFERROR(SUMIFS('NORMA SANCHEZ'!$M$2:$M$14,'NORMA SANCHEZ'!$H$2:$H$14,"ENTRADA",'NORMA SANCHEZ'!$J$2:$J$14,$B104),0) -> 0 | Q104: =IFERROR(SUMIFS('JOSE CARLOS'!$M$2:$M$16,'JOSE CARLOS'!$H$2:$H$16,"ENTRADA",'JOSE CARLOS'!$J$2:$J$16,$B104),0) -> 0 | R104: =IFERROR(SUMIFS('LUIS ENRIQUE '!$M$2:$M$21,'LUIS ENRIQUE '!$H$2:$H$21,"ENTRADA",'LUIS ENRIQUE '!$J$2:$J$21,$B104),0) -> 0 | S104: =IFERROR(SUMIFS(CESARIA!$M$2:$M$15,CESARIA!$H$2:$H$15,"ENTRADA",CESARIA!$J$2:$J$15,$B104),0) -> 0 | T104: =IFERROR(SUMIFS(ALAN!$M$2:$M$14,ALAN!$H$2:$H$14,"ENTRADA",ALAN!$J$2:$J$14,$B104),0) -> 0 | U104: =IFERROR(SUMIFS(ELVIA!$M$2:$M$6,ELVIA!$H$2:$H$6,"ENTRADA",ELVIA!$J$2:$J$6,$B104),0) -> 0 | V104: =IFERROR(SUMIFS(CAJA!$M$2:$M$586,CAJA!$H$2:$H$586,"ENTRADA",CAJA!$J$2:$J$586,$B104),0) -> 69752.28 | W104: =IFERROR(SUMIFS('CAJA TIGRES'!$M$2:$M$139,'CAJA TIGRES'!$H$2:$H$139,"ENTRADA",'CAJA TIGRES'!$J$2:$J$139,$B104),0) -> 0 | X104: =IFERROR(SUMIFS(RESERVA!$M$2:$M$2,RESERVA!$H$2:$H$2,"ENTRADA",RESERVA!$J$2:$J$2,$B104),0) -> 0 | Y104: =SUM(C104:X104) -> 69752.28 | Z104: =Y104 -> 69752.28
...

Sheet FEB25
B1: FEBRERO
B2: CONCEPTOS | C2: MGZ121 | D2: MGZ BBVA | E2: MGZ DOLARES | F2: MGZ BAJIO | G2: VICTOR BANAMEX | H2: VICTOR BANORTE | I2: RODRIGO | J2: MOY | K2: NORMA RUTH | L2: VALERIA | M2: MANUEL BANAMEX | N2: ROBERTO | O2: JUAN | P2: NORMA SANCHEZ | Q2: JOSE CARLOS | R2: LUIS ENRIQUE | S2: CESARIA | T2: ALAN | U2: ELVIA | V2: CAJA | W2: CAJA TIGRES | X2: RESERVA | Y2: TOTALES | Z2: ACUMULADO
B3: ENTRADAS
B4: INGRESOS
A5: 11.1 | B5: VENTA PIÑAS | C5: =IFERROR(SUMIFS('MGZ121'!$M$176:'MGZ121'!$M$312,'MGZ121'!$H$176:$H$312,"ENTRADA",'MGZ121'!$J$176:$J$312,$B5),0) -> 5483691 | D5: =IFERROR(SUMIFS('MGZ BBVA'!$M$89:$M$189,'MGZ BBVA'!$H$89:$H$189,"ENTRADA",'MGZ BBVA'!$J$89:$J$189,$B5),0) -> 1831830 | E5: =IFERROR(SUMIFS('MGZ DOLARES'!$M$2:$M$2,'MGZ DOLARES'!$F$2:$F$2,"ENTRADA",'MGZ DOLARES'!$J$2:$J$2,$B5),0) -> 0 | F5: =IFERROR(SUMIFS('MGZ BAJIO'!$M$5:$M$6,'MGZ BAJIO'!$H$5:$H$6,"ENTRADA",'MGZ BAJIO'!$J$5:$J$6,$B5),0) -> 0 | G5: =IFERROR(SUMIFS('VICTOR BANAMEX'!$M$66:$M$106,'VICTOR BANAMEX'!$H$66:$H$106,"ENTRADA",'VICTOR BANAMEX'!$J$66:$J$106,$B5),0) -> 0 | H5: =IFERROR(SUMIFS('VICTOR BANORTE'!$M$10:$M$28,'VICTOR BANORTE'!$H$10:$H$28,"ENTRADA",'VICTOR BANORTE'!$J$10:$J$28,$B5),0) -> 0 | I5: =IFERROR(SUMIFS(RODRIGO!$M$2:$M$2,RODRIGO!$H$2:$H$2,"ENTRADA",RODRIGO!$J$2:$J$2,$B5),0) -> 0 | J5: =IFERROR(SUMIFS(MOY!$M$13:$M$21,MOY!$H$13:$H$21,"ENTRADA",MOY!$J$13:$J$21,$B5),0) -> 0 | K5: =IFERROR(SUMIFS('NORMA RUTH'!$M$13:$M$16,'NORMA RUTH'!$H$13:$H$16,"ENTRADA",'NORMA RUTH'!$J$13:$J$16,$B5),0) -> 0 | L5: =IFERROR(SUMIFS(VALERIA!$M$11:$M$13,VALERIA!$H$11:$H$13,"ENTRADA",VALERIA!$J$11:$J$13,$B5),0) -> 0 | M5: =IFERROR(SUMIFS('MANUEL BANAMEX'!$M$26:$M$29,'MANUEL BANAMEX'!$H$26:$H$29,"ENTRADA",'MANUEL BANAMEX'!$J$26:$J$29,$B5),0) -> 0 | N5: =IFERROR(SUMIFS(ROBERTO!$M$2:$M$2,ROBERTO!$H$2:$H$2,"ENTRADA",ROBERTO!$J$2:$J$2,$B5),0) -> 0 | O5: =IFERROR(SUMIFS(JUAN!$M$12:$M$19,JUAN!$H$12:$H$19,"ENTRADA",JUAN!$J$12:$J$19,$B5),0) -> 0 | P5: =IFERROR(SUMIFS('NORMA SANCHEZ'!$M$15:$M$18,'NORMA SANCHEZ'!$H$15:$H$18,"ENTRADA",'NORMA SANCHEZ'!$J$15:$J$18,$B5),0) -> 0 | Q5: =IFERROR(SUMIFS('JOSE CARLOS'!$M$17:$M$23,'JOSE CARLOS'!$H$17:$H$23,"ENTRADA",'JOSE CARLOS'!$J$17:$J$23,$B5),0) -> 0 | R5: =IFERROR(SUMIFS('LUIS ENRIQUE '!$M$22:$M$29,'LUIS ENRIQUE '!$H$22:$H$29,"ENTRADA",'LUIS ENRIQUE '!$J$22:$J$29,$B5),0) -> 0 | S5: =IFERROR(SUMIFS(CESARIA!$M$16:$M$18,CESARIA!$H$16:$H$18,"ENTRADA",CESARIA!$J$16:$J$18,$B5),0) -> 0 | T5: =IFERROR(SUMIFS(ALAN!$M$15:$M$25,ALAN!$H$15:$H$25,"ENTRADA",ALAN!$J$15:$J$25,$B5),0) -> 0 | U5: =IFERROR(SUMIFS(ELVIA!$M$7:$M$12,ELVIA!$H$7:$H$12,"ENTRADA",ELVIA!$J$7:$J$12,$B5),0) -> 0 | V5: =IFERROR(SUMIFS(CAJA!$M$587:$M$1165,CAJA!$H$587:$H$1165,"ENTRADA",CAJA!$J$587:$J$1165,$B5),0) -> 541315 | W5: =IFERROR(SUMIFS('CAJA TIGRES'!$M$140:$M$302,'CAJA TIGRES'!$H$140:$H$302,"ENTRADA",'CAJA TIGRES'!$J$140:$J$302,$B5),0) -> 0 | X5: =IFERROR(SUMIFS(RESERVA!$M$2:$M$2,RESERVA!$H$2:$H$2,"ENTRADA",RESERVA!$J$2:$J$2,$B5),0) -> 0 | Y5: =SUM(C5:X5) -> 7856836 | Z5: =Y5+'ENE25'!Z5 -> 17883638
A6: 11.2 | B6: VENTA GANADO | C6: =IFERROR(SUMIFS('MGZ121'!$M$176:'MGZ121'!$M$312,'MGZ121'!$H$176:$H$312,"ENTRADA",'MGZ121'!$J$176:$J$312,$B6),0) -> 0 | D6: =IFERROR(SUMIFS('MGZ BBVA'!$M$89:$M$189,'MGZ BBVA'!$H$89:$H$189,"ENTRADA",'MGZ BBVA'!$J$89:$J$189,$B6),0) -> 0 | E6: =IFERROR(SUMIFS('MGZ DOLARES'!$M$2:$M$2,'MGZ DOLARES'!$F$2:$F$2,"ENTRADA",'MGZ DOLARES'!$J$2:$J$2,$B6),0) -> 0 | F6: =IFERROR(SUMIFS('MGZ BAJIO'!$M$5:$M$6,'MGZ BAJIO'!$H$5:$H$6,"ENTRADA",'MGZ BAJIO'!$J$5:$J$6,$B6),0) -> 0 | G6: =IFERROR(SUMIFS('VICTOR BANAMEX'!$M$66:$M$106,'VICTOR BANAMEX'!$H$66:$H$106,"ENTRADA",'VICTOR BANAMEX'!$J$66:$J$106,$B6),0) -> 50000 | H6: =IFERROR(SUMIFS('VICTOR BANORTE'!$M$10:$M$28,'VICTOR BANORTE'!$H$10:$H$28,"ENTRADA",'VICTOR BANORTE'!$J$10:$J$28,$B6),0) -> 0 | I6: =IFERROR(SUMIFS(RODRIGO!$M$2:$M$2,RODRIGO!$H$2:$H$2,"ENTRADA",RODRIGO!$J$2:$J$2,$B6),0) -> 0 | J6: =IFERROR(SUMIFS(MOY!$M$13:$M$21,MOY!$H$13:$H$21,"ENTRADA",MOY!$J$13:$J$21,$B6),0) -> 0 | K6: =IFERROR(SUMIFS('NORMA RUTH'!$M$13:$M$16,'NORMA RUTH'!$H$13:$H$16,"ENTRADA",'NORMA RUTH'!$J$13:$J$16,$B6),0) -> 0 | L6: =IFERROR(SUMIFS(VALERIA!$M$11:$M$13,VALERIA!$H$11:$H$13,"ENTRADA",VALERIA!$J$11:$J$13,$B6),0) -> 0 | M6: =IFERROR(SUMIFS('MANUEL BANAMEX'!$M$26:$M$29,'MANUEL BANAMEX'!$H$26:$H$29,"ENTRADA",'MANUEL BANAMEX'!$J$26:$J$29,$B6),0) -> 0 | N6: =IFERROR(SUMIFS(ROBERTO!$M$2:$M$2,ROBERTO!$H$2:$H$2,"ENTRADA",ROBERTO!$J$2:$J$2,$B6),0) -> 0 | O6: =IFERROR(SUMIFS(JUAN!$M$12:$M$19,JUAN!$H$12:$H$19,"ENTRADA",JUAN!$J$12:$J$19,$B6),0) -> 0 | P6: =IFERROR(SUMIFS('NORMA SANCHEZ'!$M$15:$M$18,'NORMA SANCHEZ'!$H$15:$H$18,"ENTRADA",'NORMA SANCHEZ'!$J$15:$J$18,$B6),0) -> 0 | Q6: =IFERROR(SUMIFS('JOSE CARLOS'!$M$17:$M$23,'JOSE CARLOS'!$H$17:$H$23,"ENTRADA",'JOSE CARLOS'!$J$17:$J$23,$B6),0) -> 0 | R6: =IFERROR(SUMIFS('LUIS ENRIQUE '!$M$22:$M$29,'LUIS ENRIQUE '!$H$22:$H$29,"ENTRADA",'LUIS ENRIQUE '!$J$22:$J$29,$B6),0) -> 0 | S6: =IFERROR(SUMIFS(CESARIA!$M$16:$M$18,CESARIA!$H$16:$H$18,"ENTRADA",CESARIA!$J$16:$J$18,$B6),0) -> 0 | T6: =IFERROR(SUMIFS(ALAN!$M$15:$M$25,ALAN!$H$15:$H$25,"ENTRADA",ALAN!$J$15:$J$25,$B6),0) -> 0 | U6: =IFERROR(SUMIFS(ELVIA!$M$7:$M$12,ELVIA!$H$7:$H$12,"ENTRADA",ELVIA!$J$7:$J$12,$B6),0) -> 0 | V6: =IFERROR(SUMIFS(CAJA!$M$587:$M$1165,CAJA!$H$587:$H$1165,"ENTRADA",CAJA!$J$587:$J$1165,$B6),0) -> 503995 | W6: =IFERROR(SUMIFS('CAJA TIGRES'!$M$140:$M$302,'CAJA TIGRES'!$H$140:$H$302,"ENTRADA",'CAJA TIGRES'!$J$140:$J$302,$B6),0) -> 0 | X6: =IFERROR(SUMIFS(RESERVA!$M$2:$M$2,RESERVA!$H$2:$H$2,"ENTRADA",RESERVA!$J$2:$J$2,$B6),0) -> 0 | Y6: =SUM(C6:X6) -> 553995 | Z6: =Y6+'ENE25'!Z6 -> 739970
